Workbook

Sheet Cover
A1: BRAND LLC: 5 Year Financial Model
A2: US launch of hybrid active optical HDMI cables on Amazon, then eBay and Walmart, B2B installers, a DTC site, Amazon Canada and a pro line
A3: Build date: October 8, 2026. Workbook: output/03_Financial_Model_5Y.xlsx. Generator: build/build_model.py.
A5: How to use
A6: 1. Change the three selectors on the Assumptions tab: Scenario (1 Low, 2 Medium, 3 High), DutyScenario (1 Copper, 2 Fiber, 3 Stress), FXRate (KRW per USD).
A7: 2. Every other tab reads the Active column on Assumptions, so one selector drives every sheet. The Scenario Summary tab shows all three scenarios side by side without changing the selector.
A8: 3. Edit yellow cells only. Black cells are formulas. Green cells are links to another sheet.
A9: 4. Months are model months: Month 1 is the first month with inventory live on Amazon (assumed early 2027). Year 1 is Months 1 to 12.
A10: 5. Months 1 to 18 reproduce the August 2026 Amazon model. Year 2 drivers (ocean freight, fixed cost step up, compliance, FBA fee inflation) start in Month 19.
A11: 6. Recalculate after edits (Excel does this automatically). The build script recalculates with LibreOffice and checks that there are no formula errors.
A13: Legend
A14: Input: yellow fill with blue text
... A19: Tabs in order
A20: Cover | B20: this page
A21: Assumptions | B21: Low, Medium, High side by side, the Active column and the three selectors
A22: FX | B22: KRW per USD input, the three FX scenarios, conversions of capital, the August deal and profit repatriation
A23: SKU Unit Economics | B23: per SKU cost build (FOB, freight, duty by scenario, fees, FBA, referral, ads, returns, net) and the three cost bases
A24: Landed Cost & Tariff Scenarios | B24: duty table, landed COGS % build for the active scenario, waterfall data
A25: Monthly PL Y1 Y2 | B25: Months 1 to 24, Amazon US plus the Year 2 channels, 18 month block
A26: Annual PL Y1 to Y5 | B26: Years 1 to 5 by channel with the check rows to the monthly tab
A27: Cash Flow and Working Capital | B27: inventory purchases, in transit stock, payout lag, cash balance, peak need, runway, funding gap
A28: Funding and Breakeven | B28: funding plan, Day 90 and Month 12 gates with PASS, REVIEW or KILL, Plan B summary
A29: Sensitivity | B29: one way sensitivity of 18 month net and Year 5 net, tornado data
A30: KPI Dashboard | B30: KPI table and the five charts
A31: Levers | B31: the twelve levers mapped to the assumption each one moves
... A33: Plan B | B33: B2B installer distribution plus continued Korea wholesale if Amazon fails
A35: Basis tags: Evidence based = brief section 1, the August deal, the August model or a verified regulatory fact. Management estimate = everything else.
A36: Largest unverified assumption: the factory cost. At the Alibaba benchmark FOB ($17 to $22) the hero SKU loses money at $44.99. See SKU Unit Economics.

Sheet Assumptions
A1: Assumptions
A2: Low, Medium and High side by side. The Active column (F) is what every other sheet reads. Edit yellow cells only.
A3: Scenario selector (1 Low, 2 Medium, 3 High) | C3: 2 | D3: =CHOOSE(Scenario,"Low","Medium","High") -> Medium | E3: active scenario name
A4: Duty scenario selector (1 Copper, 2 Fiber, 3 Stress) | C4: 1 | D4: =CHOOSE(DutyScenario,"Copper","Fiber","Stress") -> Copper | E4: active duty scenario name
A5: FX rate, KRW per USD (scenarios 1,300 / 1,430 / 1,550) | C5: 1430 | D5: ="FX "&TEXT(FXRate,"#,##0")&" KRW per USD" -> FX 1,430 KRW per USD
A7: Driver | B7: Unit | C7: Low | D7: Medium | E7: High | F7: Active | G7: Basis | H7: Note
A9: Eighteen month block (August 2026 Amazon model; Months 1 to 18 reproduce it)
A10: ASP Years 1 and 2 | B10: $ | C10: 38 | D10: 42 | E10: 43 | F10: =INDEX($C10:$E10,1,Scenario) -> 42 | G10: Evidence based | H10: August model Medium $42; Low and High calibrated per spec 2.3
A11: Landed COGS % of revenue, base (copper duty, air then ocean) | B11: % | C11: 0.43 | D11: 0.38 | E11: 0.32 | F11: =INDEX($C11:$E11,1,Scenario) -> 0.38 | G11: Evidence based | H11: August model 38% pending the customs ruling; Low 43%; High 32% assumes fiber ruling, ocean and volume pricing
A12: Returns % Year 1 | B12: % | C12: 0.04 | D12: 0.03 | E12: 0.025 | F12: =INDEX($C12:$E12,1,Scenario) -> 0.03 | G12: Evidence based | H12: August model 3%
A13: Ad spend % Months 1 to 3 | B13: % | C13: 0.37 | D13: 0.3 | E13: 0.26 | F13: =INDEX($C13:$E13,1,Scenario) -> 0.3 | G13: Evidence based | H13: August model 30%; Low plus 7 points; High minus 4 points
A14: Ad spend % Months 4 to 6 | B14: % | C14: 0.29 | D14: 0.22 | E14: 0.18 | F14: =INDEX($C14:$E14,1,Scenario) -> 0.22 | G14: Evidence based
A15: Ad spend % Months 7 to 12 | B15: % | C15: 0.22 | D15: 0.15 | E15: 0.11 | F15: =INDEX($C15:$E15,1,Scenario) -> 0.15 | G15: Evidence based
A16: Ad spend % Months 13 to 18 | B16: % | C16: 0.18 | D16: 0.11 | E16: 0.08 | F16: =INDEX($C16:$E16,1,Scenario) -> 0.11 | G16: Evidence based | H16: August model 11% for Months 13 to 18; Low plus 7 points; High minus 3 points (the 8% floor)
A17: Fixed costs per month Year 1 (software, insurance, misc), Months 1 to 18 | B17: $ | C17: 850 | D17: 850 | E17: 850 | F17: =INDEX($C17:$E17,1,Scenario) -> 850 | G17: Evidence based | H17: August model
A18: Unit ramp multiplier on the Medium ramp, Months 1 to 18 | B18: x | C18: 0.6 | D18: 1 | E18: 1.55 | F18: =INDEX($C18:$E18,1,Scenario) -> 1 | G18: Management estimate | H18: Low 0.60 and High 1.55 per the build spec; Medium ramp is the August deck
A19: Amazon referral fee % | B19: % | C19: 0.15 | D19: 0.15 | E19: 0.15 | F19: =INDEX($C19:$E19,1,Scenario) -> 0.15 | G19: Evidence based | H19: August model; same in every scenario
A20: FBA fulfillment fee per unit, Year 1 (hero basis) | B20: $ | C20: 5.5 | D20: 5.5 | E20: 5.5 | F20: =INDEX($C20:$E20,1,Scenario) -> 5.5 | G20: Evidence based | H20: August model; same in every scenario
A21: Storage and inbound % of revenue | B21: % | C21: 0.02 | D21: 0.02 | E21: 0.02 | F21: =INDEX($C21:$E21,1,Scenario) -> 0.02 | G21: Evidence based | H21: August model; same in every scenario
A22: Professional seller fee per month | B22: $ | C22: 39.99 | D22: 39.99 | E22: 39.99 | F22: =INDEX($C22:$E22,1,Scenario) -> 39.99 | G22: Evidence based | H22: August model; same in every scenario
A23: One time launch costs in Month 1 | B23: $ | C23: 9500 | D23: 9500 | E23: 9500 | F23: =INDEX($C23:$E23,1,Scenario) -> 9500 | G23: Evidence based | H23: August model; same in every scenario
A25: Year 2 to Year 5 drivers (Year 2 changes start in Month 19, after the August horizon)
A26: Year 2 driver start month (ocean landed cost, fixed cost step up, compliance, FBA fee inflation, Year 2 returns and the Months 19 to 24 ad rate begin here) | B26: month | C26: 19 | D26: 19 | E26: 19 | F26: =INDEX($C26:$E26,1,Scenario) -> 19 | G26: Evidence based | H26: Month 19 is the first month after the August 18 month horizon; the compliance charge is spread over the months from here to Month 24
A27: Ad spend % Months 19 to 24 | B27: % | C27: 0.18 | D27: 0.11 | E27: 0.095 | F27: =INDEX($C27:$E27,1,Scenario) -> 0.11 | G27: Management estimate | H27: Low and Medium carry the Months 13 to 18 rate; High steps to its Year 3 rate so the Year 2 ad spend across all channels stays above the 8% floor (8.1% blended; at 8% Amazon only it diluted to 7.4%)
A28: Months 19 to 24 units added per month on top of Month 18 | B28: units | C28: 0 | D28: 100 | E28: 160 | F28: =INDEX($C28:$E28,1,Scenario) -> 100 | G28: Management estimate | H28: Low flat at Month 18
A29: Lost quarter factor (listing suppression or account health event) | B29: x | C29: 0.1 | D29: 1 | E29: 1 | F29: =INDEX($C29:$E29,1,Scenario) -> 1 | G29: Management estimate | H29: Low case only: units at 10% of trend for three months
A30: Lost quarter start month (three months) | B30: month | C30: 19 | D30: 99 | E30: 99 | F30: =INDEX($C30:$E30,1,Scenario) -> 99 | G30: Management estimate | H30: Spec 2.5 said Months 15 to 17; moved to Months 19 to 21 so the Low 18 month block reproduces the August Low case, per the brief
A31: Returns % Year 2 onward (from Month 19) | B31: % | C31: 0.04 | D31: 0.025 | E31: 0.02 | F31: =INDEX($C31:$E31,1,Scenario) -> 0.025 | G31: Management estimate | H31: never below 2%
A32: FBA fee inflation per year from Year 2 | B32: % | C32: 0.03 | D32: 0.03 | E32: 0.03 | F32: =INDEX($C32:$E32,1,Scenario) -> 0.03 | G32: Management estimate
A33: Landed COGS % change vs base, Year 2 (from Month 19) | B33: pts | C33: 0 | D33: -0.015 | E33: -0.01 | F33: =INDEX($C33:$E33,1,Scenario) -> -0.015 | G33: Management estimate | H33: ocean freight and volume
A34: Landed COGS % change vs base, Year 3 | B34: pts | C34: 0 | D34: -0.015 | E34: -0.015 | F34: =INDEX($C34:$E34,1,Scenario) -> -0.015 | G34: Management estimate | H34: spec starting value Medium minus 2.5; held at the Year 2 benefit
A35: Landed COGS % change vs base, Year 4 | B35: pts | C35: 0 | D35: -0.01 | E35: -0.01 | F35: =INDEX($C35:$E35,1,Scenario) -> -0.01 | G35: Management estimate | H35: spec starting value Medium minus 2.0; creep back starts in Year 4 so the Medium net margin compresses at least 1 point from Year 3 to Year 4
A36: Landed COGS % change vs base, Year 5 | B36: pts | C36: 0 | D36: -0.005 | E36: 0 | F36: =INDEX($C36:$E36,1,Scenario) -> -0.005 | G36: Management estimate | H36: creep back toward base (factory price increases, freight volatility); spec starting values minus 1.5 and minus 0.5
A37: Amazon US unit growth Year 3 | B37: % | C37: 0.1 | D37: 0.3 | E37: 0.35 | F37: =INDEX($C37:$E37,1,Scenario) -> 0.3 | G37: Management estimate | H37: spec starting values Low 5, Medium 30, High 35; Low raised 5 points (within the ±5 bound) so Year 5 lands in the 0.7 to 1.2M band
A38: Amazon US unit growth Year 4 | B38: % | C38: 0.08 | D38: 0.2 | E38: 0.25 | F38: =INDEX($C38:$E38,1,Scenario) -> 0.2 | G38: Management estimate | H38: Low raised 5 points within bound
A39: Amazon US unit growth Year 5 | B39: % | C39: 0.05 | D39: 0.12 | E39: 0.15 | F39: =INDEX($C39:$E39,1,Scenario) -> 0.12 | G39: Management estimate | H39: Low raised 5 points within bound
A40: ASP change per year from Year 3 (price competition) | B40: % | C40: -0.04 | D40: -0.04 | E40: -0.03 | F40: =INDEX($C40:$E40,1,Scenario) -> -0.04 | G40: Management estimate | H40: spec starting values minus 3, minus 2, minus 1.5 per year; deepened so contribution margin falls at least 1 point a year overall and Year 5 net lands in band
A41: Roadmap SKU mix uplift to ASP in Year 3 (HDMI 2.2 16K, DP 2.1, USB4 AOC) | B41: % | C41: 0 | D41: 0.03 | E41: 0.03 | F41: =INDEX($C41:$E41,1,Scenario) -> 0.03 | G41: Management estimate | H41: Low has no capital for roadmap SKUs
A42: Ad spend % Year 3 | B42: % | C42: 0.13 | D42: 0.115 | E42: 0.095 | F42: =INDEX($C42:$E42,1,Scenario) -> 0.115 | G42: Management estimate | H42: spec starting values 12, 9.5, 9.0; raised so competition compresses margin at least 1 point a year; never below 8%
A43: Ad spend % Year 4 | B43: % | C43: 0.135 | D43: 0.115 | E43: 0.095 | F43: =INDEX($C43:$E43,1,Scenario) -> 0.115 | G43: Management estimate | H43: spec starting values 12, 9.0, 8.5; see Year 3 note
A44: Ad spend % Year 5 | B44: % | C44: 0.165 | D44: 0.115 | E44: 0.095 | F44: =INDEX($C44:$E44,1,Scenario) -> 0.115 | G44: Management estimate | H44: spec starting values 12, 8.5, 8.0; see Year 3 note; never below 8%; Low 16.5% so the Low Year 5 net is at or below zero (the listing buys rank it cannot earn from reviews)
... A46: Fixed costs per month Year 3 | B46: $ | C46: 1200 | D46: 4000 | E46: 5200 | F46: =INDEX($C46:$E46,1,Scenario) -> 4000 | G46: Management estimate | H46: Medium adds Mark consulting retainer 2,000, virtual assistant 1,000, tools and insurance 1,000; Low frozen
A47: Fixed costs per month Year 4 | B47: $ | C47: 1200 | D47: 7000 | E47: 9100 | F47: =INDEX($C47:$E47,1,Scenario) -> 7000 | G47: Management estimate
A48: Fixed costs per month Year 5 | B48: $ | C48: 1200 | D48: 10000 | E48: 13000 | F48: =INDEX($C48:$E48,1,Scenario) -> 10000 | G48: Management estimate
A49: eBay and Walmart overflow, % of Amazon US revenue, Year 2 | B49: % | C49: 0.08 | D49: 0.08 | E49: 0.08 | F49: =INDEX($C49:$E49,1,Scenario) -> 0.08 | G49: Management estimate
A50: eBay and Walmart overflow, % of Amazon US revenue, Year 3 | B50: % | C50: 0.08 | D50: 0.1 | E50: 0.1 | F50: =INDEX($C50:$E50,1,Scenario) -> 0.1 | G50: Management estimate
A51: eBay and Walmart overflow, % of Amazon US revenue, Year 4 | B51: % | C51: 0.08 | D51: 0.12 | E51: 0.12 | F51: =INDEX($C51:$E51,1,Scenario) -> 0.12 | G51: Management estimate
A52: eBay and Walmart overflow, % of Amazon US revenue, Year 5 | B52: % | C52: 0.08 | D52: 0.12 | E52: 0.12 | F52: =INDEX($C52:$E52,1,Scenario) -> 0.12 | G52: Management estimate
A53: B2B installer and AV integrator revenue, Year 2 | B53: $ | C53: 0 | D53: 120000 | E53: 216000 | F53: =INDEX($C53:$E53,1,Scenario) -> 120000 | G53: Management estimate | H53: High 1.8 times Medium
A54: B2B installer and AV integrator revenue, Year 3 | B54: $ | C54: 60000 | D54: 350000 | E54: 630000 | F54: =INDEX($C54:$E54,1,Scenario) -> 350000 | G54: Management estimate | H54: Low 60K flat from Year 3
A55: B2B installer and AV integrator revenue, Year 4 | B55: $ | C55: 60000 | D55: 600000 | E55: 1080000 | F55: =INDEX($C55:$E55,1,Scenario) -> 600000 | G55: Management estimate
A56: B2B installer and AV integrator revenue, Year 5 | B56: $ | C56: 60000 | D56: 850000 | E56: 1530000 | F56: =INDEX($C56:$E56,1,Scenario) -> 850000 | G56: Management estimate
A57: DTC site revenue, Year 3 | B57: $ | C57: 0 | D57: 100000 | E57: 180000 | F57: =INDEX($C57:$E57,1,Scenario) -> 100000 | G57: Management estimate
A58: DTC site revenue, Year 4 | B58: $ | C58: 0 | D58: 250000 | E58: 450000 | F58: =INDEX($C58:$E58,1,Scenario) -> 250000 | G58: Management estimate
A59: DTC site revenue, Year 5 | B59: $ | C59: 0 | D59: 400000 | E59: 720000 | F59: =INDEX($C59:$E59,1,Scenario) -> 400000 | G59: Management estimate
A60: Amazon Canada revenue, Year 4 | B60: $ | C60: 0 | D60: 120000 | E60: 216000 | F60: =INDEX($C60:$E60,1,Scenario) -> 120000 | G60: Management estimate
A61: Amazon Canada revenue, Year 5 | B61: $ | C61: 0 | D61: 250000 | E61: 450000 | F61: =INDEX($C61:$E61,1,Scenario) -> 250000 | G61: Management estimate
A62: Pro line revenue, Year 4 | B62: $ | C62: 0 | D62: 150000 | E62: 270000 | F62: =INDEX($C62:$E62,1,Scenario) -> 150000 | G62: Management estimate
A63: Pro line revenue, Year 5 | B63: $ | C63: 0 | D63: 350000 | E63: 630000 | F63: =INDEX($C63:$E63,1,Scenario) -> 350000 | G63: Management estimate
A65: Channel economics (same in every scenario; management estimates)
A66: eBay and Walmart referral % | B66: % | C66: 0.13 | D66: 0.13 | E66: 0.13 | F66: =INDEX($C66:$E66,1,Scenario) -> 0.13 | G66: Management estimate
A67: eBay and Walmart multi channel fulfillment per unit | B67: $ | C67: 6.5 | D67: 6.5 | E67: 6.5 | F67: =INDEX($C67:$E67,1,Scenario) -> 6.5 | G67: Management estimate
A68: eBay and Walmart ads % of revenue | B68: % | C68: 0.05 | D68: 0.05 | E68: 0.05 | F68: =INDEX($C68:$E68,1,Scenario) -> 0.05 | G68: Management estimate
A69: eBay and Walmart returns % | B69: % | C69: 0.03 | D69: 0.03 | E69: 0.03 | F69: =INDEX($C69:$E69,1,Scenario) -> 0.03 | G69: Management estimate
A70: B2B price as a share of retail ASP | B70: % | C70: 0.6 | D70: 0.6 | E70: 0.6 | F70: =INDEX($C70:$E70,1,Scenario) -> 0.6 | G70: Management estimate
A71: B2B 3PL pick pack ship per unit | B71: $ | C71: 4 | D71: 4 | E71: 4 | F71: =INDEX($C71:$E71,1,Scenario) -> 4 | G71: Management estimate
A72: B2B sales commission % | B72: % | C72: 0.05 | D72: 0.05 | E72: 0.05 | F72: =INDEX($C72:$E72,1,Scenario) -> 0.05 | G72: Management estimate
A73: B2B marketing % | B73: % | C73: 0.03 | D73: 0.03 | E73: 0.03 | F73: =INDEX($C73:$E73,1,Scenario) -> 0.03 | G73: Management estimate
A74: B2B returns % | B74: % | C74: 0.02 | D74: 0.02 | E74: 0.02 | F74: =INDEX($C74:$E74,1,Scenario) -> 0.02 | G74: Management estimate
A75: DTC payment processing % | B75: % | C75: 0.03 | D75: 0.03 | E75: 0.03 | F75: =INDEX($C75:$E75,1,Scenario) -> 0.03 | G75: Management estimate
A76: DTC fulfillment and shipping per unit | B76: $ | C76: 11 | D76: 11 | E76: 11 | F76: =INDEX($C76:$E76,1,Scenario) -> 11 | G76: Management estimate
A77: DTC ads % | B77: % | C77: 0.15 | D77: 0.15 | E77: 0.15 | F77: =INDEX($C77:$E77,1,Scenario) -> 0.15 | G77: Management estimate
... A91: Pro line Amazon storage and inbound % | B91: % | C91: 0.02 | D91: 0.02 | E91: 0.02 | F91: =INDEX($C91:$E91,1,Scenario) -> 0.02 | G91: Management estimate
A93: Compliance costs per year from Year 2 (Year 1 is inside the August fixed 850 per month and the 9,500 launch costs)
A94: Form 5472 preparation (with pro forma Form 1120) | B94: $ | C94: 800 | D94: 800 | E94: 800 | F94: =INDEX($C94:$E94,1,Scenario) -> 800 | G94: Management estimate
A95: Wyoming annual report | B95: $ | C95: 60 | D95: 60 | E95: 60 | F95: =INDEX($C95:$E95,1,Scenario) -> 60 | G95: Evidence based
A96: Customs continuous bond renewal | B96: $ | C96: 500 | D96: 500 | E96: 500 | F96: =INDEX($C96:$E96,1,Scenario) -> 500 | G96: Evidence based
A97: Product liability insurance ($1M cover) per year once monthly sales pass $10K | B97: $ | C97: 1200 | D97: 1200 | E97: 1200 | F97: =INDEX($C97:$E97,1,Scenario) -> 1200 | G97: Management estimate
A98: Trademark maintenance in Year 5 [PLACEHOLDER: attorney quote] | B98: $ | C98: 0 | D98: 0 | E98: 0 | F98: =INDEX($C98:$E98,1,Scenario) -> 0 | G98: Management estimate
A100: Working capital
A101: Inventory cover target, months of forward units | B101: months | C101: 3 | D101: 2.5 | E101: 2 | F101: =INDEX($C101:$E101,1,Scenario) -> 2.5 | G101: Management estimate
A102: Ocean freight from Month (before that air) | B102: month | C102: 99 | D102: 7 | E102: 7 | F102: =INDEX($C102:$E102,1,Scenario) -> 7 | G102: Management estimate | H102: after the Day 90 gate for proven SKUs; Low stays on air
A103: Air freight lead time, months (order to arrival) | B103: months | C103: 1 | D103: 1 | E103: 1 | F103: =INDEX($C103:$E103,1,Scenario) -> 1 | G103: Management estimate | H103: spec 2.6
A104: Ocean freight lead time, months (order to arrival) | B104: months | C104: 2 | D104: 2 | E104: 2 | F104: =INDEX($C104:$E104,1,Scenario) -> 2 | G104: Management estimate | H104: spec 2.6
A105: Inventory days of landed COGS, Years 3 to 5 | B105: days | C105: 135 | D105: 95 | E105: 85 | F105: =INDEX($C105:$E105,1,Scenario) -> 95 | G105: Management estimate | H105: spec 2.6 starting values 90, 75, 60; raised to the days implied by the Month 24 stock (cover months plus one lead time in transit) so Year 3 does not release cash artificially
A106: Opening capital (self funded, August ask) | B106: $ | C106: 39000 | D106: 39000 | E106: 39000 | F106: =INDEX($C106:$E106,1,Scenario) -> 39000 | G106: Evidence based | H106: DECISIONS.md
A107: PO deposit at order (balance at shipment) | B107: % | C107: 0.3 | D107: 0.3 | E107: 0.3 | F107: =INDEX($C107:$E107,1,Scenario) -> 0.3 | G107: Management estimate | H107: 30% at order, 70% at shipment
A108: Amazon payout lag, days (receivable = lag/30 of the month's net proceeds) | B108: days | C108: 14 | D108: 14 | E108: 14 | F108: =INDEX($C108:$E108,1,Scenario) -> 14 | G108: Evidence based | H108: brief
A109: Receivable days of revenue, Years 3 to 5 | B109: days | C109: 14 | D109: 14 | E109: 14 | F109: =INDEX($C109:$E109,1,Scenario) -> 14 | G109: Management estimate
A110: Funding gap cushion on the negative minimum balance | B110: x | C110: 1.2 | D110: 1.2 | E110: 1.2 | F110: =INDEX($C110:$E110,1,Scenario) -> 1.2 | G110: Management estimate | H110: 1.2 times
A111: FX embedded in the KRW cost base, KRW per USD | B111: x | C111: 1430 | D111: 1430 | E111: 1430 | F111: =INDEX($C111:$E111,1,Scenario) -> 1430 | G111: Evidence based | H111: the only verified cost data is in KRW; a USD factory quote removes the FX effect
A113: Gate thresholds (spec 2.7; same in every scenario). The Funding and Breakeven tab and the three Scenario Summary engines read these cells, so one edit moves every PASS and KILL test and its wording
A114: Day 90: unit session conversion, pass at or above (3 of 5 launch SKUs; observed) | B114: % | C114: 0.08 | D114: 0.08 | E114: 0.08 | F114: =INDEX($C114:$E114,1,Scenario) -> 0.08 | G114: Management estimate | H114: spec 2.7 (the brief asks for the gates in numbers; the numbers are management estimates)
A115: Day 90: hero conversion, kill below (observed) | B115: % | C115: 0.05 | D115: 0.05 | E115: 0.05 | F115: =INDEX($C115:$E115,1,Scenario) -> 0.05 | G115: Management estimate | H115: spec 2.7 (the brief asks for the gates in numbers; the numbers are management estimates)
A116: Day 90: TACOS in Month 3, pass at or below | B116: % | C116: 0.3 | D116: 0.3 | E116: 0.3 | F116: =INDEX($C116:$E116,1,Scenario) -> 0.3 | G116: Management estimate | H116: spec 2.7 (the brief asks for the gates in numbers; the numbers are management estimates)
A117: Day 90: TACOS in Month 3, kill above | B117: % | C117: 0.4 | D117: 0.4 | E117: 0.4 | F117: =INDEX($C117:$E117,1,Scenario) -> 0.4 | G117: Management estimate | H117: spec 2.7 (the brief asks for the gates in numbers; the numbers are management estimates)
A118: Day 90: return rate, pass at or below | B118: % | C118: 0.04 | D118: 0.04 | E118: 0.04 | F118: =INDEX($C118:$E118,1,Scenario) -> 0.04 | G118: Management estimate | H118: spec 2.7 (the brief asks for the gates in numbers; the numbers are management estimates)
A119: Day 90: return rate, kill above | B119: % | C119: 0.07 | D119: 0.07 | E119: 0.07 | F119: =INDEX($C119:$E119,1,Scenario) -> 0.07 | G119: Management estimate | H119: spec 2.7 (the brief asks for the gates in numbers; the numbers are management estimates)
A120: Day 90: contribution per unit before advertising, pass at or above | B120: $ | C120: 11 | D120: 11 | E120: 11 | F120: =INDEX($C120:$E120,1,Scenario) -> 11 | G120: Management estimate | H120: spec 2.7 (the brief asks for the gates in numbers; the numbers are management estimates)
A121: Day 90: hero contribution per unit before advertising, kill below | B121: $ | C121: 8 | D121: 8 | E121: 8 | F121: =INDEX($C121:$E121,1,Scenario) -> 8 | G121: Management estimate | H121: spec 2.7 (the brief asks for the gates in numbers; the numbers are management estimates)
...

Sheet FX
A1: FX
A2: The only verified cost data is in KRW (August deal). FX moves landed COGS % through the hero FOB share. A USD factory quote removes this effect.
A4: Active FX rate, KRW per USD (input on Assumptions) | B4: =FXRate -> 1430
A6: Item | B6: Active | C6: Scenario 1,300 | D6: Scenario 1,430 | E6: Scenario 1,550 | F6: Basis
A7: FX rate, KRW per USD | B7: =FXRate -> 1430 | C7: 1300 | D7: 1430 | E7: 1550 | F7: Evidence based default 1,430; scenarios per the brief
A8: August 2026 deal totals (inputs from inputs/august_deal_totals.csv; H2 Company to Dioptek, 1,400 units)
A9: August deal units | B9: 1400 | F9: Evidence based: August 2026 deal (inputs/august_deal_totals.csv)
A10: August deal cost, KRW | B10: 19460000 | F10: Evidence based: August 2026 deal (inputs/august_deal_totals.csv)
A11: August deal revenue ex VAT, KRW | B11: 24400000 | F11: Evidence based: August 2026 deal (inputs/august_deal_totals.csv)
A12: August deal gross profit, KRW | B12: 4940000 | F12: Evidence based: August 2026 deal (inputs/august_deal_totals.csv)
A13: August deal gross margin (gross profit divided by revenue) | B13: =B12/B11 -> 0.20245902 | F13: 20.3% in the brief
A15: Conversions at the active FX rate and the three FX scenarios
A16: Hero FOB USD (8K 10M, KRW 11,470 times the FOB factor) | B16: ='SKU Unit Economics'!$D$6/B$7*'SKU Unit Economics'!$B$18 -> 7.3793007 | C16: ='SKU Unit Economics'!$D$6/C$7*'SKU Unit Economics'!$B$18 -> 8.1172308 | D16: ='SKU Unit Economics'!$D$6/D$7*'SKU Unit Economics'!$B$18 -> 7.3793007 | E16: ='SKU Unit Economics'!$D$6/E$7*'SKU Unit Economics'!$B$18 -> 6.808 | F16: Evidence based KRW cost
A17: Landed COGS % delta vs the 1,430 cost base (hero FOB share times (1,430 / FX minus 1)) | B17: =HeroFobShare*(Assumptions!$F$111/B$7-1) -> 0 | C17: =HeroFobShare*(Assumptions!$F$111/C$7-1) -> 0.016402091 | D17: =HeroFobShare*(Assumptions!$F$111/D$7-1) -> 0 | E17: =HeroFobShare*(Assumptions!$F$111/E$7-1) -> -0.012698393 | F17: Model formula
A18: Opening capital $39,000 in KRW | B18: =Assumptions!$F$106*B$7 -> 55770000 | C18: =Assumptions!$F$106*C$7 -> 50700000 | D18: =Assumptions!$F$106*D$7 -> 55770000 | E18: =Assumptions!$F$106*E$7 -> 60450000 | F18: DECISIONS.md
A19: August deal cost in USD | B19: =$B$10/B$7 -> 13608.392 | C19: =$B$10/C$7 -> 14969.231 | D19: =$B$10/D$7 -> 13608.392 | E19: =$B$10/E$7 -> 12554.839 | F19: August deal (input above)
A20: August deal revenue ex VAT in USD | B20: =$B$11/B$7 -> 17062.937 | C20: =$B$11/C$7 -> 18769.231 | D20: =$B$11/D$7 -> 17062.937 | E20: =$B$11/E$7 -> 15741.935 | F20: August deal (input above)
A21: August deal gross profit in USD | B21: =$B$12/B$7 -> 3454.5455 | C21: =$B$12/C$7 -> 3800 | D21: =$B$12/D$7 -> 3454.5455 | E21: =$B$12/E$7 -> 3187.0968 | F21: August deal (input above; about $3,500 at 1,430)
A22: Hero H2 cost KRW 11,470 in USD (Korea landed) | B22: ='SKU Unit Economics'!$D$6/B$7 -> 8.020979 | C22: ='SKU Unit Economics'!$D$6/C$7 -> 8.8230769 | D22: ='SKU Unit Economics'!$D$6/D$7 -> 8.020979 | E22: ='SKU Unit Economics'!$D$6/E$7 -> 7.4 | F22: August deal
A23: Profit repatriation examples (active scenario)
A24: Year 1 net (active scenario) in KRW | B24: ='Annual PL Y1 to Y5'!$C$80*B$7 -> 54397372 | C24: ='Annual PL Y1 to Y5'!$C$80*C$7 -> 49452156 | D24: ='Annual PL Y1 to Y5'!$C$80*D$7 -> 54397372 | E24: ='Annual PL Y1 to Y5'!$C$80*E$7 -> 58962186 | F24: Model
A25: Year 5 net (active scenario) in KRW | B25: ='Annual PL Y1 to Y5'!$G$80*B$7 -> 8.7618183e+08 | C25: ='Annual PL Y1 to Y5'!$G$80*C$7 -> 7.9652894e+08 | D25: ='Annual PL Y1 to Y5'!$G$80*D$7 -> 8.7618183e+08 | E25: ='Annual PL Y1 to Y5'!$G$80*E$7 -> 9.4970758e+08 | F25: Model
A26: Cumulative 5 year net (active scenario) in KRW | B26: ='Annual PL Y1 to Y5'!$G$82*B$7 -> 2.7666569e+09 | C26: ='Annual PL Y1 to Y5'!$G$82*C$7 -> 2.5151427e+09 | D26: ='Annual PL Y1 to Y5'!$G$82*D$7 -> 2.7666569e+09 | E26: ='Annual PL Y1 to Y5'!$G$82*E$7 -> 2.9988239e+09 | F26: Model; before US and Korean tax
A27: Korean overseas financial account report threshold: KRW 500M month end aggregate (flag for the tax accountant). Overseas direct investment report before capital moves (any stake 10% or more, any amount).

Sheet SKU Unit Economics
A1: SKU Unit Economics
A2: FOB China = H2 landed Korea cost in KRW divided by FX times the FOB factor. Duty columns use the duty table. Air and ocean landed costs use the active duty scenario. Hero row highlighted.
A4: SKU | B4: Spec (internal only) | C4: Length m | D4: H2 cost KRW | E4: FOB USD | F4: US list | G4: US sale price (ASP) | H4: Packaged lb | I4: kg | J4: Air freight | K4: Ocean freight | L4: Duty copper | M4: Duty fiber | N4: Duty stress | O4: Duty active | P4: MPF and HMF (ocean) | Q4: Broker and bond | R4: FBA inbound and prep | S4: QC and labels | T4: Landed air | U4: Landed ocean | V4: Landed air % | W4: Landed ocean % | X4: FBA fee | Y4: Referral 15% | Z4: Ads | AA4: Returns and storage | AB4: Net air | AC4: Net air % | AD4: Net ocean | AE4: Net ocean % | AF4: Launch SKU
A5: 8K_7M | B5: HDMI 2.1 8K hybrid AOC | C5: 7 | D5: 10525 | E5: =D5/FXRate*$B$18 -> 6.7713287 | F5: 49.99 | G5: 39.99 | H5: 0.35 | I5: =H5*$B$21 -> 0.15876 | J5: =I5*$B$19 -> 1.34946 | K5: =I5*$B$20 -> 0.174636 | L5: =E5*'Landed Cost & Tariff Scenarios'!$G$5 -> 2.7153028 | M5: =E5*'Landed Cost & Tariff Scenarios'!$G$6 -> 0.84641608 | N5: =E5*'Landed Cost & Tariff Scenarios'!$G$7 -> 3.3924357 | O5: =INDEX(L5:N5,1,DutyScenario) -> 2.7153028 | P5: =E5*$B$22 -> 0.02369965 | Q5: =$B$23 -> 0.4 | R5: =$B$24 -> 0.5 | S5: =$B$25 -> 0.25 | T5: =E5+J5+O5+Q5+R5+S5 -> 11.986091 | U5: =E5+K5+O5+P5+Q5+R5+S5 -> 10.834967 | V5: =T5/G5 -> 0.29972722 | W5: =U5/G5 -> 0.27094191 | X5: 4.9 | Y5: =G5*Assumptions!$F$19 -> 5.9985 | Z5: =G5*$B$26 -> 4.7988 | AA5: =G5*$B$27 -> 1.9995 | AB5: =G5-T5-X5-Y5-Z5-AA5 -> 10.307109 | AC5: =AB5/G5 -> 0.25774215 | AD5: =G5-U5-X5-Y5-Z5-AA5 -> 11.458233 | AE5: =AD5/G5 -> 0.28652745 | AF5: Yes
A6: 8K_10M | B6: HDMI 2.1 8K hybrid AOC (hero) | C6: 10 | D6: 11470 | E6: =D6/FXRate*$B$18 -> 7.3793007 | F6: 59.99 | G6: 44.99 | H6: 0.45 | I6: =H6*$B$21 -> 0.20412 | J6: =I6*$B$19 -> 1.73502 | K6: =I6*$B$20 -> 0.224532 | L6: =E6*'Landed Cost & Tariff Scenarios'!$G$5 -> 2.9590996 | M6: =E6*'Landed Cost & Tariff Scenarios'!$G$6 -> 0.92241259 | N6: =E6*'Landed Cost & Tariff Scenarios'!$G$7 -> 3.6970297 | O6: =INDEX(L6:N6,1,DutyScenario) -> 2.9590996 | P6: =E6*$B$22 -> 0.025827552 | Q6: =$B$23 -> 0.4 | R6: =$B$24 -> 0.5 | S6: =$B$25 -> 0.25 | T6: =E6+J6+O6+Q6+R6+S6 -> 13.22342 | U6: =E6+K6+O6+P6+Q6+R6+S6 -> 11.73876 | V6: =T6/G6 -> 0.2939191 | W6: =U6/G6 -> 0.26091931 | X6: 4.9 | Y6: =G6*Assumptions!$F$19 -> 6.7485 | Z6: =G6*$B$26 -> 5.3988 | AA6: =G6*$B$27 -> 2.2495 | AB6: =G6-T6-X6-Y6-Z6-AA6 -> 12.46978 | AC6: =AB6/G6 -> 0.27716781 | AD6: =G6-U6-X6-Y6-Z6-AA6 -> 13.95444 | AE6: =AD6/G6 -> 0.3101676 | AF6: Yes
A7: 8K_15M | B7: HDMI 2.1 8K hybrid AOC | C7: 15 | D7: 13376 | E7: =D7/FXRate*$B$18 -> 8.6055385 | F7: 69.99 | G7: 54.99 | H7: 0.6 | I7: =H7*$B$21 -> 0.27216 | J7: =I7*$B$19 -> 2.31336 | K7: =I7*$B$20 -> 0.299376 | L7: =E7*'Landed Cost & Tariff Scenarios'!$G$5 -> 3.4508209 | M7: =E7*'Landed Cost & Tariff Scenarios'!$G$6 -> 1.0756923 | N7: =E7*'Landed Cost & Tariff Scenarios'!$G$7 -> 4.3113748 | O7: =INDEX(L7:N7,1,DutyScenario) -> 3.4508209 | P7: =E7*$B$22 -> 0.030119385 | Q7: =$B$23 -> 0.4 | R7: =$B$24 -> 0.5 | S7: =$B$25 -> 0.25 | T7: =E7+J7+O7+Q7+R7+S7 -> 15.519719 | U7: =E7+K7+O7+P7+Q7+R7+S7 -> 13.535855 | V7: =T7/G7 -> 0.28222803 | W7: =U7/G7 -> 0.24615121 | X7: 5.5 | Y7: =G7*Assumptions!$F$19 -> 8.2485 | Z7: =G7*$B$26 -> 6.5988 | AA7: =G7*$B$27 -> 2.7495 | AB7: =G7-T7-X7-Y7-Z7-AA7 -> 16.373481 | AC7: =AB7/G7 -> 0.29775378 | AD7: =G7-U7-X7-Y7-Z7-AA7 -> 18.357345 | AE7: =AD7/G7 -> 0.33383061 | AF7: Yes
A8: 8K_20M | B8: HDMI 2.1 8K hybrid AOC | C8: 20 | D8: 15266 | E8: =D8/FXRate*$B$18 -> 9.8214825 | F8: 79.99 | G8: 64.99 | H8: 0.75 | I8: =H8*$B$21 -> 0.3402 | J8: =I8*$B$19 -> 2.8917 | K8: =I8*$B$20 -> 0.37422 | L8: =E8*'Landed Cost & Tariff Scenarios'!$G$5 -> 3.9384145 | M8: =E8*'Landed Cost & Tariff Scenarios'!$G$6 -> 1.2276853 | N8: =E8*'Landed Cost & Tariff Scenarios'!$G$7 -> 4.9205627 | O8: =INDEX(L8:N8,1,DutyScenario) -> 3.9384145 | P8: =E8*$B$22 -> 0.034375189 | Q8: =$B$23 -> 0.4 | R8: =$B$24 -> 0.5 | S8: =$B$25 -> 0.25 | T8: =E8+J8+O8+Q8+R8+S8 -> 17.801597 | U8: =E8+K8+O8+P8+Q8+R8+S8 -> 15.318492 | V8: =T8/G8 -> 0.27391286 | W8: =U8/G8 -> 0.23570537 | X8: 5.5 | Y8: =G8*Assumptions!$F$19 -> 9.7485 | Z8: =G8*$B$26 -> 7.7988 | AA8: =G8*$B$27 -> 3.2495 | AB8: =G8-T8-X8-Y8-Z8-AA8 -> 20.891603 | AC8: =AB8/G8 -> 0.32145873 | AD8: =G8-U8-X8-Y8-Z8-AA8 -> 23.374708 | AE8: =AD8/G8 -> 0.35966622 | AF8: Yes
A9: 8K_25M | B9: HDMI 2.1 8K hybrid AOC | C9: 25 | D9: 17172 | E9: =D9/FXRate*$B$18 -> 11.04772 | F9: 89.99 | G9: 74.99 | H9: 0.9 | I9: =H9*$B$21 -> 0.40824 | J9: =I9*$B$19 -> 3.47004 | K9: =I9*$B$20 -> 0.449064 | L9: =E9*'Landed Cost & Tariff Scenarios'!$G$5 -> 4.4301358 | M9: =E9*'Landed Cost & Tariff Scenarios'!$G$6 -> 1.380965 | N9: =E9*'Landed Cost & Tariff Scenarios'!$G$7 -> 5.5349079 | O9: =INDEX(L9:N9,1,DutyScenario) -> 4.4301358 | P9: =E9*$B$22 -> 0.038667021 | Q9: =$B$23 -> 0.4 | R9: =$B$24 -> 0.5 | S9: =$B$25 -> 0.25 | T9: =E9+J9+O9+Q9+R9+S9 -> 20.097896 | U9: =E9+K9+O9+P9+Q9+R9+S9 -> 17.115587 | V9: =T9/G9 -> 0.26800768 | W9: =U9/G9 -> 0.22823826 | X9: 6.6 | Y9: =G9*Assumptions!$F$19 -> 11.2485 | Z9: =G9*$B$26 -> 8.9988 | AA9: =G9*$B$27 -> 3.7495 | AB9: =G9-T9-X9-Y9-Z9-AA9 -> 24.295304 | AC9: =AB9/G9 -> 0.32398058 | AD9: =G9-U9-X9-Y9-Z9-AA9 -> 27.277613 | AE9: =AD9/G9 -> 0.36375 | AF9: No
A10: 8K_50M | B10: HDMI 2.1 8K hybrid AOC | C10: 50 | D10: 27349 | E10: =D10/FXRate*$B$18 -> 17.595161 | F10: 149.99 | G10: 119.99 | H10: 1.9 | I10: =H10*$B$21 -> 0.86184 | J10: =I10*$B$19 -> 7.32564 | K10: =I10*$B$20 -> 0.948024 | L10: =E10*'Landed Cost & Tariff Scenarios'!$G$5 -> 7.0556595 | M10: =E10*'Landed Cost & Tariff Scenarios'!$G$6 -> 2.1993951 | N10: =E10*'Landed Cost & Tariff Scenarios'!$G$7 -> 8.8151756 | O10: =INDEX(L10:N10,1,DutyScenario) -> 7.0556595 | P10: =E10*$B$22 -> 0.061583063 | Q10: =$B$23 -> 0.4 | R10: =$B$24 -> 0.5 | S10: =$B$25 -> 0.25 | T10: =E10+J10+O10+Q10+R10+S10 -> 33.12646 | U10: =E10+K10+O10+P10+Q10+R10+S10 -> 26.810427 | V10: =T10/G10 -> 0.27607684 | W10: =U10/G10 -> 0.22343885 | X10: 8.4 | Y10: =G10*Assumptions!$F$19 -> 17.9985 | Z10: =G10*$B$26 -> 14.3988 | AA10: =G10*$B$27 -> 5.9995 | AB10: =G10-T10-X10-Y10-Z10-AA10 -> 40.06674 | AC10: =AB10/G10 -> 0.33391732 | AD10: =G10-U10-X10-Y10-Z10-AA10 -> 46.382773 | AE10: =AD10/G10 -> 0.38655532 | AF10: No
A11: 4K_15M | B11: HDMI 2.0 4K hybrid AOC | C11: 15 | D11: 12680 | E11: =D11/FXRate*$B$18 -> 8.1577622 | F11: 44.99 | G11: 34.99 | H11: 0.6 | I11: =H11*$B$21 -> 0.27216 | J11: =I11*$B$19 -> 2.31336 | K11: =I11*$B$20 -> 0.299376 | L11: =E11*'Landed Cost & Tariff Scenarios'!$G$5 -> 3.2712627 | M11: =E11*'Landed Cost & Tariff Scenarios'!$G$6 -> 1.0197203 | N11: =E11*'Landed Cost & Tariff Scenarios'!$G$7 -> 4.0870389 | O11: =INDEX(L11:N11,1,DutyScenario) -> 3.2712627 | P11: =E11*$B$22 -> 0.028552168 | Q11: =$B$23 -> 0.4 | R11: =$B$24 -> 0.5 | S11: =$B$25 -> 0.25 | T11: =E11+J11+O11+Q11+R11+S11 -> 14.892385 | U11: =E11+K11+O11+P11+Q11+R11+S11 -> 12.906953 | V11: =T11/G11 -> 0.42561832 | W11: =U11/G11 -> 0.36887548 | X11: 5.5 | Y11: =G11*Assumptions!$F$19 -> 5.2485 | Z11: =G11*$B$26 -> 4.1988 | AA11: =G11*$B$27 -> 1.7495 | AB11: =G11-T11-X11-Y11-Z11-AA11 -> 3.4008151 | AC11: =AB11/G11 -> 0.097193916 | AD11: =G11-U11-X11-Y11-Z11-AA11 -> 5.3862469 | AE11: =AD11/G11 -> 0.15393675 | AF11: No
A12: 4K_20M | B12: HDMI 2.0 4K hybrid AOC | C12: 20 | D12: 14122 | E12: =D12/FXRate*$B$18 -> 9.0854825 | F12: 49.99 | G12: 39.99 | H12: 0.75 | I12: =H12*$B$21 -> 0.3402 | J12: =I12*$B$19 -> 2.8917 | K12: =I12*$B$20 -> 0.37422 | L12: =E12*'Landed Cost & Tariff Scenarios'!$G$5 -> 3.6432785 | M12: =E12*'Landed Cost & Tariff Scenarios'!$G$6 -> 1.1356853 | N12: =E12*'Landed Cost & Tariff Scenarios'!$G$7 -> 4.5518267 | O12: =INDEX(L12:N12,1,DutyScenario) -> 3.6432785 | P12: =E12*$B$22 -> 0.031799189 | Q12: =$B$23 -> 0.4 | R12: =$B$24 -> 0.5 | S12: =$B$25 -> 0.25 | T12: =E12+J12+O12+Q12+R12+S12 -> 16.770461 | U12: =E12+K12+O12+P12+Q12+R12+S12 -> 14.28478 | V12: =T12/G12 -> 0.41936637 | W12: =U12/G12 -> 0.35720881 | X12: 5.5 | Y12: =G12*Assumptions!$F$19 -> 5.9985 | Z12: =G12*$B$26 -> 4.7988 | AA12: =G12*$B$27 -> 1.9995 | AB12: =G12-T12-X12-Y12-Z12-AA12 -> 4.922739 | AC12: =AB12/G12 -> 0.12309925 | AD12: =G12-U12-X12-Y12-Z12-AA12 -> 7.4084198 | AE12: =AD12/G12 -> 0.18525681 | AF12: No
A13: 4K_30M | B13: HDMI 2.0 4K hybrid AOC | C13: 30 | D13: 19542 | E13: =D13/FXRate*$B$18 -> 12.572476 | F13: 64.99 | G13: 49.99 | H13: 1.1 | I13: =H13*$B$21 -> 0.49896 | J13: =I13*$B$19 -> 4.24116 | K13: =I13*$B$20 -> 0.548856 | L13: =E13*'Landed Cost & Tariff Scenarios'!$G$5 -> 5.0415627 | M13: =E13*'Landed Cost & Tariff Scenarios'!$G$6 -> 1.5715594 | N13: =E13*'Landed Cost & Tariff Scenarios'!$G$7 -> 6.2988102 | O13: =INDEX(L13:N13,1,DutyScenario) -> 5.0415627 | P13: =E13*$B$22 -> 0.044003664 | Q13: =$B$23 -> 0.4 | R13: =$B$24 -> 0.5 | S13: =$B$25 -> 0.25 | T13: =E13+J13+O13+Q13+R13+S13 -> 23.005198 | U13: =E13+K13+O13+P13+Q13+R13+S13 -> 19.356898 | V13: =T13/G13 -> 0.460196 | W13: =U13/G13 -> 0.3872154 | X13: 6.6 | Y13: =G13*Assumptions!$F$19 -> 7.4985 | Z13: =G13*$B$26 -> 5.9988 | AA13: =G13*$B$27 -> 2.4995 | AB13: =G13-T13-X13-Y13-Z13-AA13 -> 4.3880018 | AC13: =AB13/G13 -> 0.087777591 | AD13: =G13-U13-X13-Y13-Z13-AA13 -> 8.0363021 | AE13: =AD13/G13 -> 0.16075819 | AF13: Yes
A14: 4K_40M | B14: HDMI 2.0 4K hybrid AOC | C14: 40 | D14: 22609 | E14: =D14/FXRate*$B$18 -> 14.54565 | F14: 74.99 | G14: 59.99 | H14: 1.5 | I14: =H14*$B$21 -> 0.6804 | J14: =I14*$B$19 -> 5.7834 | K14: =I14*$B$20 -> 0.74844 | L14: =E14*'Landed Cost & Tariff Scenarios'!$G$5 -> 5.8328058 | M14: =E14*'Landed Cost & Tariff Scenarios'!$G$6 -> 1.8182063 | N14: =E14*'Landed Cost & Tariff Scenarios'!$G$7 -> 7.2873708 | O14: =INDEX(L14:N14,1,DutyScenario) -> 5.8328058 | P14: =E14*$B$22 -> 0.050909776 | Q14: =$B$23 -> 0.4 | R14: =$B$24 -> 0.5 | S14: =$B$25 -> 0.25 | T14: =E14+J14+O14+Q14+R14+S14 -> 27.311856 | U14: =E14+K14+O14+P14+Q14+R14+S14 -> 22.327806 | V14: =T14/G14 -> 0.45527348 | W14: =U14/G14 -> 0.37219213 | X14: 8.4 | Y14: =G14*Assumptions!$F$19 -> 8.9985 | Z14: =G14*$B$26 -> 7.1988 | AA14: =G14*$B$27 -> 2.9995 | AB14: =G14-T14-X14-Y14-Z14-AA14 -> 5.0813439 | AC14: =AB14/G14 -> 0.084703182 | AD14: =G14-U14-X14-Y14-Z14-AA14 -> 10.065394 | AE14: =AD14/G14 -> 0.16778453 | AF14: No
A15: Basis: H2 cost KRW evidence based (August deal). FOB factor, freight, fees, weights, US prices and FBA fees are management estimates pending the Amazon rate card check. The spec column is internal: packaging and listings use the category names (Ultra High Speed HDMI Cable; Premium High Speed HDMI Cable pending certification).
A17: Cost build constants
A18: FOB factor on the H2 Korea landed cost (removes Korea inbound freight and handling) | B18: 0.92 | C18: Management estimate
A19: Air freight DDP per kg packaged | B19: 8.5 | C19: Management estimate | D19: consolidated express, first lots
A20: Ocean LCL plus drayage per kg packaged | B20: 1.1 | C20: Management estimate
A21: Kilograms per pound | B21: 0.4536 | C21: Evidence based
A22: Merchandise processing and harbor maintenance fees, % of FOB, ocean only | B22: 0.0035 | C22: Management estimate
A23: Broker entry fee and continuous bond, amortized per unit | B23: 0.4 | C23: Management estimate | D23: $150 per entry plus $500 per year bond at launch volumes
A24: FBA inbound placement and prep per unit | B24: 0.5 | C24: Management estimate
A25: Third party QC and FNSKU labeling at the factory per unit | B25: 0.25 | C25: Management estimate
A26: Advertising % of price for unit economics (August hero: $5.40 on $44.99) | B26: 0.12 | C26: Evidence based
A27: Returns and storage reserve % of price (3% returns plus 2% storage and inbound) | B27: 0.05 | C27: Evidence based
A28: FBA fee used in the August hero unit economics | B28: 5.5 | C28: Evidence based
A29: Alibaba benchmark FOB, low, comparable 30 ft (9 m) AOC | B29: 17 | C29: Evidence based | D29: quote, flagged
A30: Alibaba benchmark FOB, high | B30: 22 | C30: Evidence based | D30: quote, flagged
A32: Hero SKU unit economics, August model (evidence based): 8K AOC 10M on Amazon US
A33: Price | B33: 44.99
A34: List price | B34: 59.99
A35: Landed cost % (assumed 38% pending the customs ruling) | B35: 0.38
A36: Landed cost | B36: =B33*B35 -> 17.0962
A37: Referral % | B37: =Assumptions!$F$19 -> 0.15
A38: Referral | B38: =B33*B37 -> 6.7485
A39: FBA fulfillment | B39: =$B$28 -> 5.5
A40: Advertising % (blended) | B40: =$B$26 -> 0.12
A41: Advertising | B41: =B33*B40 -> 5.3988
A42: Returns and storage reserve % | B42: =$B$27 -> 0.05
A43: Returns and storage reserve | B43: =B33*B42 -> 2.2495
A44: Net per unit | B44: =B33-B36-B38-B39-B41-B43 -> 7.997
A45: Net % | B45: =B44/B33 -> 0.17775061
A46: Korea wholesale gross on the same unit | B46: 1.86
A47: Contribution per unit before advertising | B47: =B44+B41 -> 13.3958
A48: Hero FOB share of the August price (hero FOB USD at the FX embedded in the KRW cost base, 1,430, divided by $44.99): drives the duty and FX effect on landed COGS %. Held at the base FX so the FX delta formula (spec 2.4) is the only FX effect | B48: =$D$6/Assumptions!$F$111*$B$18/$B$33 -> 0.16402091
A49: Hero FOB USD at the active FX rate | B49: =E6 -> 7.3793007
A51: Three cost bases for the hero SKU at $44.99 (air freight, active duty scenario). The gap between (a) and (c) is the single largest unverified assumption in the plan.
A52: Cost basis | B52: FOB USD | C52: Freight, duty, fees | D52: Landed cost | E52: Landed % | F52: Net per unit at $44.99 (August fees) | G52: Net % | H52: Basis
A53: (a) H2 cost base (August deal KRW, FOB factor, bottom up) | B53: =E6 -> 7.3793007 | C53: =J6+B53*'Landed Cost & Tariff Scenarios'!$G$9+Q6+R6+S6 -> 5.8441196 | D53: =B53+C53 -> 13.22342 | E53: =D53/B33 -> 0.2939191 | F53: =B33-D53-B38-B39-B41-B43 -> 11.86978 | G53: =F53/B33 -> 0.26383151 | H53: Evidence based cost, management estimate build
A54: (b) August model assumption (38% of price) | D54: =B36 -> 17.0962 | E54: =D54/B33 -> 0.38 | F54: =B33-D54-B38-B39-B41-B43 -> 7.997 | G54: =F54/B33 -> 0.17775061 | H54: Evidence based (August deck assumption)
A55: (c) Alibaba benchmark FOB $17 (comparable 30 ft AOC) | B55: =$B$29 -> 17 | C55: =J6+B55*'Landed Cost & Tariff Scenarios'!$G$9+Q6+R6+S6 -> 9.70202 | D55: =B55+C55 -> 26.70202 | E55: =D55/B33 -> 0.59351011 | F55: =B33-D55-B38-B39-B41-B43 -> -1.60882 | G55: =F55/B33 -> -0.035759502 | H55: Evidence based quote, flagged
A56: (c) Alibaba benchmark FOB $22 | B56: =$B$30 -> 22 | C56: =J6+B56*'Landed Cost & Tariff Scenarios'!$G$9+Q6+R6+S6 -> 11.70702 | D56: =B56+C56 -> 33.70702 | E56: =D56/B33 -> 0.74921138 | F56: =B33-D56-B38-B39-B41-B43 -> -8.61382 | G56: =F56/B33 -> -0.19146077 | H56: Evidence based quote, flagged
A57: At the Alibaba cost the hero SKU loses money at $44.99. Verify the factory FOB quote in USD before the first purchase order.

Sheet Landed Cost & Tariff Scenarios
A1: Landed Cost and Tariff Scenarios
A2: Duty is a selector (DutyScenario on Assumptions). The 12.5% Section 301 forced labor rate applies whichever classification the CBP binding ruling gives.
A4: Scenario | B4: HTS | C4: MFN | D4: Section 301 list rate | E4: Section 301 forced labor (late July 2026) | F4: Pending second Section 301 action | G4: Total duty rate | H4: Basis
A5: Copper | B5: 8544.42.90 | C5: 0.026 | D5: 0.25 | E5: 0.125 | F5: 0 | G5: =SUM(C5:F5) -> 0.401 | H5: Evidence based
A6: Fiber | B6: 8544.70.00 | C6: 0 | D6: 0 | E6: 0.125 | F6: 0 | G6: =SUM(C6:F6) -> 0.125 | H6: Evidence based rates; List 3 coverage of 8544.70.00 is a broker check [PLACEHOLDER]
A7: Stress | B7: 8544.42.90 plus pending second Section 301 action | C7: 0.026 | D7: 0.25 | E7: 0.125 | F7: 0.1 | G7: =SUM(C7:F7) -> 0.501 | H7: Management estimate
A8: Fiber if also on List 3 (check row only, not selectable) | B8: 8544.70.00 | C8: 0 | D8: 0.25 | E8: 0.125 | F8: 0 | G8: =SUM(C8:F8) -> 0.375 | H8: Shown as a check row only
A9: Active duty rate (selected scenario) | G9: =INDEX($G$5:$G$7,DutyScenario,1) -> 0.401
A10: Copper rate (the rate embedded in the base landed COGS %) | G10: =$G$5 -> 0.401
A12: Landed COGS % build for the active scenario (P&L)
A13: Base landed COGS % (Assumptions, Active: Low 43%, Medium 38%, High 32%) | C13: =Assumptions!$F$11 -> 0.38
A14: Duty delta = (active duty rate minus copper rate) times hero FOB share of price | C14: =(DutyRateActive-DutyRateCopper)*HeroFobShare -> 0
A15: Freight mode delta (points; 0 because the base already assumes air then ocean; the Year 2 landed change carries the ocean benefit) | C15: 0
A16: FX delta = hero FOB share times (FX embedded in the cost base divided by FXRate, minus 1) | C16: =HeroFobShare*(Assumptions!$F$111/FXRate-1) -> 0
A17: Active landed COGS % used by the P&L | C17: =C13+C14+C15+C16 -> 0.38
A18: Note: the High base of 32% already assumes the fiber ruling, ocean freight and volume pricing. Selecting Fiber duty with High counts the ruling twice. Use Medium plus Fiber to see the ruling effect (about 33.5%, the August lever 38% to 33%).
A20: Landed COGS % by scenario and duty scenario at the active FX rate (used by the Scenario Summary engines)
A21: Scenario | B21: Copper | C21: Fiber | D21: Stress | E21: At active duty | F21: Hero net per unit at active duty (August fees, $44.99)
A22: Low | B22: =Assumptions!$C$11+($G$5-DutyRateCopper)*HeroFobShare+LandedFreightDelta+LandedFxDelta -> 0.43 | C22: =Assumptions!$C$11+($G$6-DutyRateCopper)*HeroFobShare+LandedFreightDelta+LandedFxDelta -> 0.38473023 | D22: =Assumptions!$C$11+($G$7-DutyRateCopper)*HeroFobShare+LandedFreightDelta+LandedFxDelta -> 0.44640209 | E22: =INDEX(B22:D22,1,DutyScenario) -> 0.43 | F22: =ue_hero_price*(1-E22)-ue_hero_referral-ue_hero_fba-ue_hero_ads-ue_hero_returns_storage -> 5.7475
A23: Medium | B23: =Assumptions!$D$11+($G$5-DutyRateCopper)*HeroFobShare+LandedFreightDelta+LandedFxDelta -> 0.38 | C23: =Assumptions!$D$11+($G$6-DutyRateCopper)*HeroFobShare+LandedFreightDelta+LandedFxDelta -> 0.33473023 | D23: =Assumptions!$D$11+($G$7-DutyRateCopper)*HeroFobShare+LandedFreightDelta+LandedFxDelta -> 0.39640209 | E23: =INDEX(B23:D23,1,DutyScenario) -> 0.38 | F23: =ue_hero_price*(1-E23)-ue_hero_referral-ue_hero_fba-ue_hero_ads-ue_hero_returns_storage -> 7.997
A24: High | B24: =Assumptions!$E$11+($G$5-DutyRateCopper)*HeroFobShare+LandedFreightDelta+LandedFxDelta -> 0.32 | C24: =Assumptions!$E$11+($G$6-DutyRateCopper)*HeroFobShare+LandedFreightDelta+LandedFxDelta -> 0.27473023 | D24: =Assumptions!$E$11+($G$7-DutyRateCopper)*HeroFobShare+LandedFreightDelta+LandedFxDelta -> 0.33640209 | E24: =INDEX(B24:D24,1,DutyScenario) -> 0.32 | F24: =ue_hero_price*(1-E24)-ue_hero_referral-ue_hero_fba-ue_hero_ads-ue_hero_returns_storage -> 10.6964
A26: Hero net per unit by duty scenario (Medium base 38%, August fees, price $44.99) and the waterfall data for the chart
A27: Duty scenario | B27: Duty rate | C27: Landed % | D27: Hero net per unit | E27: Waterfall label | F27: Invisible base | G27: Bar value | H27: Bar color
A28: Copper | B28: =$G$5 -> 0.401 | C28: =B23 -> 0.38 | D28: =ue_hero_price*(1-C28)-ue_hero_referral-ue_hero_fba-ue_hero_ads-ue_hero_returns_storage -> 7.997
A29: Fiber | B29: =$G$6 -> 0.125 | C29: =C23 -> 0.33473023 | D29: =ue_hero_price*(1-C29)-ue_hero_referral-ue_hero_fba-ue_hero_ads-ue_hero_returns_storage -> 10.033687
A30: Stress | B30: =$G$7 -> 0.501 | C30: =D23 -> 0.39640209 | D30: =ue_hero_price*(1-C30)-ue_hero_referral-ue_hero_fba-ue_hero_ads-ue_hero_returns_storage -> 7.2590699
E31: Copper net | F31: =0 -> 0 | G31: =D28 -> 7.997 | H31: value
E32: Fiber ruling uplift | F32: =D28 -> 7.997 | G32: =D29-D28 -> 2.036687 | H32: up
E33: Fiber net | F33: =0 -> 0 | G33: =D29 -> 10.033687 | H33: value
E34: Stress penalty | F34: =D30 -> 7.2590699 | G34: =D28-D30 -> 0.73793007 | H34: down
E35: Stress net | F35: =0 -> 0 | G35: =D30 -> 7.2590699 | H35: value
A37: Tariff stack by scenario (for the stacked chart)
A38: Scenario | B38: MFN | C38: Section 301 list | D38: Section 301 forced labor | E38: Pending second action | F38: Total
A39: Copper | B39: =C5 -> 0.026 | C39: =D5 -> 0.25 | D39: =E5 -> 0.125 | E39: =F5 -> 0 | F39: =G5 -> 0.401
A40: Fiber | B40: =C6 -> 0 | C40: =D6 -> 0 | D40: =E6 -> 0.125 | E40: =F6 -> 0 | F40: =G6 -> 0.125
A41: Stress | B41: =C7 -> 0.026 | C41: =D7 -> 0.25 | D41: =E7 -> 0.125 | E41: =F7 -> 0.1 | F41: =G7 -> 0.501

Sheet Monthly PL Y1 Y2
A1: Monthly P&L, Years 1 and 2 (Months 1 to 24)
A2: ="Active scenario: "&ScenarioName&". Duty: "&DutyScenarioName&". FX "&TEXT(FXRate,"#,##0")&" KRW per USD. Amazon US rows reproduce the August model through Month 18; Year 2 driver changes start in Month 19; eBay, Walmart and B2B rows start in Month 13." -> Active scenario: Medium. Duty: Copper. FX 1,430 KRW per USD. Amazon US rows reproduce the August model through Month 18; Year 2 driver changes start in Month 19; eBay, Walmart and B2B rows start in Month 13.
A3: Monthly P&L engine, active scenario
A4: Line | B4: Unit | C4: Month 0 (pre launch) | D4: Month 1 | E4: Month 2 | F4: Month 3 | G4: Month 4 | H4: Month 5 | I4: Month 6 | J4: Month 7 | K4: Month 8 | L4: Month 9 | M4: Month 10 | N4: Month 11 | O4: Month 12 | P4: Month 13 | Q4: Month 14 | R4: Month 15 | S4: Month 16 | T4: Month 17 | U4: Month 18 | V4: Month 19 | W4: Month 20 | X4: Month 21 | Y4: Month 22 | Z4: Month 23 | AA4: Month 24 | AB4: Year 1 | AC4: Year 2
A5: Month index | C5: 0 | D5: 1 | E5: 2 | F5: 3 | G5: 4 | H5: 5 | I5: 6 | J5: 7 | K5: 8 | L5: 9 | M5: 10 | N5: 11 | O5: 12 | P5: 13 | Q5: 14 | R5: 15 | S5: 16 | T5: 17 | U5: 18 | V5: 19 | W5: 20 | X5: 21 | Y5: 22 | Z5: 23 | AA5: 24 | AB5: Months 1 to 12 | AC5: Months 13 to 24
A6: Amazon US (Months 1 to 18 reproduce the August model; Year 2 driver changes start in Month 19)
A7: Units sold | B7: units | D7: =Assumptions!$F$137 -> 150 | E7: =Assumptions!$F$138 -> 240 | F7: =Assumptions!$F$139 -> 360 | G7: =Assumptions!$F$140 -> 500 | H7: =Assumptions!$F$141 -> 650 | I7: =Assumptions!$F$142 -> 820 | J7: =Assumptions!$F$143 -> 1000 | K7: =Assumptions!$F$144 -> 1200 | L7: =Assumptions!$F$145 -> 1400 | M7: =Assumptions!$F$146 -> 1600 | N7: =Assumptions!$F$147 -> 1800 | O7: =Assumptions!$F$148 -> 2050 | P7: =Assumptions!$F$149 -> 2250 | Q7: =Assumptions!$F$150 -> 2450 | R7: =Assumptions!$F$151 -> 2600 | S7: =Assumptions!$F$152 -> 2750 | T7: =Assumptions!$F$153 -> 2900 | U7: =Assumptions!$F$154 -> 3050 | V7: =Assumptions!$F$155 -> 3150 | W7: =Assumptions!$F$156 -> 3250 | X7: =Assumptions!$F$157 -> 3350 | Y7: =Assumptions!$F$158 -> 3450 | Z7: =Assumptions!$F$159 -> 3550 | AA7: =Assumptions!$F$160 -> 3650 | AB7: =SUM(D7:O7) -> 11770 | AC7: =SUM(P7:AA7) -> 36400
A8: ASP | B8: $ per unit | D8: =Assumptions!$F$10 -> 42 | E8: =Assumptions!$F$10 -> 42 | F8: =Assumptions!$F$10 -> 42 | G8: =Assumptions!$F$10 -> 42 | H8: =Assumptions!$F$10 -> 42 | I8: =Assumptions!$F$10 -> 42 | J8: =Assumptions!$F$10 -> 42 | K8: =Assumptions!$F$10 -> 42 | ... AA8: =Assumptions!$F$10 -> 42 | AB8: =IF(AB7=0,0,AB9/AB7) -> 42 | AC8: =IF(AC7=0,0,AC9/AC7) -> 42
A9: Revenue | B9: $ | D9: =D7*D8 -> 6300 | E9: =E7*E8 -> 10080 | F9: =F7*F8 -> 15120 | G9: =G7*G8 -> 21000 | H9: =H7*H8 -> 27300 | I9: =I7*I8 -> 34440 | J9: =J7*J8 -> 42000 | K9: =K7*K8 -> 50400 | ... AA9: =AA7*AA8 -> 153300 | AB9: =SUM(D9:O9) -> 494340 | AC9: =SUM(P9:AA9) -> 1528800
A10: Landed COGS | B10: $ | D10: =D9*D30 -> 2394 | E10: =E9*E30 -> 3830.4 | F10: =F9*F30 -> 5745.6 | G10: =G9*G30 -> 7980 | H10: =H9*H30 -> 10374 | I10: =I9*I30 -> 13087.2 | J10: =J9*J30 -> 15960 | K10: =K9*K30 -> 19152 | ... AA10: =AA9*AA30 -> 55954.5 | AB10: =SUM(D10:O10) -> 187849.2 | AC10: =SUM(P10:AA10) -> 568092
A11: Referral fee | B11: $ | D11: =D9*Assumptions!$F$19 -> 945 | E11: =E9*Assumptions!$F$19 -> 1512 | F11: =F9*Assumptions!$F$19 -> 2268 | G11: =G9*Assumptions!$F$19 -> 3150 | H11: =H9*Assumptions!$F$19 -> 4095 | I11: =I9*Assumptions!$F$19 -> 5166 | J11: =J9*Assumptions!$F$19 -> 6300 | K11: =K9*Assumptions!$F$19 -> 7560 | ... AA11: =AA9*Assumptions!$F$19 -> 22995 | AB11: =SUM(D11:O11) -> 74151 | AC11: =SUM(P11:AA11) -> 229320
A12: FBA fulfillment | B12: $ | D12: =D7*D31 -> 825 | E12: =E7*E31 -> 1320 | F12: =F7*F31 -> 1980 | G12: =G7*G31 -> 2750 | H12: =H7*H31 -> 3575 | I12: =I7*I31 -> 4510 | J12: =J7*J31 -> 5500 | K12: =K7*K31 -> 6600 | ... AA12: =AA7*AA31 -> 20677.25 | AB12: =SUM(D12:O12) -> 64735 | AC12: =SUM(P12:AA12) -> 203566
A13: Returns | B13: $ | D13: =D9*D32 -> 189 | E13: =E9*E32 -> 302.4 | F13: =F9*F32 -> 453.6 | G13: =G9*G32 -> 630 | H13: =H9*H32 -> 819 | I13: =I9*I32 -> 1033.2 | J13: =J9*J32 -> 1260 | K13: =K9*K32 -> 1512 | ... AA13: =AA9*AA32 -> 3832.5 | AB13: =SUM(D13:O13) -> 14830.2 | AC13: =SUM(P13:AA13) -> 41580
A14: Storage and inbound | B14: $ | D14: =D9*Assumptions!$F$21 -> 126 | E14: =E9*Assumptions!$F$21 -> 201.6 | F14: =F9*Assumptions!$F$21 -> 302.4 | G14: =G9*Assumptions!$F$21 -> 420 | H14: =H9*Assumptions!$F$21 -> 546 | I14: =I9*Assumptions!$F$21 -> 688.8 | J14: =J9*Assumptions!$F$21 -> 840 | K14: =K9*Assumptions!$F$21 -> 1008 | ... AA14: =AA9*Assumptions!$F$21 -> 3066 | AB14: =SUM(D14:O14) -> 9886.8 | AC14: =SUM(P14:AA14) -> 30576
A15: Advertising | B15: $ | D15: =D9*D33 -> 1890 | E15: =E9*E33 -> 3024 | F15: =F9*F33 -> 4536 | G15: =G9*G33 -> 4620 | H15: =H9*H33 -> 6006 | I15: =I9*I33 -> 7576.8 | J15: =J9*J33 -> 6300 | K15: =K9*K33 -> 7560 | ... AA15: =AA9*AA33 -> 16863 | AB15: =SUM(D15:O15) -> 84667.8 | AC15: =SUM(P15:AA15) -> 168168
A16: Contribution, Amazon US (after advertising) | B16: $ | D16: =D9-D10-D11-D12-D13-D14-D15 -> -69 | E16: =E9-E10-E11-E12-E13-E14-E15 -> -110.4 | F16: =F9-F10-F11-F12-F13-F14-F15 -> -165.6 | G16: =G9-G10-G11-G12-G13-G14-G15 -> 1450 | H16: =H9-H10-H11-H12-H13-H14-H15 -> 1885 | I16: =I9-I10-I11-I12-I13-I14-I15 -> 2378 | J16: =J9-J10-J11-J12-J13-J14-J15 -> 5840 | K16: =K9-K10-K11-K12-K13-K14-K15 -> 7008 | ... AA16: =AA9-AA10-AA11-AA12-AA13-AA14-AA15 -> 29911.75 | AB16: =SUM(D16:O16) -> 58220 | AC16: =SUM(P16:AA16) -> 287498
A17: Fixed (software, insurance, misc; people from Year 3) | B17: $ | D17: =IF(D$5>=Assumptions!$F$26,Assumptions!$F$45,Assumptions!$F$17) -> 850 | E17: =IF(E$5>=Assumptions!$F$26,Assumptions!$F$45,Assumptions!$F$17) -> 850 | F17: =IF(F$5>=Assumptions!$F$26,Assumptions!$F$45,Assumptions!$F$17) -> 850 | G17: =IF(G$5>=Assumptions!$F$26,Assumptions!$F$45,Assumptions!$F$17) -> 850 | H17: =IF(H$5>=Assumptions!$F$26,Assumptions!$F$45,Assumptions!$F$17) -> 850 | I17: =IF(I$5>=Assumptions!$F$26,Assumptions!$F$45,Assumptions!$F$17) -> 850 | J17: =IF(J$5>=Assumptions!$F$26,Assumptions!$F$45,Assumptions!$F$17) -> 850 | K17: =IF(K$5>=Assumptions!$F$26,Assumptions!$F$45,Assumptions!$F$17) -> 850 | ... AA17: =IF(AA$5>=Assumptions!$F$26,Assumptions!$F$45,Assumptions!$F$17) -> 1500 | AB17: =SUM(D17:O17) -> 10200 | AC17: =SUM(P17:AA17) -> 14100
A18: Professional seller fee | B18: $ | D18: =Assumptions!$F$22 -> 39.99 | E18: =Assumptions!$F$22 -> 39.99 | F18: =Assumptions!$F$22 -> 39.99 | G18: =Assumptions!$F$22 -> 39.99 | H18: =Assumptions!$F$22 -> 39.99 | I18: =Assumptions!$F$22 -> 39.99 | J18: =Assumptions!$F$22 -> 39.99 | K18: =Assumptions!$F$22 -> 39.99 | ... AA18: =Assumptions!$F$22 -> 39.99 | AB18: =SUM(D18:O18) -> 479.88 | AC18: =SUM(P18:AA18) -> 479.88
A19: One time launch costs | B19: $ | D19: =IF(D$5=1,Assumptions!$F$23,0) -> 9500 | E19: =IF(E$5=1,Assumptions!$F$23,0) -> 0 | F19: =IF(F$5=1,Assumptions!$F$23,0) -> 0 | G19: =IF(G$5=1,Assumptions!$F$23,0) -> 0 | H19: =IF(H$5=1,Assumptions!$F$23,0) -> 0 | I19: =IF(I$5=1,Assumptions!$F$23,0) -> 0 | J19: =IF(J$5=1,Assumptions!$F$23,0) -> 0 | K19: =IF(K$5=1,Assumptions!$F$23,0) -> 0 | ... AA19: =IF(AA$5=1,Assumptions!$F$23,0) -> 0 | AB19: =SUM(D19:O19) -> 9500 | AC19: =SUM(P19:AA19) -> 0
A20: Compliance (Form 5472, Wyoming report, bond, insurance; spread over the months from the Year 2 start month to Month 24) | B20: $ | D20: =IF(D$5>=Assumptions!$F$26,(Assumptions!$F$94+Assumptions!$F$95+Assumptions!$F$96+Assumptions!$F$97)/(24-Assumptions!$F$26+1),0) -> 0 | E20: =IF(E$5>=Assumptions!$F$26,(Assumptions!$F$94+Assumptions!$F$95+Assumptions!$F$96+Assumptions!$F$97)/(24-Assumptions!$F$26+1),0) -> 0 | F20: =IF(F$5>=Assumptions!$F$26,(Assumptions!$F$94+Assumptions!$F$95+Assumptions!$F$96+Assumptions!$F$97)/(24-Assumptions!$F$26+1),0) -> 0 | G20: =IF(G$5>=Assumptions!$F$26,(Assumptions!$F$94+Assumptions!$F$95+Assumptions!$F$96+Assumptions!$F$97)/(24-Assumptions!$F$26+1),0) -> 0 | H20: =IF(H$5>=Assumptions!$F$26,(Assumptions!$F$94+Assumptions!$F$95+Assumptions!$F$96+Assumptions!$F$97)/(24-Assumptions!$F$26+1),0) -> 0 | I20: =IF(I$5>=Assumptions!$F$26,(Assumptions!$F$94+Assumptions!$F$95+Assumptions!$F$96+Assumptions!$F$97)/(24-Assumptions!$F$26+1),0) -> 0 | J20: =IF(J$5>=Assumptions!$F$26,(Assumptions!$F$94+Assumptions!$F$95+Assumptions!$F$96+Assumptions!$F$97)/(24-Assumptions!$F$26+1),0) -> 0 | K20: =IF(K$5>=Assumptions!$F$26,(Assumptions!$F$94+Assumptions!$F$95+Assumptions!$F$96+Assumptions!$F$97)/(24-Assumptions!$F$26+1),0) -> 0 | ... AA20: =IF(AA$5>=Assumptions!$F$26,(Assumptions!$F$94+Assumptions!$F$95+Assumptions!$F$96+Assumptions!$F$97)/(24-Assumptions!$F$26+1),0) -> 426.66667 | AB20: =SUM(D20:O20) -> 0 | AC20: =SUM(P20:AA20) -> 2560
A21: Net, Amazon US after fixed costs (August basis) | B21: $ | D21: =D16-D17-D18-D19-D20 -> -10458.99 | E21: =E16-E17-E18-E19-E20 -> -1000.39 | F21: =F16-F17-F18-F19-F20 -> -1055.59 | G21: =G16-G17-G18-G19-G20 -> 560.01 | H21: =H16-H17-H18-H19-H20 -> 995.01 | I21: =I16-I17-I18-I19-I20 -> 1488.01 | J21: =J16-J17-J18-J19-J20 -> 4950.01 | K21: =K16-K17-K18-K19-K20 -> 6118.01 | ... AA21: =AA16-AA17-AA18-AA19-AA20 -> 27945.093 | AB21: =SUM(D21:O21) -> 38040.12 | AC21: =SUM(P21:AA21) -> 270358.12
A22: Cumulative net | B22: $ | D22: =D21 -> -10458.99 | E22: =D22+E21 -> -11459.38 | F22: =E22+F21 -> -12514.97 | G22: =F22+G21 -> -11954.96 | H22: =G22+H21 -> -10959.95 | I22: =H22+I21 -> -9471.94 | J22: =I22+J21 -> -4521.93 | K22: =J22+K21 -> 1596.08 | L22: =K22+L21 -> 8882.09 | ... AA22: =Z22+AA21 -> 308398.24 | AB22: =O22 -> 38040.12 | AC22: =AA22 -> 308398.24
A23: Net margin | B23: % | D23: =IF(D9=0,0,D21/D9) -> -1.6601571 | E23: =IF(E9=0,0,E21/E9) -> -0.09924504 | F23: =IF(F9=0,0,F21/F9) -> -0.069814153 | G23: =IF(G9=0,0,G21/G9) -> 0.026667143 | H23: =IF(H9=0,0,H21/H9) -> 0.036447253 | I23: =IF(I9=0,0,I21/I9) -> 0.043205865 | J23: =IF(J9=0,0,J21/J9) -> 0.11785738 | K23: =IF(K9=0,0,K21/K9) -> 0.12138909 | ... AC23: =IF(AC9=0,0,AC21/AC9) -> 0.17684335
A24: TACOS (advertising divided by revenue) | B24: % | D24: =IF(D9=0,0,D15/D9) -> 0.3 | E24: =IF(E9=0,0,E15/E9) -> 0.3 | F24: =IF(F9=0,0,F15/F9) -> 0.3 | G24: =IF(G9=0,0,G15/G9) -> 0.22 | H24: =IF(H9=0,0,H15/H9) -> 0.22 | I24: =IF(I9=0,0,I15/I9) -> 0.22 | J24: =IF(J9=0,0,J15/J9) -> 0.15 | K24: =IF(K9=0,0,K15/K9) -> 0.15 | ... AC24: =IF(AC9=0,0,AC15/AC9) -> 0.11
A25: Contribution per unit before advertising | B25: $ per unit | D25: =IF(D7=0,0,(D16+D15)/D7) -> 12.14 | E25: =IF(E7=0,0,(E16+E15)/E7) -> 12.14 | F25: =IF(F7=0,0,(F16+F15)/F7) -> 12.14 | G25: =IF(G7=0,0,(G16+G15)/G7) -> 12.14 | H25: =IF(H7=0,0,(H16+H15)/H7) -> 12.14 | I25: =IF(I7=0,0,(I16+I15)/I7) -> 12.14 | J25: =IF(J7=0,0,(J16+J15)/J7) -> 12.14 | K25: =IF(K7=0,0,(K16+K15)/K7) -> 12.14 | ... AC25: =IF(AC7=0,0,(AC16+AC15)/AC7) -> 12.518297
A26: Contribution per unit after advertising | B26: $ per unit | D26: =IF(D7=0,0,D16/D7) -> -0.46 | E26: =IF(E7=0,0,E16/E7) -> -0.46 | F26: =IF(F7=0,0,F16/F7) -> -0.46 | G26: =IF(G7=0,0,G16/G7) -> 2.9 | H26: =IF(H7=0,0,H16/H7) -> 2.9 | I26: =IF(I7=0,0,I16/I7) -> 2.9 | J26: =IF(J7=0,0,J16/J7) -> 5.84 | K26: =IF(K7=0,0,K16/K7) -> 5.84 | ... AC26: =IF(AC7=0,0,AC16/AC7) -> 7.8982967
A27: Cumulative breakeven flag (1 when cumulative net is at or above 0) | B27: flag | D27: =IF(D22>=0,1,0) -> 0 | E27: =IF(E22>=0,1,0) -> 0 | F27: =IF(F22>=0,1,0) -> 0 | G27: =IF(G22>=0,1,0) -> 0 | H27: =IF(H22>=0,1,0) -> 0 | I27: =IF(I22>=0,1,0) -> 0 | J27: =IF(J22>=0,1,0) -> 0 | K27: =IF(K22>=0,1,0) -> 1 | ... AA27: =IF(AA22>=0,1,0) -> 1
A29: Monthly drivers (from Assumptions)
A30: Landed COGS % of revenue (base plus duty, FX and the Year 2 change from the Year 2 start month) | B30: % | D30: =IF(D$5>=Assumptions!$F$26,LandedPctActive+Assumptions!$F$33,LandedPctActive) -> 0.38 | E30: =IF(E$5>=Assumptions!$F$26,LandedPctActive+Assumptions!$F$33,LandedPctActive) -> 0.38 | F30: =IF(F$5>=Assumptions!$F$26,LandedPctActive+Assumptions!$F$33,LandedPctActive) -> 0.38 | G30: =IF(G$5>=Assumptions!$F$26,LandedPctActive+Assumptions!$F$33,LandedPctActive) -> 0.38 | H30: =IF(H$5>=Assumptions!$F$26,LandedPctActive+Assumptions!$F$33,LandedPctActive) -> 0.38 | I30: =IF(I$5>=Assumptions!$F$26,LandedPctActive+Assumptions!$F$33,LandedPctActive) -> 0.38 | J30: =IF(J$5>=Assumptions!$F$26,LandedPctActive+Assumptions!$F$33,LandedPctActive) -> 0.38 | K30: =IF(K$5>=Assumptions!$F$26,LandedPctActive+Assumptions!$F$33,LandedPctActive) -> 0.38 | ... AA30: =IF(AA$5>=Assumptions!$F$26,LandedPctActive+Assumptions!$F$33,LandedPctActive) -> 0.365 | AB30: =IF(AB9=0,0,AB10/AB9) -> 0.38 | AC30: =IF(AC9=0,0,AC10/AC9) -> 0.37159341
A31: FBA fee per unit (inflation from the Year 2 start month) | B31: $ per unit | D31: =Assumptions!$F$20*IF(D$5>=Assumptions!$F$26,1+Assumptions!$F$32,1) -> 5.5 | E31: =Assumptions!$F$20*IF(E$5>=Assumptions!$F$26,1+Assumptions!$F$32,1) -> 5.5 | F31: =Assumptions!$F$20*IF(F$5>=Assumptions!$F$26,1+Assumptions!$F$32,1) -> 5.5 | G31: =Assumptions!$F$20*IF(G$5>=Assumptions!$F$26,1+Assumptions!$F$32,1) -> 5.5 | H31: =Assumptions!$F$20*IF(H$5>=Assumptions!$F$26,1+Assumptions!$F$32,1) -> 5.5 | I31: =Assumptions!$F$20*IF(I$5>=Assumptions!$F$26,1+Assumptions!$F$32,1) -> 5.5 | J31: =Assumptions!$F$20*IF(J$5>=Assumptions!$F$26,1+Assumptions!$F$32,1) -> 5.5 | K31: =Assumptions!$F$20*IF(K$5>=Assumptions!$F$26,1+Assumptions!$F$32,1) -> 5.5 | ... AA31: =Assumptions!$F$20*IF(AA$5>=Assumptions!$F$26,1+Assumptions!$F$32,1) -> 5.665 | AB31: =IF(AB7=0,0,AB12/AB7) -> 5.5 | AC31: =IF(AC7=0,0,AC12/AC7) -> 5.5924725
A32: Returns % (Year 2 rate from the Year 2 start month) | B32: % | D32: =IF(D$5>=Assumptions!$F$26,Assumptions!$F$31,Assumptions!$F$12) -> 0.03 | E32: =IF(E$5>=Assumptions!$F$26,Assumptions!$F$31,Assumptions!$F$12) -> 0.03 | F32: =IF(F$5>=Assumptions!$F$26,Assumptions!$F$31,Assumptions!$F$12) -> 0.03 | G32: =IF(G$5>=Assumptions!$F$26,Assumptions!$F$31,Assumptions!$F$12) -> 0.03 | H32: =IF(H$5>=Assumptions!$F$26,Assumptions!$F$31,Assumptions!$F$12) -> 0.03 | I32: =IF(I$5>=Assumptions!$F$26,Assumptions!$F$31,Assumptions!$F$12) -> 0.03 | J32: =IF(J$5>=Assumptions!$F$26,Assumptions!$F$31,Assumptions!$F$12) -> 0.03 | K32: =IF(K$5>=Assumptions!$F$26,Assumptions!$F$31,Assumptions!$F$12) -> 0.03 | ... AA32: =IF(AA$5>=Assumptions!$F$26,Assumptions!$F$31,Assumptions!$F$12) -> 0.025 | AB32: =IF(AB9=0,0,AB13/AB9) -> 0.03 | AC32: =IF(AC9=0,0,AC13/AC9) -> 0.027197802
A33: Ad spend % (phases: Months 1 to 3, 4 to 6, 7 to 12, 13 to 18, then the Year 2 start month to 24) | B33: % | D33: =IF(D$5<=3,Assumptions!$F$13,IF(D$5<=6,Assumptions!$F$14,IF(D$5<=12,Assumptions!$F$15,IF(D$5<Assumptions!$F$26,Assumptions!$F$16,Assumptions!$F$27)))) -> 0.3 | E33: =IF(E$5<=3,Assumptions!$F$13,IF(E$5<=6,Assumptions!$F$14,IF(E$5<=12,Assumptions!$F$15,IF(E$5<Assumptions!$F$26,Assumptions!$F$16,Assumptions!$F$27)))) -> 0.3 | F33: =IF(F$5<=3,Assumptions!$F$13,IF(F$5<=6,Assumptions!$F$14,IF(F$5<=12,Assumptions!$F$15,IF(F$5<Assumptions!$F$26,Assumptions!$F$16,Assumptions!$F$27)))) -> 0.3 | G33: =IF(G$5<=3,Assumptions!$F$13,IF(G$5<=6,Assumptions!$F$14,IF(G$5<=12,Assumptions!$F$15,IF(G$5<Assumptions!$F$26,Assumptions!$F$16,Assumptions!$F$27)))) -> 0.22 | H33: =IF(H$5<=3,Assumptions!$F$13,IF(H$5<=6,Assumptions!$F$14,IF(H$5<=12,Assumptions!$F$15,IF(H$5<Assumptions!$F$26,Assumptions!$F$16,Assumptions!$F$27)))) -> 0.22 | I33: =IF(I$5<=3,Assumptions!$F$13,IF(I$5<=6,Assumptions!$F$14,IF(I$5<=12,Assumptions!$F$15,IF(I$5<Assumptions!$F$26,Assumptions!$F$16,Assumptions!$F$27)))) -> 0.22 | J33: =IF(J$5<=3,Assumptions!$F$13,IF(J$5<=6,Assumptions!$F$14,IF(J$5<=12,Assumptions!$F$15,IF(J$5<Assumptions!$F$26,Assumptions!$F$16,Assumptions!$F$27)))) -> 0.15 | K33: =IF(K$5<=3,Assumptions!$F$13,IF(K$5<=6,Assumptions!$F$14,IF(K$5<=12,Assumptions!$F$15,IF(K$5<Assumptions!$F$26,Assumptions!$F$16,Assumptions!$F$27)))) -> 0.15 | ... AA33: =IF(AA$5<=3,Assumptions!$F$13,IF(AA$5<=6,Assumptions!$F$14,IF(AA$5<=12,Assumptions!$F$15,IF(AA$5<Assumptions!$F$26,Assumptions!$F$16,Assumptions!$F$27)))) -> 0.11 | AB33: =IF(AB9=0,0,AB15/AB9) -> 0.17127443 | AC33: =IF(AC9=0,0,AC15/AC9) -> 0.11
A35: Year 2 channels (Months 13 to 24) so Year 2 ties to the annual tab
A36: eBay and Walmart overflow revenue (% of Amazon US revenue) | B36: $ | D36: =IF(D$5>=13,D9*Assumptions!$F$49,0) -> 0 | E36: =IF(E$5>=13,E9*Assumptions!$F$49,0) -> 0 | F36: =IF(F$5>=13,F9*Assumptions!$F$49,0) -> 0 | G36: =IF(G$5>=13,G9*Assumptions!$F$49,0) -> 0 | H36: =IF(H$5>=13,H9*Assumptions!$F$49,0) -> 0 | I36: =IF(I$5>=13,I9*Assumptions!$F$49,0) -> 0 | J36: =IF(J$5>=13,J9*Assumptions!$F$49,0) -> 0 | K36: =IF(K$5>=13,K9*Assumptions!$F$49,0) -> 0 | ... AA36: =IF(AA$5>=13,AA9*Assumptions!$F$49,0) -> 12264 | AB36: =SUM(D36:O36) -> 0 | AC36: =SUM(P36:AA36) -> 122304
A37: eBay and Walmart units | B37: units | D37: =IF(D8=0,0,D36/D8) -> 0 | E37: =IF(E8=0,0,E36/E8) -> 0 | F37: =IF(F8=0,0,F36/F8) -> 0 | G37: =IF(G8=0,0,G36/G8) -> 0 | H37: =IF(H8=0,0,H36/H8) -> 0 | I37: =IF(I8=0,0,I36/I8) -> 0 | J37: =IF(J8=0,0,J36/J8) -> 0 | K37: =IF(K8=0,0,K36/K8) -> 0 | ... AA37: =IF(AA8=0,0,AA36/AA8) -> 292 | AB37: =SUM(D37:O37) -> 0 | AC37: =SUM(P37:AA37) -> 2912
A38: eBay and Walmart landed COGS | B38: $ | D38: =D36*D30 -> 0 | E38: =E36*E30 -> 0 | F38: =F36*F30 -> 0 | G38: =G36*G30 -> 0 | H38: =H36*H30 -> 0 | I38: =I36*I30 -> 0 | J38: =J36*J30 -> 0 | K38: =K36*K30 -> 0 | ... AA38: =AA36*AA30 -> 4476.36 | AB38: =SUM(D38:O38) -> 0 | AC38: =SUM(P38:AA38) -> 45447.36
A39: eBay and Walmart referral | B39: $ | D39: =D36*Assumptions!$F$66 -> 0 | E39: =E36*Assumptions!$F$66 -> 0 | F39: =F36*Assumptions!$F$66 -> 0 | G39: =G36*Assumptions!$F$66 -> 0 | H39: =H36*Assumptions!$F$66 -> 0 | I39: =I36*Assumptions!$F$66 -> 0 | J39: =J36*Assumptions!$F$66 -> 0 | K39: =K36*Assumptions!$F$66 -> 0 | ... AA39: =AA36*Assumptions!$F$66 -> 1594.32 | AB39: =SUM(D39:O39) -> 0 | AC39: =SUM(P39:AA39) -> 15899.52
A40: eBay and Walmart multi channel fulfillment | B40: $ | D40: =D37*Assumptions!$F$67 -> 0 | E40: =E37*Assumptions!$F$67 -> 0 | F40: =F37*Assumptions!$F$67 -> 0 | G40: =G37*Assumptions!$F$67 -> 0 | H40: =H37*Assumptions!$F$67 -> 0 | I40: =I37*Assumptions!$F$67 -> 0 | J40: =J37*Assumptions!$F$67 -> 0 | K40: =K37*Assumptions!$F$67 -> 0 | ... AA40: =AA37*Assumptions!$F$67 -> 1898 | AB40: =SUM(D40:O40) -> 0 | AC40: =SUM(P40:AA40) -> 18928
A41: eBay and Walmart advertising | B41: $ | D41: =D36*Assumptions!$F$68 -> 0 | E41: =E36*Assumptions!$F$68 -> 0 | F41: =F36*Assumptions!$F$68 -> 0 | G41: =G36*Assumptions!$F$68 -> 0 | H41: =H36*Assumptions!$F$68 -> 0 | I41: =I36*Assumptions!$F$68 -> 0 | J41: =J36*Assumptions!$F$68 -> 0 | K41: =K36*Assumptions!$F$68 -> 0 | ... AA41: =AA36*Assumptions!$F$68 -> 613.2 | AB41: =SUM(D41:O41) -> 0 | AC41: =SUM(P41:AA41) -> 6115.2
A42: eBay and Walmart returns | B42: $ | D42: =D36*Assumptions!$F$69 -> 0 | E42: =E36*Assumptions!$F$69 -> 0 | F42: =F36*Assumptions!$F$69 -> 0 | G42: =G36*Assumptions!$F$69 -> 0 | H42: =H36*Assumptions!$F$69 -> 0 | I42: =I36*Assumptions!$F$69 -> 0 | J42: =J36*Assumptions!$F$69 -> 0 | K42: =K36*Assumptions!$F$69 -> 0 | ... AA42: =AA36*Assumptions!$F$69 -> 367.92 | AB42: =SUM(D42:O42) -> 0 | AC42: =SUM(P42:AA42) -> 3669.12
A43: eBay and Walmart contribution | B43: $ | D43: =D36-D38-D39-D40-D41-D42 -> 0 | E43: =E36-E38-E39-E40-E41-E42 -> 0 | F43: =F36-F38-F39-F40-F41-F42 -> 0 | G43: =G36-G38-G39-G40-G41-G42 -> 0 | H43: =H36-H38-H39-H40-H41-H42 -> 0 | I43: =I36-I38-I39-I40-I41-I42 -> 0 | J43: =J36-J38-J39-J40-J41-J42 -> 0 | K43: =K36-K38-K39-K40-K41-K42 -> 0 | ... AA43: =AA36-AA38-AA39-AA40-AA41-AA42 -> 3314.2 | AB43: =SUM(D43:O43) -> 0 | AC43: =SUM(P43:AA43) -> 32244.8
A44: B2B installer and AV integrator revenue (Year 2 total spread evenly) | B44: $ | D44: =IF(D$5>=13,Assumptions!$F$53/12,0) -> 0 | E44: =IF(E$5>=13,Assumptions!$F$53/12,0) -> 0 | F44: =IF(F$5>=13,Assumptions!$F$53/12,0) -> 0 | G44: =IF(G$5>=13,Assumptions!$F$53/12,0) -> 0 | H44: =IF(H$5>=13,Assumptions!$F$53/12,0) -> 0 | I44: =IF(I$5>=13,Assumptions!$F$53/12,0) -> 0 | J44: =IF(J$5>=13,Assumptions!$F$53/12,0) -> 0 | K44: =IF(K$5>=13,Assumptions!$F$53/12,0) -> 0 | ... AA44: =IF(AA$5>=13,Assumptions!$F$53/12,0) -> 10000 | AB44: =SUM(D44:O44) -> 0 | AC44: =SUM(P44:AA44) -> 120000
A45: B2B units (price 60% of retail ASP) | B45: units | D45: =IF(D8=0,0,D44/(D8*Assumptions!$F$70)) -> 0 | E45: =IF(E8=0,0,E44/(E8*Assumptions!$F$70)) -> 0 | F45: =IF(F8=0,0,F44/(F8*Assumptions!$F$70)) -> 0 | G45: =IF(G8=0,0,G44/(G8*Assumptions!$F$70)) -> 0 | H45: =IF(H8=0,0,H44/(H8*Assumptions!$F$70)) -> 0 | I45: =IF(I8=0,0,I44/(I8*Assumptions!$F$70)) -> 0 | J45: =IF(J8=0,0,J44/(J8*Assumptions!$F$70)) -> 0 | K45: =IF(K8=0,0,K44/(K8*Assumptions!$F$70)) -> 0 | ... AA45: =IF(AA8=0,0,AA44/(AA8*Assumptions!$F$70)) -> 396.8254 | AB45: =SUM(D45:O45) -> 0 | AC45: =SUM(P45:AA45) -> 4761.9048
A46: B2B landed COGS | B46: $ | D46: =D45*D8*D30 -> 0 | E46: =E45*E8*E30 -> 0 | F46: =F45*F8*F30 -> 0 | G46: =G45*G8*G30 -> 0 | H46: =H45*H8*H30 -> 0 | I46: =I45*I8*I30 -> 0 | J46: =J45*J8*J30 -> 0 | K46: =K45*K8*K30 -> 0 | ... AA46: =AA45*AA8*AA30 -> 6083.3333 | AB46: =SUM(D46:O46) -> 0 | AC46: =SUM(P46:AA46) -> 74500
A47: B2B 3PL pick pack ship | B47: $ | D47: =D45*Assumptions!$F$71 -> 0 | E47: =E45*Assumptions!$F$71 -> 0 | F47: =F45*Assumptions!$F$71 -> 0 | G47: =G45*Assumptions!$F$71 -> 0 | H47: =H45*Assumptions!$F$71 -> 0 | I47: =I45*Assumptions!$F$71 -> 0 | J47: =J45*Assumptions!$F$71 -> 0 | K47: =K45*Assumptions!$F$71 -> 0 | ... AA47: =AA45*Assumptions!$F$71 -> 1587.3016 | AB47: =SUM(D47:O47) -> 0 | AC47: =SUM(P47:AA47) -> 19047.619
A48: B2B sales commission | B48: $ | D48: =D44*Assumptions!$F$72 -> 0 | E48: =E44*Assumptions!$F$72 -> 0 | F48: =F44*Assumptions!$F$72 -> 0 | G48: =G44*Assumptions!$F$72 -> 0 | H48: =H44*Assumptions!$F$72 -> 0 | I48: =I44*Assumptions!$F$72 -> 0 | J48: =J44*Assumptions!$F$72 -> 0 | K48: =K44*Assumptions!$F$72 -> 0 | ... AA48: =AA44*Assumptions!$F$72 -> 500 | AB48: =SUM(D48:O48) -> 0 | AC48: =SUM(P48:AA48) -> 6000
A49: B2B marketing | B49: $ | D49: =D44*Assumptions!$F$73 -> 0 | E49: =E44*Assumptions!$F$73 -> 0 | F49: =F44*Assumptions!$F$73 -> 0 | G49: =G44*Assumptions!$F$73 -> 0 | H49: =H44*Assumptions!$F$73 -> 0 | I49: =I44*Assumptions!$F$73 -> 0 | J49: =J44*Assumptions!$F$73 -> 0 | K49: =K44*Assumptions!$F$73 -> 0 | ... AA49: =AA44*Assumptions!$F$73 -> 300 | AB49: =SUM(D49:O49) -> 0 | AC49: =SUM(P49:AA49) -> 3600
A50: B2B returns | B50: $ | D50: =D44*Assumptions!$F$74 -> 0 | E50: =E44*Assumptions!$F$74 -> 0 | F50: =F44*Assumptions!$F$74 -> 0 | G50: =G44*Assumptions!$F$74 -> 0 | H50: =H44*Assumptions!$F$74 -> 0 | I50: =I44*Assumptions!$F$74 -> 0 | J50: =J44*Assumptions!$F$74 -> 0 | K50: =K44*Assumptions!$F$74 -> 0 | ... AA50: =AA44*Assumptions!$F$74 -> 200 | AB50: =SUM(D50:O50) -> 0 | AC50: =SUM(P50:AA50) -> 2400
A51: B2B contribution | B51: $ | D51: =D44-D46-D47-D48-D49-D50 -> 0 | E51: =E44-E46-E47-E48-E49-E50 -> 0 | F51: =F44-F46-F47-F48-F49-F50 -> 0 | G51: =G44-G46-G47-G48-G49-G50 -> 0 | H51: =H44-H46-H47-H48-H49-H50 -> 0 | I51: =I44-I46-I47-I48-I49-I50 -> 0 | J51: =J44-J46-J47-J48-J49-J50 -> 0 | K51: =K44-K46-K47-K48-K49-K50 -> 0 | ... AA51: =AA44-AA46-AA47-AA48-AA49-AA50 -> 1329.3651 | AB51: =SUM(D51:O51) -> 0 | AC51: =SUM(P51:AA51) -> 14452.381
A53: All channels
A54: Revenue, all channels | B54: $ | D54: =D9+D36+D44 -> 6300 | E54: =E9+E36+E44 -> 10080 | F54: =F9+F36+F44 -> 15120 | G54: =G9+G36+G44 -> 21000 | H54: =H9+H36+H44 -> 27300 | I54: =I9+I36+I44 -> 34440 | J54: =J9+J36+J44 -> 42000 | K54: =K9+K36+K44 -> 50400 | ... AA54: =AA9+AA36+AA44 -> 175564 | AB54: =SUM(D54:O54) -> 494340 | AC54: =SUM(P54:AA54) -> 1771104
A55: Net, all channels | B55: $ | D55: =D21+D43+D51 -> -10458.99 | E55: =E21+E43+E51 -> -1000.39 | F55: =F21+F43+F51 -> -1055.59 | G55: =G21+G43+G51 -> 560.01 | H55: =H21+H43+H51 -> 995.01 | I55: =I21+I43+I51 -> 1488.01 | J55: =J21+J43+J51 -> 4950.01 | K55: =K21+K43+K51 -> 6118.01 | ... AA55: =AA21+AA43+AA51 -> 32588.658 | AB55: =SUM(D55:O55) -> 38040.12 | AC55: =SUM(P55:AA55) -> 317055.3
A56: Cumulative net, all channels | B56: $ | D56: =D55 -> -10458.99 | E56: =D56+E55 -> -11459.38 | F56: =E56+F55 -> -12514.97 | G56: =F56+G55 -> -11954.96 | H56: =G56+H55 -> -10959.95 | I56: =H56+I55 -> -9471.94 | J56: =I56+J55 -> -4521.93 | K56: =J56+K55 -> 1596.08 | L56: =K56+L55 -> 8882.09 | ... AA56: =Z56+AA55 -> 355095.42 | AB56: =O56 -> 38040.12 | AC56: =AA56 -> 355095.42
A57: Net margin, all channels | B57: % | D57: =IF(D54=0,0,D55/D54) -> -1.6601571 | E57: =IF(E54=0,0,E55/E54) -> -0.09924504 | F57: =IF(F54=0,0,F55/F54) -> -0.069814153 | G57: =IF(G54=0,0,G55/G54) -> 0.026667143 | H57: =IF(H54=0,0,H55/H54) -> 0.036447253 | I57: =IF(I54=0,0,I55/I54) -> 0.043205865 | J57: =IF(J54=0,0,J55/J54) -> 0.11785738 | K57: =IF(K54=0,0,K55/K54) -> 0.12138909 | ... AC57: =IF(AC54=0,0,AC55/AC54) -> 0.17901563
A59: Eighteen month block (Amazon US only, August basis, Months 1 to 18)
A60: 18 month revenue | C60: =SUM(D9:U9) -> 1166340
A61: 18 month net | C61: =SUM(D21:U21) -> 153020.18
A62: 18 month net margin | C62: =IF(C60=0,0,C61/C60) -> 0.13119689
A63: Cumulative breakeven month within 18 months (none if never) | C63: =IFERROR(MATCH(1,D27:U27,0),"none") -> 8
A64: Month 18 run rate (Month 18 revenue times 12) | C64: =U9*12 -> 1537200
A65: Exit margin (Month 18 net margin) | C65: =U23 -> 0.1721
A66: 18 month units | C66: =SUM(D7:U7) -> 27770
A67: Cumulative breakeven month within 24 months (all channels) | C67: =IFERROR(MATCH(1,D27:AA27,0),"none") -> 8
A68: 24 month revenue, all channels | C68: =SUM(D54:AA54) -> 2265444
A69: 24 month net, all channels | C69: =SUM(D55:AA55) -> 355095.42

Sheet Annual PL Y1 to Y5
A1: Annual P&L, Years 1 to 5 by channel
A2: ="Active scenario: "&ScenarioName&". Years 1 and 2 are sums of the monthly tab (check rows show 0). Years 3 to 5 come from the Year 3 to 5 drivers on Assumptions." -> Active scenario: Medium. Years 1 and 2 are sums of the monthly tab (check rows show 0). Years 3 to 5 come from the Year 3 to 5 drivers on Assumptions.
A3: Annual P&L engine, active scenario
A4: Line | B4: Unit | C4: Year 1 | D4: Year 2 | E4: Year 3 | F4: Year 4 | G4: Year 5 | H4: Basis
A5: Amazon US drivers
A6: Amazon US units | B6: units | C6: ='Monthly PL Y1 Y2'!AB7 -> 11770 | D6: ='Monthly PL Y1 Y2'!AC7 -> 36400 | E6: =D6*(1+Assumptions!$F$37) -> 47320 | F6: =E6*(1+Assumptions!$F$38) -> 56784 | G6: =F6*(1+Assumptions!$F$39) -> 63598.08 | H6: Years 1 and 2 from the monthly tab; then unit growth driver
A7: ASP (Years 3 to 5: yearly change plus the Year 3 roadmap mix uplift) | B7: $ per unit | C7: ='Monthly PL Y1 Y2'!AB8 -> 42 | D7: ='Monthly PL Y1 Y2'!AC8 -> 42 | E7: =D7*(1+Assumptions!$F$40)*IF(3=3,1+Assumptions!$F$41,1) -> 41.5296 | F7: =E7*(1+Assumptions!$F$40)*IF(4=3,1+Assumptions!$F$41,1) -> 39.868416 | G7: =F7*(1+Assumptions!$F$40)*IF(5=3,1+Assumptions!$F$41,1) -> 38.273679
A8: Landed COGS % (active base plus duty, FX and the yearly change) | B8: % | C8: ='Monthly PL Y1 Y2'!AB30 -> 0.38 | D8: ='Monthly PL Y1 Y2'!AC30 -> 0.37159341 | E8: =LandedPctActive+Assumptions!$F$34 -> 0.365 | F8: =LandedPctActive+Assumptions!$F$35 -> 0.37 | G8: =LandedPctActive+Assumptions!$F$36 -> 0.375
A9: Ad spend % of revenue | B9: % | C9: ='Monthly PL Y1 Y2'!AB33 -> 0.17127443 | D9: ='Monthly PL Y1 Y2'!AC33 -> 0.11 | E9: =Assumptions!$F$42 -> 0.115 | F9: =Assumptions!$F$43 -> 0.115 | G9: =Assumptions!$F$44 -> 0.115
A10: Returns % | B10: % | C10: ='Monthly PL Y1 Y2'!AB32 -> 0.03 | D10: ='Monthly PL Y1 Y2'!AC32 -> 0.027197802 | E10: =Assumptions!$F$31 -> 0.025 | F10: =Assumptions!$F$31 -> 0.025 | G10: =Assumptions!$F$31 -> 0.025
A11: FBA fee per unit (3% inflation per year) | B11: $ per unit | C11: ='Monthly PL Y1 Y2'!AB31 -> 5.5 | D11: ='Monthly PL Y1 Y2'!AC31 -> 5.5924725 | E11: =Assumptions!$F$20*(1+Assumptions!$F$32)^(3-1) -> 5.83495 | F11: =Assumptions!$F$20*(1+Assumptions!$F$32)^(4-1) -> 6.0099985 | G11: =Assumptions!$F$20*(1+Assumptions!$F$32)^(5-1) -> 6.1902985
A13: Amazon US
A14: Units | B14: units | C14: ='Monthly PL Y1 Y2'!AB7 -> 11770 | D14: ='Monthly PL Y1 Y2'!AC7 -> 36400 | E14: =E6 -> 47320 | F14: =F6 -> 56784 | G14: =G6 -> 63598.08
A15: Revenue | B15: $ | C15: ='Monthly PL Y1 Y2'!AB9 -> 494340 | D15: ='Monthly PL Y1 Y2'!AC9 -> 1528800 | E15: =E14*E7 -> 1965180.7 | F15: =F14*F7 -> 2263888.1 | G15: =G14*G7 -> 2434132.5
A16: Landed COGS | B16: $ | C16: ='Monthly PL Y1 Y2'!AB10 -> 187849.2 | D16: ='Monthly PL Y1 Y2'!AC10 -> 568092 | E16: =E15*E8 -> 717290.95 | F16: =F15*F8 -> 837638.61 | G16: =G15*G8 -> 912799.7
A17: Channel fees (referral, payment, commission) | B17: $ | C17: ='Monthly PL Y1 Y2'!AB11 -> 74151 | D17: ='Monthly PL Y1 Y2'!AC11 -> 229320 | E17: =E15*Assumptions!$F$19 -> 294777.1 | F17: =F15*Assumptions!$F$19 -> 339583.22 | G17: =G15*Assumptions!$F$19 -> 365119.88
A18: Fulfillment (FBA, MCF, 3PL, shipping) | B18: $ | C18: ='Monthly PL Y1 Y2'!AB12 -> 64735 | D18: ='Monthly PL Y1 Y2'!AC12 -> 203566 | E18: =E14*E11 -> 276109.83 | F18: =F14*F11 -> 341271.75 | G18: =G14*G11 -> 393691.1
A19: Advertising and marketing | B19: $ | C19: ='Monthly PL Y1 Y2'!AB15 -> 84667.8 | D19: ='Monthly PL Y1 Y2'!AC15 -> 168168 | E19: =E15*E9 -> 225995.78 | F19: =F15*F9 -> 260347.14 | G19: =G15*G9 -> 279925.24
A20: Returns and storage | B20: $ | C20: ='Monthly PL Y1 Y2'!AB13+'Monthly PL Y1 Y2'!AB14 -> 24717 | D20: ='Monthly PL Y1 Y2'!AC13+'Monthly PL Y1 Y2'!AC14 -> 72156 | E20: =E15*(E10+Assumptions!$F$21) -> 88433.13 | F20: =F15*(F10+Assumptions!$F$21) -> 101874.97 | G20: =G15*(G10+Assumptions!$F$21) -> 109535.96
A21: Contribution | B21: $ | C21: =C15-C16-C17-C18-C19-C20 -> 58220 | D21: =D15-D16-D17-D18-D19-D20 -> 287498 | E21: =E15-E16-E17-E18-E19-E20 -> 362573.88 | F21: =F15-F16-F17-F18-F19-F20 -> 383172.45 | G21: =G15-G16-G17-G18-G19-G20 -> 373060.65
A22: eBay and Walmart overflow
A23: Units | B23: units | C23: ='Monthly PL Y1 Y2'!AB37 -> 0 | D23: ='Monthly PL Y1 Y2'!AC37 -> 2912 | E23: =IF(E7=0,0,E24/E7) -> 4732 | F23: =IF(F7=0,0,F24/F7) -> 6814.08 | G23: =IF(G7=0,0,G24/G7) -> 7631.7696
A24: Revenue | B24: $ | C24: ='Monthly PL Y1 Y2'!AB36 -> 0 | D24: ='Monthly PL Y1 Y2'!AC36 -> 122304 | E24: =E15*Assumptions!$F$50 -> 196518.07 | F24: =F15*Assumptions!$F$51 -> 271666.58 | G24: =G15*Assumptions!$F$52 -> 292095.9
A25: Landed COGS | B25: $ | C25: ='Monthly PL Y1 Y2'!AB38 -> 0 | D25: ='Monthly PL Y1 Y2'!AC38 -> 45447.36 | E25: =E24*E8 -> 71729.095 | F25: =F24*F8 -> 100516.63 | G25: =G24*G8 -> 109535.96
A26: Channel fees (referral, payment, commission) | B26: $ | C26: ='Monthly PL Y1 Y2'!AB39 -> 0 | D26: ='Monthly PL Y1 Y2'!AC39 -> 15899.52 | E26: =E24*Assumptions!$F$66 -> 25547.349 | F26: =F24*Assumptions!$F$66 -> 35316.655 | G26: =G24*Assumptions!$F$66 -> 37972.467
A27: Fulfillment (FBA, MCF, 3PL, shipping) | B27: $ | C27: ='Monthly PL Y1 Y2'!AB40 -> 0 | D27: ='Monthly PL Y1 Y2'!AC40 -> 18928 | E27: =E23*Assumptions!$F$67 -> 30758 | F27: =F23*Assumptions!$F$67 -> 44291.52 | G27: =G23*Assumptions!$F$67 -> 49606.502
A28: Advertising and marketing | B28: $ | C28: ='Monthly PL Y1 Y2'!AB41 -> 0 | D28: ='Monthly PL Y1 Y2'!AC41 -> 6115.2 | E28: =E24*Assumptions!$F$68 -> 9825.9034 | F28: =F24*Assumptions!$F$68 -> 13583.329 | G28: =G24*Assumptions!$F$68 -> 14604.795
A29: Returns and storage | B29: $ | C29: ='Monthly PL Y1 Y2'!AB42 -> 0 | D29: ='Monthly PL Y1 Y2'!AC42 -> 3669.12 | E29: =E24*Assumptions!$F$69 -> 5895.542 | F29: =F24*Assumptions!$F$69 -> 8149.9973 | G29: =G24*Assumptions!$F$69 -> 8762.8771
A30: Contribution | B30: $ | C30: =C24-C25-C26-C27-C28-C29 -> 0 | D30: =D24-D25-D26-D27-D28-D29 -> 32244.8 | E30: =E24-E25-E26-E27-E28-E29 -> 52762.179 | F30: =F24-F25-F26-F27-F28-F29 -> 69808.442 | G30: =G24-G25-G26-G27-G28-G29 -> 71613.297
A31: B2B installer and AV integrator
A32: Units | B32: units | C32: ='Monthly PL Y1 Y2'!AB45 -> 0 | D32: ='Monthly PL Y1 Y2'!AC45 -> 4761.9048 | E32: =IF(E7=0,0,E33/(E7*Assumptions!$F$70)) -> 14046.206 | F32: =IF(F7=0,0,F33/(F7*Assumptions!$F$70)) -> 25082.511 | G32: =IF(G7=0,0,G33/(G7*Assumptions!$F$70)) -> 37014.123
A33: Revenue | B33: $ | C33: ='Monthly PL Y1 Y2'!AB44 -> 0 | D33: ='Monthly PL Y1 Y2'!AC44 -> 120000 | E33: =Assumptions!$F$54 -> 350000 | F33: =Assumptions!$F$55 -> 600000 | G33: =Assumptions!$F$56 -> 850000
A34: Landed COGS | B34: $ | C34: ='Monthly PL Y1 Y2'!AB46 -> 0 | D34: ='Monthly PL Y1 Y2'!AC46 -> 74500 | E34: =E32*E7*E8 -> 212916.67 | F34: =F32*F7*F8 -> 370000 | G34: =G32*G7*G8 -> 531250
A35: Channel fees (referral, payment, commission) | B35: $ | C35: ='Monthly PL Y1 Y2'!AB48 -> 0 | D35: ='Monthly PL Y1 Y2'!AC48 -> 6000 | E35: =E33*Assumptions!$F$72 -> 17500 | F35: =F33*Assumptions!$F$72 -> 30000 | G35: =G33*Assumptions!$F$72 -> 42500
A36: Fulfillment (FBA, MCF, 3PL, shipping) | B36: $ | C36: ='Monthly PL Y1 Y2'!AB47 -> 0 | D36: ='Monthly PL Y1 Y2'!AC47 -> 19047.619 | E36: =E32*Assumptions!$F$71 -> 56184.826 | F36: =F32*Assumptions!$F$71 -> 100330.05 | G36: =G32*Assumptions!$F$71 -> 148056.49
A37: Advertising and marketing | B37: $ | C37: ='Monthly PL Y1 Y2'!AB49 -> 0 | D37: ='Monthly PL Y1 Y2'!AC49 -> 3600 | E37: =E33*Assumptions!$F$73 -> 10500 | F37: =F33*Assumptions!$F$73 -> 18000 | G37: =G33*Assumptions!$F$73 -> 25500
A38: Returns and storage | B38: $ | C38: ='Monthly PL Y1 Y2'!AB50 -> 0 | D38: ='Monthly PL Y1 Y2'!AC50 -> 2400 | E38: =E33*Assumptions!$F$74 -> 7000 | F38: =F33*Assumptions!$F$74 -> 12000 | G38: =G33*Assumptions!$F$74 -> 17000
A39: Contribution | B39: $ | C39: =C33-C34-C35-C36-C37-C38 -> 0 | D39: =D33-D34-D35-D36-D37-D38 -> 14452.381 | E39: =E33-E34-E35-E36-E37-E38 -> 45898.508 | F39: =F33-F34-F35-F36-F37-F38 -> 69669.954 | G39: =G33-G34-G35-G36-G37-G38 -> 85693.509
A40: DTC site
A41: Units | B41: units | C41: =0 -> 0 | D41: =0 -> 0 | E41: =IF(E7=0,0,E42/E7) -> 2407.9211 | F41: =IF(F7=0,0,F42/F7) -> 6270.6279 | G41: =IF(G7=0,0,G42/G7) -> 10451.046
A42: Revenue | B42: $ | C42: =0 -> 0 | D42: =0 -> 0 | E42: =Assumptions!$F$57 -> 100000 | F42: =Assumptions!$F$58 -> 250000 | G42: =Assumptions!$F$59 -> 400000
A43: Landed COGS | B43: $ | C43: =0 -> 0 | D43: =0 -> 0 | E43: =E42*E8 -> 36500 | F43: =F42*F8 -> 92500 | G43: =G42*G8 -> 150000
A44: Channel fees (referral, payment, commission) | B44: $ | C44: =0 -> 0 | D44: =0 -> 0 | E44: =E42*Assumptions!$F$75 -> 3000 | F44: =F42*Assumptions!$F$75 -> 7500 | G44: =G42*Assumptions!$F$75 -> 12000
A45: Fulfillment (FBA, MCF, 3PL, shipping) | B45: $ | C45: =0 -> 0 | D45: =0 -> 0 | E45: =E41*Assumptions!$F$76 -> 26487.132 | F45: =F41*Assumptions!$F$76 -> 68976.906 | G45: =G41*Assumptions!$F$76 -> 114961.51
A46: Advertising and marketing | B46: $ | C46: =0 -> 0 | D46: =0 -> 0 | E46: =E42*Assumptions!$F$77 -> 15000 | F46: =F42*Assumptions!$F$77 -> 37500 | G46: =G42*Assumptions!$F$77 -> 60000
A47: Returns and storage | B47: $ | C47: =0 -> 0 | D47: =0 -> 0 | E47: =E42*Assumptions!$F$78 -> 3000 | F47: =F42*Assumptions!$F$78 -> 7500 | G47: =G42*Assumptions!$F$78 -> 12000
A48: Contribution | B48: $ | C48: =C42-C43-C44-C45-C46-C47 -> 0 | D48: =D42-D43-D44-D45-D46-D47 -> 0 | E48: =E42-E43-E44-E45-E46-E47 -> 16012.868 | F48: =F42-F43-F44-F45-F46-F47 -> 36023.094 | G48: =G42-G43-G44-G45-G46-G47 -> 51038.489
A49: Amazon Canada
A50: Units | B50: units | C50: =0 -> 0 | D50: =0 -> 0 | E50: =IF(E7=0,0,E51/(E7*Assumptions!$F$79)) -> 0 | F50: =IF(F7=0,0,F51/(F7*Assumptions!$F$79)) -> 3271.6319 | G50: =IF(G7=0,0,G51/(G7*Assumptions!$F$79)) -> 7099.8957
A51: Revenue | B51: $ | C51: =0 -> 0 | D51: =0 -> 0 | E51: =0 -> 0 | F51: =Assumptions!$F$60 -> 120000 | G51: =Assumptions!$F$61 -> 250000
A52: Landed COGS | B52: $ | C52: =0 -> 0 | D52: =0 -> 0 | E52: =E50*E7*E8*(1+Assumptions!$F$84) -> 0 | F52: =F50*F7*F8*(1+Assumptions!$F$84) -> 48260.87 | G52: =G50*G7*G8*(1+Assumptions!$F$84) -> 101902.17
A53: Channel fees (referral, payment, commission) | B53: $ | C53: =0 -> 0 | D53: =0 -> 0 | E53: =E51*Assumptions!$F$81 -> 0 | F53: =F51*Assumptions!$F$81 -> 18000 | G53: =G51*Assumptions!$F$81 -> 37500
A54: Fulfillment (FBA, MCF, 3PL, shipping) | B54: $ | C54: =0 -> 0 | D54: =0 -> 0 | E54: =E50*Assumptions!$F$80 -> 0 | F54: =F50*Assumptions!$F$80 -> 21265.608 | G54: =G50*Assumptions!$F$80 -> 46149.322
A55: Advertising and marketing | B55: $ | C55: =0 -> 0 | D55: =0 -> 0 | E55: =E51*Assumptions!$F$82 -> 0 | F55: =F51*Assumptions!$F$82 -> 14400 | G55: =G51*Assumptions!$F$82 -> 30000
A56: Returns and storage | B56: $ | C56: =0 -> 0 | D56: =0 -> 0 | E56: =E51*Assumptions!$F$83 -> 0 | F56: =F51*Assumptions!$F$83 -> 3600 | G56: =G51*Assumptions!$F$83 -> 7500
A57: Contribution | B57: $ | C57: =C51-C52-C53-C54-C55-C56 -> 0 | D57: =D51-D52-D53-D54-D55-D56 -> 0 | E57: =E51-E52-E53-E54-E55-E56 -> 0 | F57: =F51-F52-F53-F54-F55-F56 -> 14473.523 | G57: =G51-G52-G53-G54-G55-G56 -> 26948.504
A58: Pro line (CL3, plenum, conduit pull, long run fiber KVM)
A59: Units | B59: units | C59: =0 -> 0 | D59: =0 -> 0 | E59: =IF(Assumptions!$F$85=0,0,E60/Assumptions!$F$85) -> 0 | F59: =IF(Assumptions!$F$85=0,0,F60/Assumptions!$F$85) -> 1250 | G59: =IF(Assumptions!$F$85=0,0,G60/Assumptions!$F$85) -> 2916.6667
A60: Revenue | B60: $ | C60: =0 -> 0 | D60: =0 -> 0 | E60: =0 -> 0 | F60: =Assumptions!$F$62 -> 150000 | G60: =Assumptions!$F$63 -> 350000
A61: Landed COGS | B61: $ | C61: =0 -> 0 | D61: =0 -> 0 | E61: =E60*Assumptions!$F$86 -> 0 | F61: =F60*Assumptions!$F$86 -> 60000 | G61: =G60*Assumptions!$F$86 -> 140000
A62: Channel fees (referral, payment, commission) | B62: $ | C62: =0 -> 0 | D62: =0 -> 0 | E62: =E60*(Assumptions!$F$87*Assumptions!$F$72+(1-Assumptions!$F$87)*Assumptions!$F$19) -> 0 | F62: =F60*(Assumptions!$F$87*Assumptions!$F$72+(1-Assumptions!$F$87)*Assumptions!$F$19) -> 13500 | G62: =G60*(Assumptions!$F$87*Assumptions!$F$72+(1-Assumptions!$F$87)*Assumptions!$F$19) -> 31500
A63: Fulfillment (FBA, MCF, 3PL, shipping) | B63: $ | C63: =0 -> 0 | D63: =0 -> 0 | E63: =E59*(Assumptions!$F$87*Assumptions!$F$71+(1-Assumptions!$F$87)*Assumptions!$F$88) -> 0 | F63: =F59*(Assumptions!$F$87*Assumptions!$F$71+(1-Assumptions!$F$87)*Assumptions!$F$88) -> 7200 | G63: =G59*(Assumptions!$F$87*Assumptions!$F$71+(1-Assumptions!$F$87)*Assumptions!$F$88) -> 16800
A64: Advertising and marketing | B64: $ | C64: =0 -> 0 | D64: =0 -> 0 | E64: =E60*(Assumptions!$F$87*Assumptions!$F$73+(1-Assumptions!$F$87)*Assumptions!$F$89) -> 0 | F64: =F60*(Assumptions!$F$87*Assumptions!$F$73+(1-Assumptions!$F$87)*Assumptions!$F$89) -> 9900 | G64: =G60*(Assumptions!$F$87*Assumptions!$F$73+(1-Assumptions!$F$87)*Assumptions!$F$89) -> 23100
A65: Returns and storage | B65: $ | C65: =0 -> 0 | D65: =0 -> 0 | E65: =E60*(Assumptions!$F$87*Assumptions!$F$74+(1-Assumptions!$F$87)*(Assumptions!$F$90+Assumptions!$F$91)) -> 0 | F65: =F60*(Assumptions!$F$87*Assumptions!$F$74+(1-Assumptions!$F$87)*(Assumptions!$F$90+Assumptions!$F$91)) -> 4800 | G65: =G60*(Assumptions!$F$87*Assumptions!$F$74+(1-Assumptions!$F$87)*(Assumptions!$F$90+Assumptions!$F$91)) -> 11200
A66: Contribution | B66: $ | C66: =C60-C61-C62-C63-C64-C65 -> 0 | D66: =D60-D61-D62-D63-D64-D65 -> 0 | E66: =E60-E61-E62-E63-E64-E65 -> 0 | F66: =F60-F61-F62-F63-F64-F65 -> 54600 | G66: =G60-G61-G62-G63-G64-G65 -> 127400
A68: Totals
A69: Revenue, all channels | B69: $ | C69: =C15+C24+C33+C42+C51+C60 -> 494340 | D69: =D15+D24+D33+D42+D51+D60 -> 1771104 | E69: =E15+E24+E33+E42+E51+E60 -> 2611698.7 | F69: =F15+F24+F33+F42+F51+F60 -> 3655554.7 | G69: =G15+G24+G33+G42+G51+G60 -> 4576228.4
A70: Landed COGS | B70: $ | C70: =C16+C25+C34+C43+C52+C61 -> 187849.2 | D70: =D16+D25+D34+D43+D52+D61 -> 688039.36 | E70: =E16+E25+E34+E43+E52+E61 -> 1038436.7 | F70: =F16+F25+F34+F43+F52+F61 -> 1508916.1 | G70: =G16+G25+G34+G43+G52+G61 -> 1945487.8
A71: Channel fees | B71: $ | C71: =C17+C26+C35+C44+C53+C62 -> 74151 | D71: =D17+D26+D35+D44+D53+D62 -> 251219.52 | E71: =E17+E26+E35+E44+E53+E62 -> 340824.45 | F71: =F17+F26+F35+F44+F53+F62 -> 443899.88 | G71: =G17+G26+G35+G44+G53+G62 -> 526592.35
A72: Fulfillment | B72: $ | C72: =C18+C27+C36+C45+C54+C63 -> 64735 | D72: =D18+D27+D36+D45+D54+D63 -> 241541.62 | E72: =E18+E27+E36+E45+E54+E63 -> 389539.79 | F72: =F18+F27+F36+F45+F54+F63 -> 583335.83 | G72: =G18+G27+G36+G45+G54+G63 -> 769264.92
A73: Advertising and marketing | B73: $ | C73: =C19+C28+C37+C46+C55+C64 -> 84667.8 | D73: =D19+D28+D37+D46+D55+D64 -> 177883.2 | E73: =E19+E28+E37+E46+E55+E64 -> 261321.68 | F73: =F19+F28+F37+F46+F55+F64 -> 353730.46 | G73: =G19+G28+G37+G46+G55+G64 -> 433130.04
A74: Returns and storage | B74: $ | C74: =C20+C29+C38+C47+C56+C65 -> 24717 | D74: =D20+D29+D38+D47+D56+D65 -> 78225.12 | E74: =E20+E29+E38+E47+E56+E65 -> 104328.67 | F74: =F20+F29+F38+F47+F56+F65 -> 137924.96 | G74: =G20+G29+G38+G47+G56+G65 -> 165998.84
A75: Contribution, all channels | B75: $ | C75: =C21+C30+C39+C48+C57+C66 -> 58220 | D75: =D21+D30+D39+D48+D57+D66 -> 334195.18 | E75: =E21+E30+E39+E48+E57+E66 -> 477247.44 | F75: =F21+F30+F39+F48+F57+F66 -> 627747.46 | G75: =G21+G30+G39+G48+G57+G66 -> 735754.45
A76: Fixed costs (software, insurance, people, tools) | B76: $ | C76: ='Monthly PL Y1 Y2'!AB17 -> 10200 | D76: ='Monthly PL Y1 Y2'!AC17 -> 14100 | E76: =Assumptions!$F$46*12 -> 48000 | F76: =Assumptions!$F$47*12 -> 84000 | G76: =Assumptions!$F$48*12 -> 120000 | H76: Years 1 and 2 from the monthly tab; Year 3 adds Mark consulting retainer, VA, tools and insurance
A77: Professional seller fee | B77: $ | C77: ='Monthly PL Y1 Y2'!AB18 -> 479.88 | D77: ='Monthly PL Y1 Y2'!AC18 -> 479.88 | E77: =Assumptions!$F$22*12 -> 479.88 | F77: =Assumptions!$F$22*12 -> 479.88 | G77: =Assumptions!$F$22*12 -> 479.88
A78: One time launch costs | B78: $ | C78: ='Monthly PL Y1 Y2'!AB19 -> 9500 | D78: ='Monthly PL Y1 Y2'!AC19 -> 0 | E78: =0 -> 0 | F78: =0 -> 0 | G78: =0 -> 0
A79: Compliance (Form 5472, Wyoming report, bond, insurance, trademark maintenance) | B79: $ | C79: ='Monthly PL Y1 Y2'!AB20 -> 0 | D79: ='Monthly PL Y1 Y2'!AC20 -> 2560 | E79: =Assumptions!$F$94+Assumptions!$F$95+Assumptions!$F$96+Assumptions!$F$97+IF(3=5,Assumptions!$F$98,0) -> 2560 | F79: =Assumptions!$F$94+Assumptions!$F$95+Assumptions!$F$96+Assumptions!$F$97+IF(4=5,Assumptions!$F$98,0) -> 2560 | G79: =Assumptions!$F$94+Assumptions!$F$95+Assumptions!$F$96+Assumptions!$F$97+IF(5=5,Assumptions!$F$98,0) -> 2560 | H79: Year 1 compliance is inside the August fixed 850 per month and the 9,500 launch costs
A80: Net | B80: $ | C80: =C75-C76-C77-C78-C79 -> 38040.12 | D80: =D75-D76-D77-D78-D79 -> 317055.3 | E80: =E75-E76-E77-E78-E79 -> 426207.56 | F80: =F75-F76-F77-F78-F79 -> 540707.58 | G80: =G75-G76-G77-G78-G79 -> 612714.57
A81: Net margin | B81: % | C81: =IF(C69=0,0,C80/C69) -> 0.076951329 | D81: =IF(D69=0,0,D80/D69) -> 0.17901563 | E81: =IF(E69=0,0,E80/E69) -> 0.1631917 | F81: =IF(F69=0,0,F80/F69) -> 0.14791396 | G81: =IF(G69=0,0,G80/G69) -> 0.13389073
A82: Cumulative net, 5 years | B82: $ | C82: =C80 -> 38040.12 | D82: =C82+D80 -> 355095.42 | E82: =D82+E80 -> 781302.98 | F82: =E82+F80 -> 1322010.6 | G82: =F82+G80 -> 1934725.1
A83: Amazon US contribution margin after advertising (compression check) | B83: % | C83: =IF(C15=0,0,C21/C15) -> 0.11777319 | D83: =IF(D15=0,0,D21/D15) -> 0.18805468 | E83: =IF(E15=0,0,E21/E15) -> 0.18449901 | F83: =IF(F15=0,0,F21/F15) -> 0.16925414 | G83: =IF(G15=0,0,G21/G15) -> 0.15326226
A85: Check rows (must be 0): annual minus monthly tab
A86: Revenue check, Year 1 and Year 2 (annual minus monthly) | C86: =C69-'Monthly PL Y1 Y2'!AB54 -> 0 | D86: =D69-'Monthly PL Y1 Y2'!AC54 -> 0
A87: Net check, Year 1 and Year 2 (annual minus monthly) | C87: =C80-'Monthly PL Y1 Y2'!AB55 -> 0 | D87: =D80-'Monthly PL Y1 Y2'!AC55 -> 0

Sheet Cash Flow and Working Capital
A1: Cash Flow and Working Capital
A2: ="Active scenario: "&ScenarioName&". Inventory cover, PO deposits, air then ocean lead times, 14 day payout lag, in transit stock funded by the business. Peak cash need, funding gap and runway below." -> Active scenario: Medium. Inventory cover, PO deposits, air then ocean lead times, 14 day payout lag, in transit stock funded by the business. Peak cash need, funding gap and runway below.
A3: Cash flow engine, active scenario
A4: Line | B4: Unit | C4: Month 0 (pre launch) | D4: Month 1 | E4: Month 2 | F4: Month 3 | G4: Month 4 | H4: Month 5 | I4: Month 6 | J4: Month 7 | K4: Month 8 | L4: Month 9 | M4: Month 10 | N4: Month 11 | O4: Month 12 | P4: Month 13 | Q4: Month 14 | R4: Month 15 | S4: Month 16 | T4: Month 17 | U4: Month 18 | V4: Month 19 | W4: Month 20 | X4: Month 21 | Y4: Month 22 | Z4: Month 23 | AA4: Month 24 | AB4: Month 25 forecast (planning only) | AC4: Month 26 forecast (planning only) | AD4: Month 27 forecast (planning only) | AE4: Month 28 forecast (planning only) | AF4: Month 29 forecast (planning only) | AG4: Month 30 forecast (planning only)
A5: Month index | C5: 0 | D5: 1 | E5: 2 | F5: 3 | G5: 4 | H5: 5 | I5: 6 | J5: 7 | K5: 8 | L5: 9 | M5: 10 | N5: 11 | O5: 12 | P5: 13 | Q5: 14 | R5: 15 | S5: 16 | T5: 17 | U5: 18 | V5: 19 | W5: 20 | X5: 21 | Y5: 22 | Z5: 23 | AA5: 24 | AB5: 25 | AC5: 26 | AD5: 27 | AE5: 28 | AF5: 29 | AG5: 30
A6: Inventory plan (units; one pool at the P&L landed cost)
A7: Units sold, all channels (Months 25 to 30: Month 24 times 1 plus Year 3 growth) | B7: units | C7: =0 -> 0 | D7: ='Monthly PL Y1 Y2'!D7+'Monthly PL Y1 Y2'!D37+'Monthly PL Y1 Y2'!D45 -> 150 | E7: ='Monthly PL Y1 Y2'!E7+'Monthly PL Y1 Y2'!E37+'Monthly PL Y1 Y2'!E45 -> 240 | F7: ='Monthly PL Y1 Y2'!F7+'Monthly PL Y1 Y2'!F37+'Monthly PL Y1 Y2'!F45 -> 360 | G7: ='Monthly PL Y1 Y2'!G7+'Monthly PL Y1 Y2'!G37+'Monthly PL Y1 Y2'!G45 -> 500 | H7: ='Monthly PL Y1 Y2'!H7+'Monthly PL Y1 Y2'!H37+'Monthly PL Y1 Y2'!H45 -> 650 | I7: ='Monthly PL Y1 Y2'!I7+'Monthly PL Y1 Y2'!I37+'Monthly PL Y1 Y2'!I45 -> 820 | J7: ='Monthly PL Y1 Y2'!J7+'Monthly PL Y1 Y2'!J37+'Monthly PL Y1 Y2'!J45 -> 1000 | K7: ='Monthly PL Y1 Y2'!K7+'Monthly PL Y1 Y2'!K37+'Monthly PL Y1 Y2'!K45 -> 1200 | ... AA7: ='Monthly PL Y1 Y2'!AA7+'Monthly PL Y1 Y2'!AA37+'Monthly PL Y1 Y2'!AA45 -> 4338.8254 | AB7: =$AA7*(1+Assumptions!$F$37) -> 5640.473 | AC7: =$AA7*(1+Assumptions!$F$37) -> 5640.473 | AD7: =$AA7*(1+Assumptions!$F$37) -> 5640.473 | AE7: =$AA7*(1+Assumptions!$F$37) -> 5640.473 | AF7: =$AA7*(1+Assumptions!$F$37) -> 5640.473 | AG7: =$AA7*(1+Assumptions!$F$37) -> 5640.473
A8: Landed cost per unit (landed % times ASP) | B8: $ per unit | D8: ='Monthly PL Y1 Y2'!D30*'Monthly PL Y1 Y2'!D8 -> 15.96 | E8: ='Monthly PL Y1 Y2'!E30*'Monthly PL Y1 Y2'!E8 -> 15.96 | F8: ='Monthly PL Y1 Y2'!F30*'Monthly PL Y1 Y2'!F8 -> 15.96 | G8: ='Monthly PL Y1 Y2'!G30*'Monthly PL Y1 Y2'!G8 -> 15.96 | H8: ='Monthly PL Y1 Y2'!H30*'Monthly PL Y1 Y2'!H8 -> 15.96 | I8: ='Monthly PL Y1 Y2'!I30*'Monthly PL Y1 Y2'!I8 -> 15.96 | J8: ='Monthly PL Y1 Y2'!J30*'Monthly PL Y1 Y2'!J8 -> 15.96 | K8: ='Monthly PL Y1 Y2'!K30*'Monthly PL Y1 Y2'!K8 -> 15.96 | ... AA8: ='Monthly PL Y1 Y2'!AA30*'Monthly PL Y1 Y2'!AA8 -> 15.33 | AB8: =$AA8 -> 15.33 | AC8: =$AA8 -> 15.33 | AD8: =$AA8 -> 15.33 | AE8: =$AA8 -> 15.33 | AF8: =$AA8 -> 15.33 | AG8: =$AA8 -> 15.33
A9: FOB per unit paid to the factory (hero FOB USD at the active FX) | B9: $ per unit | D9: =HeroFobUsd -> 7.3793007 | E9: =HeroFobUsd -> 7.3793007 | F9: =HeroFobUsd -> 7.3793007 | G9: =HeroFobUsd -> 7.3793007 | H9: =HeroFobUsd -> 7.3793007 | I9: =HeroFobUsd -> 7.3793007 | J9: =HeroFobUsd -> 7.3793007 | K9: =HeroFobUsd -> 7.3793007 | ... AG9: =HeroFobUsd -> 7.3793007
A10: Freight, duty, broker, inbound and QC per unit (landed minus FOB), paid on arrival | B10: $ per unit | D10: =D8-D9 -> 8.5806993 | E10: =E8-E9 -> 8.5806993 | F10: =F8-F9 -> 8.5806993 | G10: =G8-G9 -> 8.5806993 | H10: =H8-H9 -> 8.5806993 | I10: =I8-I9 -> 8.5806993 | J10: =J8-J9 -> 8.5806993 | K10: =K8-K9 -> 8.5806993 | ... AG10: =AG8-AG9 -> 7.9506993
A11: Target closing stock (cover months times the average of the next three months of sales) | B11: units | D11: =Assumptions!$F$101*AVERAGE(E7:G7) -> 916.66667 | E11: =Assumptions!$F$101*AVERAGE(F7:H7) -> 1258.3333 | F11: =Assumptions!$F$101*AVERAGE(G7:I7) -> 1641.6667 | G11: =Assumptions!$F$101*AVERAGE(H7:J7) -> 2058.3333 | H11: =Assumptions!$F$101*AVERAGE(I7:K7) -> 2516.6667 | I11: =Assumptions!$F$101*AVERAGE(J7:L7) -> 3000 | J11: =Assumptions!$F$101*AVERAGE(K7:M7) -> 3500 | K11: =Assumptions!$F$101*AVERAGE(L7:N7) -> 4000 | ... AC11: =Assumptions!$F$101*AVERAGE(AD7:AF7) -> 14101.183
A12: Opening stock | B12: units | D12: =0 -> 0 | E12: =D14 -> 916.66667 | F12: =E14 -> 1258.3333 | G12: =F14 -> 1641.6667 | H12: =G14 -> 2058.3333 | I12: =H14 -> 2516.6667 | J12: =I14 -> 3000 | K12: =J14 -> 3500 | L12: =K14 -> 4000 | ... AC12: =AB14 -> 14101.183
A13: Arrivals (purchase order quantity landing this month) | B13: units | D13: =MAX(0,D11-(D12-D7)) -> 1066.6667 | E13: =MAX(0,E11-(E12-E7)) -> 581.66667 | F13: =MAX(0,F11-(F12-F7)) -> 743.33333 | G13: =MAX(0,G11-(G12-G7)) -> 916.66667 | H13: =MAX(0,H11-(H12-H7)) -> 1108.3333 | I13: =MAX(0,I11-(I12-I7)) -> 1303.3333 | J13: =MAX(0,J11-(J12-J7)) -> 1500 | K13: =MAX(0,K11-(K12-K7)) -> 1700 | ... AC13: =MAX(0,AC11-(AC12-AC7)) -> 5640.473
A14: Closing stock | B14: units | D14: =D12+D13-D7 -> 916.66667 | E14: =E12+E13-E7 -> 1258.3333 | F14: =F12+F13-F7 -> 1641.6667 | G14: =G12+G13-G7 -> 2058.3333 | H14: =H12+H13-H7 -> 2516.6667 | I14: =I12+I13-I7 -> 3000 | J14: =J12+J13-J7 -> 3500 | K14: =K12+K13-K7 -> 4000 | ... AC14: =AC12+AC13-AC7 -> 14101.183
A15: Lead time, months (air lead time until the ocean switch month, then the ocean lead time; both on Assumptions) | B15: months | D15: =IF(D$5>=Assumptions!$F$102,Assumptions!$F$104,Assumptions!$F$103) -> 1 | E15: =IF(E$5>=Assumptions!$F$102,Assumptions!$F$104,Assumptions!$F$103) -> 1 | F15: =IF(F$5>=Assumptions!$F$102,Assumptions!$F$104,Assumptions!$F$103) -> 1 | G15: =IF(G$5>=Assumptions!$F$102,Assumptions!$F$104,Assumptions!$F$103) -> 1 | H15: =IF(H$5>=Assumptions!$F$102,Assumptions!$F$104,Assumptions!$F$103) -> 1 | I15: =IF(I$5>=Assumptions!$F$102,Assumptions!$F$104,Assumptions!$F$103) -> 1 | J15: =IF(J$5>=Assumptions!$F$102,Assumptions!$F$104,Assumptions!$F$103) -> 2 | K15: =IF(K$5>=Assumptions!$F$102,Assumptions!$F$104,Assumptions!$F$103) -> 2 | ... AC15: =IF(AC$5>=Assumptions!$F$102,Assumptions!$F$104,Assumptions!$F$103) -> 2
A16: Order month for this arrival (deposit paid) | B16: month | D16: =D$5-D15 -> 0 | E16: =E$5-E15 -> 1 | F16: =F$5-F15 -> 2 | G16: =G$5-G15 -> 3 | H16: =H$5-H15 -> 4 | I16: =I$5-I15 -> 5 | J16: =J$5-J15 -> 5 | K16: =K$5-K15 -> 6 | ... AC16: =AC$5-AC15 -> 24
A17: Shipment month for this arrival (balance paid; goods in transit until arrival) | B17: month | D17: =D$5-1 -> 0 | E17: =E$5-1 -> 1 | F17: =F$5-1 -> 2 | G17: =G$5-1 -> 3 | H17: =H$5-1 -> 4 | I17: =I$5-1 -> 5 | J17: =J$5-1 -> 6 | K17: =K$5-1 -> 7 | ... AC17: =AC$5-1 -> 25
A18: FOB value of arrivals | B18: $ | D18: =D13*D9 -> 7871.2541 | E18: =E13*E9 -> 4292.2932 | F18: =F13*F9 -> 5485.2802 | G18: =G13*G9 -> 6764.359 | H18: =H13*H9 -> 8178.7249 | I18: =I13*I9 -> 9617.6886 | J18: =J13*J9 -> 11068.951 | K18: =K13*K9 -> 12544.811 | ... AC18: =AC13*AC9 -> 41622.746
A19: Freight, duty and fees on arrivals | B19: $ | D19: =D13*D10 -> 9152.7459 | E19: =E13*E10 -> 4991.1068 | F19: =F13*F10 -> 6378.3198 | G19: =G13*G10 -> 7865.641 | H19: =H13*H10 -> 9510.2751 | I19: =I13*I10 -> 11183.511 | J19: =J13*J10 -> 12871.049 | K19: =K13*K10 -> 14587.189 | ... AC19: =AC13*AC10 -> 44845.705
A21: Cash flow (direct method)
A22: PO deposits paid (30% at order) | B22: $ | C22: =Assumptions!$F$107*SUMPRODUCT(($D$16:$AC$16=C$5)*$D$18:$AC$18) -> 2361.3762 | D22: =Assumptions!$F$107*SUMPRODUCT(($D$16:$AC$16=D$5)*$D$18:$AC$18) -> 1287.688 | E22: =Assumptions!$F$107*SUMPRODUCT(($D$16:$AC$16=E$5)*$D$18:$AC$18) -> 1645.5841 | F22: =Assumptions!$F$107*SUMPRODUCT(($D$16:$AC$16=F$5)*$D$18:$AC$18) -> 2029.3077 | G22: =Assumptions!$F$107*SUMPRODUCT(($D$16:$AC$16=G$5)*$D$18:$AC$18) -> 2453.6175 | H22: =Assumptions!$F$107*SUMPRODUCT(($D$16:$AC$16=H$5)*$D$18:$AC$18) -> 6205.9919 | I22: =Assumptions!$F$107*SUMPRODUCT(($D$16:$AC$16=I$5)*$D$18:$AC$18) -> 3763.4434 | J22: =Assumptions!$F$107*SUMPRODUCT(($D$16:$AC$16=J$5)*$D$18:$AC$18) -> 4298.4427 | ... AA22: =Assumptions!$F$107*SUMPRODUCT(($D$16:$AC$16=AA$5)*$D$18:$AC$18) -> 12486.824
A23: PO balances paid (70% at shipment) | B23: $ | C23: =(1-Assumptions!$F$107)*SUMPRODUCT(($D$17:$AC$17=C$5)*$D$18:$AC$18) -> 5509.8779 | D23: =(1-Assumptions!$F$107)*SUMPRODUCT(($D$17:$AC$17=D$5)*$D$18:$AC$18) -> 3004.6053 | E23: =(1-Assumptions!$F$107)*SUMPRODUCT(($D$17:$AC$17=E$5)*$D$18:$AC$18) -> 3839.6961 | F23: =(1-Assumptions!$F$107)*SUMPRODUCT(($D$17:$AC$17=F$5)*$D$18:$AC$18) -> 4735.0513 | G23: =(1-Assumptions!$F$107)*SUMPRODUCT(($D$17:$AC$17=G$5)*$D$18:$AC$18) -> 5725.1075 | H23: =(1-Assumptions!$F$107)*SUMPRODUCT(($D$17:$AC$17=H$5)*$D$18:$AC$18) -> 6732.382 | I23: =(1-Assumptions!$F$107)*SUMPRODUCT(($D$17:$AC$17=I$5)*$D$18:$AC$18) -> 7748.2657 | J23: =(1-Assumptions!$F$107)*SUMPRODUCT(($D$17:$AC$17=J$5)*$D$18:$AC$18) -> 8781.3678 | ... AA23: =(1-Assumptions!$F$107)*SUMPRODUCT(($D$17:$AC$17=AA$5)*$D$18:$AC$18) -> 29135.923
A24: Freight, duty, broker, inbound and QC paid on arrival | B24: $ | C24: =0 -> 0 | D24: =D19 -> 9152.7459 | E24: =E19 -> 4991.1068 | F24: =F19 -> 6378.3198 | G24: =G19 -> 7865.641 | H24: =H19 -> 9510.2751 | I24: =I19 -> 11183.511 | J24: =J19 -> 12871.049 | K24: =K19 -> 14587.189 | ... AA24: =AA19 -> 43120.87
A25: Inventory cash out | B25: $ | C25: =C22+C23+C24 -> 7871.2541 | D25: =D22+D23+D24 -> 13445.039 | E25: =E22+E23+E24 -> 10476.387 | F25: =F22+F23+F24 -> 13142.679 | G25: =G22+G23+G24 -> 16044.366 | H25: =H22+H23+H24 -> 22448.649 | I25: =I22+I23+I24 -> 22695.221 | J25: =J22+J23+J24 -> 25950.859 | ... AA25: =AA22+AA23+AA24 -> 84743.617
A26: Amazon net proceeds (revenue less referral, FBA, returns, storage, advertising) | B26: $ | C26: =0 -> 0 | D26: ='Monthly PL Y1 Y2'!D9-'Monthly PL Y1 Y2'!D11-'Monthly PL Y1 Y2'!D12-'Monthly PL Y1 Y2'!D13-'Monthly PL Y1 Y2'!D14-'Monthly PL Y1 Y2'!D15 -> 2325 | E26: ='Monthly PL Y1 Y2'!E9-'Monthly PL Y1 Y2'!E11-'Monthly PL Y1 Y2'!E12-'Monthly PL Y1 Y2'!E13-'Monthly PL Y1 Y2'!E14-'Monthly PL Y1 Y2'!E15 -> 3720 | F26: ='Monthly PL Y1 Y2'!F9-'Monthly PL Y1 Y2'!F11-'Monthly PL Y1 Y2'!F12-'Monthly PL Y1 Y2'!F13-'Monthly PL Y1 Y2'!F14-'Monthly PL Y1 Y2'!F15 -> 5580 | G26: ='Monthly PL Y1 Y2'!G9-'Monthly PL Y1 Y2'!G11-'Monthly PL Y1 Y2'!G12-'Monthly PL Y1 Y2'!G13-'Monthly PL Y1 Y2'!G14-'Monthly PL Y1 Y2'!G15 -> 9430 | H26: ='Monthly PL Y1 Y2'!H9-'Monthly PL Y1 Y2'!H11-'Monthly PL Y1 Y2'!H12-'Monthly PL Y1 Y2'!H13-'Monthly PL Y1 Y2'!H14-'Monthly PL Y1 Y2'!H15 -> 12259 | I26: ='Monthly PL Y1 Y2'!I9-'Monthly PL Y1 Y2'!I11-'Monthly PL Y1 Y2'!I12-'Monthly PL Y1 Y2'!I13-'Monthly PL Y1 Y2'!I14-'Monthly PL Y1 Y2'!I15 -> 15465.2 | J26: ='Monthly PL Y1 Y2'!J9-'Monthly PL Y1 Y2'!J11-'Monthly PL Y1 Y2'!J12-'Monthly PL Y1 Y2'!J13-'Monthly PL Y1 Y2'!J14-'Monthly PL Y1 Y2'!J15 -> 21800 | K26: ='Monthly PL Y1 Y2'!K9-'Monthly PL Y1 Y2'!K11-'Monthly PL Y1 Y2'!K12-'Monthly PL Y1 Y2'!K13-'Monthly PL Y1 Y2'!K14-'Monthly PL Y1 Y2'!K15 -> 26160 | ... AA26: ='Monthly PL Y1 Y2'!AA9-'Monthly PL Y1 Y2'!AA11-'Monthly PL Y1 Y2'!AA12-'Monthly PL Y1 Y2'!AA13-'Monthly PL Y1 Y2'!AA14-'Monthly PL Y1 Y2'!AA15 -> 85866.25
A27: Other channel net proceeds (eBay and Walmart, B2B) | B27: $ | C27: =0 -> 0 | D27: ='Monthly PL Y1 Y2'!D36-'Monthly PL Y1 Y2'!D39-'Monthly PL Y1 Y2'!D40-'Monthly PL Y1 Y2'!D41-'Monthly PL Y1 Y2'!D42+'Monthly PL Y1 Y2'!D44-'Monthly PL Y1 Y2'!D47-'Monthly PL Y1 Y2'!D48-'Monthly PL Y1 Y2'!D49-'Monthly PL Y1 Y2'!D50 -> 0 | E27: ='Monthly PL Y1 Y2'!E36-'Monthly PL Y1 Y2'!E39-'Monthly PL Y1 Y2'!E40-'Monthly PL Y1 Y2'!E41-'Monthly PL Y1 Y2'!E42+'Monthly PL Y1 Y2'!E44-'Monthly PL Y1 Y2'!E47-'Monthly PL Y1 Y2'!E48-'Monthly PL Y1 Y2'!E49-'Monthly PL Y1 Y2'!E50 -> 0 | F27: ='Monthly PL Y1 Y2'!F36-'Monthly PL Y1 Y2'!F39-'Monthly PL Y1 Y2'!F40-'Monthly PL Y1 Y2'!F41-'Monthly PL Y1 Y2'!F42+'Monthly PL Y1 Y2'!F44-'Monthly PL Y1 Y2'!F47-'Monthly PL Y1 Y2'!F48-'Monthly PL Y1 Y2'!F49-'Monthly PL Y1 Y2'!F50 -> 0 | G27: ='Monthly PL Y1 Y2'!G36-'Monthly PL Y1 Y2'!G39-'Monthly PL Y1 Y2'!G40-'Monthly PL Y1 Y2'!G41-'Monthly PL Y1 Y2'!G42+'Monthly PL Y1 Y2'!G44-'Monthly PL Y1 Y2'!G47-'Monthly PL Y1 Y2'!G48-'Monthly PL Y1 Y2'!G49-'Monthly PL Y1 Y2'!G50 -> 0 | H27: ='Monthly PL Y1 Y2'!H36-'Monthly PL Y1 Y2'!H39-'Monthly PL Y1 Y2'!H40-'Monthly PL Y1 Y2'!H41-'Monthly PL Y1 Y2'!H42+'Monthly PL Y1 Y2'!H44-'Monthly PL Y1 Y2'!H47-'Monthly PL Y1 Y2'!H48-'Monthly PL Y1 Y2'!H49-'Monthly PL Y1 Y2'!H50 -> 0 | I27: ='Monthly PL Y1 Y2'!I36-'Monthly PL Y1 Y2'!I39-'Monthly PL Y1 Y2'!I40-'Monthly PL Y1 Y2'!I41-'Monthly PL Y1 Y2'!I42+'Monthly PL Y1 Y2'!I44-'Monthly PL Y1 Y2'!I47-'Monthly PL Y1 Y2'!I48-'Monthly PL Y1 Y2'!I49-'Monthly PL Y1 Y2'!I50 -> 0 | J27: ='Monthly PL Y1 Y2'!J36-'Monthly PL Y1 Y2'!J39-'Monthly PL Y1 Y2'!J40-'Monthly PL Y1 Y2'!J41-'Monthly PL Y1 Y2'!J42+'Monthly PL Y1 Y2'!J44-'Monthly PL Y1 Y2'!J47-'Monthly PL Y1 Y2'!J48-'Monthly PL Y1 Y2'!J49-'Monthly PL Y1 Y2'!J50 -> 0 | K27: ='Monthly PL Y1 Y2'!K36-'Monthly PL Y1 Y2'!K39-'Monthly PL Y1 Y2'!K40-'Monthly PL Y1 Y2'!K41-'Monthly PL Y1 Y2'!K42+'Monthly PL Y1 Y2'!K44-'Monthly PL Y1 Y2'!K47-'Monthly PL Y1 Y2'!K48-'Monthly PL Y1 Y2'!K49-'Monthly PL Y1 Y2'!K50 -> 0 | ... AA27: ='Monthly PL Y1 Y2'!AA36-'Monthly PL Y1 Y2'!AA39-'Monthly PL Y1 Y2'!AA40-'Monthly PL Y1 Y2'!AA41-'Monthly PL Y1 Y2'!AA42+'Monthly PL Y1 Y2'!AA44-'Monthly PL Y1 Y2'!AA47-'Monthly PL Y1 Y2'!AA48-'Monthly PL Y1 Y2'!AA49-'Monthly PL Y1 Y2'!AA50 -> 15203.258
A28: Receivable at month end (payout lag days / 30 of the month's net proceeds) | B28: $ | C28: =(C26+C27)*Assumptions!$F$108/30 -> 0 | D28: =(D26+D27)*Assumptions!$F$108/30 -> 1085 | E28: =(E26+E27)*Assumptions!$F$108/30 -> 1736 | F28: =(F26+F27)*Assumptions!$F$108/30 -> 2604 | G28: =(G26+G27)*Assumptions!$F$108/30 -> 4400.6667 | H28: =(H26+H27)*Assumptions!$F$108/30 -> 5720.8667 | I28: =(I26+I27)*Assumptions!$F$108/30 -> 7217.0933 | J28: =(J26+J27)*Assumptions!$F$108/30 -> 10173.333 | ... AA28: =(AA26+AA27)*Assumptions!$F$108/30 -> 47165.771
A29: Cash in (proceeds received) | B29: $ | C29: =0 -> 0 | D29: =D26+D27-D28+C28 -> 1240 | E29: =E26+E27-E28+D28 -> 3069 | F29: =F26+F27-F28+E28 -> 4712 | G29: =G26+G27-G28+F28 -> 7633.3333 | H29: =H26+H27-H28+G28 -> 10938.8 | I29: =I26+I27-I28+H28 -> 13968.973 | J29: =J26+J27-J28+I28 -> 18843.76 | K29: =K26+K27-K28+J28 -> 24125.333 | ... AA29: =AA26+AA27-AA28+Z28 -> 99872.07
A30: Fixed costs, seller fee, launch costs, compliance | B30: $ | C30: =0 -> 0 | D30: ='Monthly PL Y1 Y2'!D17+'Monthly PL Y1 Y2'!D18+'Monthly PL Y1 Y2'!D19+'Monthly PL Y1 Y2'!D20 -> 10389.99 | E30: ='Monthly PL Y1 Y2'!E17+'Monthly PL Y1 Y2'!E18+'Monthly PL Y1 Y2'!E19+'Monthly PL Y1 Y2'!E20 -> 889.99 | F30: ='Monthly PL Y1 Y2'!F17+'Monthly PL Y1 Y2'!F18+'Monthly PL Y1 Y2'!F19+'Monthly PL Y1 Y2'!F20 -> 889.99 | G30: ='Monthly PL Y1 Y2'!G17+'Monthly PL Y1 Y2'!G18+'Monthly PL Y1 Y2'!G19+'Monthly PL Y1 Y2'!G20 -> 889.99 | H30: ='Monthly PL Y1 Y2'!H17+'Monthly PL Y1 Y2'!H18+'Monthly PL Y1 Y2'!H19+'Monthly PL Y1 Y2'!H20 -> 889.99 | I30: ='Monthly PL Y1 Y2'!I17+'Monthly PL Y1 Y2'!I18+'Monthly PL Y1 Y2'!I19+'Monthly PL Y1 Y2'!I20 -> 889.99 | J30: ='Monthly PL Y1 Y2'!J17+'Monthly PL Y1 Y2'!J18+'Monthly PL Y1 Y2'!J19+'Monthly PL Y1 Y2'!J20 -> 889.99 | K30: ='Monthly PL Y1 Y2'!K17+'Monthly PL Y1 Y2'!K18+'Monthly PL Y1 Y2'!K19+'Monthly PL Y1 Y2'!K20 -> 889.99 | ... AA30: ='Monthly PL Y1 Y2'!AA17+'Monthly PL Y1 Y2'!AA18+'Monthly PL Y1 Y2'!AA19+'Monthly PL Y1 Y2'!AA20 -> 1966.6567
A31: Cash out | B31: $ | C31: =C25+C30 -> 7871.2541 | D31: =D25+D30 -> 23835.029 | E31: =E25+E30 -> 11366.377 | F31: =F25+F30 -> 14032.669 | G31: =G25+G30 -> 16934.356 | H31: =H25+H30 -> 23338.639 | I31: =I25+I30 -> 23585.211 | J31: =J25+J30 -> 26840.849 | ... AA31: =AA25+AA30 -> 86710.273
A32: Net cash flow | B32: $ | C32: =C29-C31 -> -7871.2541 | D32: =D29-D31 -> -22595.029 | E32: =E29-E31 -> -8297.3769 | F32: =F29-F31 -> -9320.6688 | G32: =G29-G31 -> -9301.0226 | H32: =H29-H31 -> -12399.839 | I32: =I29-I31 -> -9616.2372 | J32: =J29-J31 -> -7997.0894 | ... AA32: =AA29-AA31 -> 13161.797
A33: Cash balance before new funding (opening capital plus cumulative net cash flow) | B33: $ | C33: =Assumptions!$F$106+C32 -> 31128.746 | D33: =C33+D32 -> 8533.7168 | E33: =D33+E32 -> 236.33981 | F33: =E33+F32 -> -9084.329 | G33: =F33+G32 -> -18385.352 | H33: =G33+H32 -> -30785.191 | I33: =H33+I32 -> -40401.428 | J33: =I33+J32 -> -48398.517 | K33: =J33+K32 -> -55585.405 | ... AA33: =Z33+AA32 -> 70495.702
A34: Negative balance flag | B34: flag | C34: =IF(C33<0,1,0) -> 0 | D34: =IF(D33<0,1,0) -> 0 | E34: =IF(E33<0,1,0) -> 0 | F34: =IF(F33<0,1,0) -> 1 | G34: =IF(G33<0,1,0) -> 1 | H34: =IF(H33<0,1,0) -> 1 | I34: =IF(I33<0,1,0) -> 1 | J34: =IF(J33<0,1,0) -> 1 | ... AA34: =IF(AA33<0,1,0) -> 0
A36: Working capital balances
A37: Inventory on hand at landed cost | B37: $ | C37: =0 -> 0 | D37: =D14*D8 -> 14630 | E37: =E14*E8 -> 20083 | F37: =F14*F8 -> 26201 | G37: =G14*G8 -> 32851 | H37: =H14*H8 -> 40166 | I37: =I14*I8 -> 47880 | J37: =J14*J8 -> 55860 | K37: =K14*K8 -> 63840 | ... AA37: =AA14*AA8 -> 216171.13
A38: Deposits on open orders plus inventory in transit (funded by the business) | B38: $ | C38: =SUMPRODUCT($D$18:$AC$18*(($D$16:$AC$16<=C$5)*(C$5<$D$17:$AC$17)*Assumptions!$F$107+($D$17:$AC$17<=C$5)*(C$5<$D$5:$AC$5))) -> 7871.2541 | D38: =SUMPRODUCT($D$18:$AC$18*(($D$16:$AC$16<=D$5)*(D$5<$D$17:$AC$17)*Assumptions!$F$107+($D$17:$AC$17<=D$5)*(D$5<$D$5:$AC$5))) -> 4292.2932 | E38: =SUMPRODUCT($D$18:$AC$18*(($D$16:$AC$16<=E$5)*(E$5<$D$17:$AC$17)*Assumptions!$F$107+($D$17:$AC$17<=E$5)*(E$5<$D$5:$AC$5))) -> 5485.2802 | F38: =SUMPRODUCT($D$18:$AC$18*(($D$16:$AC$16<=F$5)*(F$5<$D$17:$AC$17)*Assumptions!$F$107+($D$17:$AC$17<=F$5)*(F$5<$D$5:$AC$5))) -> 6764.359 | G38: =SUMPRODUCT($D$18:$AC$18*(($D$16:$AC$16<=G$5)*(G$5<$D$17:$AC$17)*Assumptions!$F$107+($D$17:$AC$17<=G$5)*(G$5<$D$5:$AC$5))) -> 8178.7249 | H38: =SUMPRODUCT($D$18:$AC$18*(($D$16:$AC$16<=H$5)*(H$5<$D$17:$AC$17)*Assumptions!$F$107+($D$17:$AC$17<=H$5)*(H$5<$D$5:$AC$5))) -> 12938.374 | I38: =SUMPRODUCT($D$18:$AC$18*(($D$16:$AC$16<=I$5)*(I$5<$D$17:$AC$17)*Assumptions!$F$107+($D$17:$AC$17<=I$5)*(I$5<$D$5:$AC$5))) -> 14832.394 | J38: =SUMPRODUCT($D$18:$AC$18*(($D$16:$AC$16<=J$5)*(J$5<$D$17:$AC$17)*Assumptions!$F$107+($D$17:$AC$17<=J$5)*(J$5<$D$5:$AC$5))) -> 16843.254 | ... AA38: =SUMPRODUCT($D$18:$AC$18*(($D$16:$AC$16<=AA$5)*(AA$5<$D$17:$AC$17)*Assumptions!$F$107+($D$17:$AC$17<=AA$5)*(AA$5<$D$5:$AC$5))) -> 54109.57
A39: Net income, all channels (monthly tab) | B39: $ | C39: =0 -> 0 | D39: ='Monthly PL Y1 Y2'!D55 -> -10458.99 | E39: ='Monthly PL Y1 Y2'!E55 -> -1000.39 | F39: ='Monthly PL Y1 Y2'!F55 -> -1055.59 | G39: ='Monthly PL Y1 Y2'!G55 -> 560.01 | H39: ='Monthly PL Y1 Y2'!H55 -> 995.01 | I39: ='Monthly PL Y1 Y2'!I55 -> 1488.01 | J39: ='Monthly PL Y1 Y2'!J55 -> 4950.01 | K39: ='Monthly PL Y1 Y2'!K55 -> 6118.01 | ... AA39: ='Monthly PL Y1 Y2'!AA55 -> 32588.658
A40: Operating cash flow for the gates (net income less the change in receivable; inventory for growth is funded separately) | B40: $ | C40: =0 -> 0 | D40: =D39-(D28-C28) -> -11543.99 | E40: =E39-(E28-D28) -> -1651.39 | F40: =F39-(F28-E28) -> -1923.59 | G40: =G39-(G28-F28) -> -1236.6567 | H40: =H39-(H28-G28) -> -325.19 | I40: =I39-(I28-H28) -> -8.2166667 | J40: =J39-(J28-I28) -> 1993.77 | K40: =K39-(K28-J28) -> 4083.3433 | ... AA40: =AA39-(AA28-Z28) -> 31391.22
A42: Peak cash need, runway and funding gap
A43: Minimum monthly cash balance before funding, Months 0 to 24 | C43: =MIN($C$33:$AA$33) -> -96319.189
A44: Month of the monthly minimum | C44: =INDEX($C$5:$AA$5,1,MATCH(C43,$C$33:$AA$33,0)) -> 12
A45: Minimum cash balance before funding, Months 0 to 24 and the Year 3 to 5 year ends | C45: =MIN(C43,$C$64:$E$64) -> -96319.189
A46: Peak cash need month (label) | C46: =IF(C43<=MIN($C$64:$E$64),"Month "&C44,CHOOSE(MATCH(C45,$C$64:$E$64,0),"Year 3","Year 4","Year 5")) -> Month 12
A47: Peak cash need month (number; 36, 48 or 60 for a year end) | C47: =IF(C43<=MIN($C$64:$E$64),C44,24+12*MATCH(C45,$C$64:$E$64,0)) -> 12
A48: Peak cash need (the negative minimum balance, 0 if never negative) | C48: =MAX(0,-C45) -> 96319.189
A49: Funding gap (1.2 times the peak cash need) | C49: =C48*Assumptions!$F$110 -> 115583.03
A50: Funding needed by month (the month before the balance first goes negative; none if never) | C50: =IFERROR(MAX(0,INDEX($C$5:$AA$5,1,MATCH(1,$C$34:$AA$34,0))-1),"none") -> 2
A51: Average monthly net cash flow, Months 4 to 6 | C51: =AVERAGE($G$32:$I$32) -> -10439.033
A52: Runway at the Day 90 gate before funding, months (cash at end of Month 3 divided by the average burn of Months 4 to 6; funded if no burn) | C52: =IF(C51<0,MAX(0,$F$33)/-C51,"funded") -> 0
A53: Funding drawn (line of credit or investor amount, in the month it is needed) | B53: $ | C53: =IF(C$5=$C$50,$C$49,0) -> 0 | D53: =IF(D$5=$C$50,$C$49,0) -> 0 | E53: =IF(E$5=$C$50,$C$49,0) -> 115583.03 | F53: =IF(F$5=$C$50,$C$49,0) -> 0 | G53: =IF(G$5=$C$50,$C$49,0) -> 0 | H53: =IF(H$5=$C$50,$C$49,0) -> 0 | I53: =IF(I$5=$C$50,$C$49,0) -> 0 | J53: =IF(J$5=$C$50,$C$49,0) -> 0 | ... AA53: =IF(AA$5=$C$50,$C$49,0) -> 0
A54: Cash balance after funding | B54: $ | C54: =C33+C53 -> 31128.746 | D54: =C54+D32+D53 -> 8533.7168 | E54: =D54+E32+E53 -> 115819.37 | F54: =E54+F32+F53 -> 106498.7 | G54: =F54+G32+G53 -> 97197.675 | H54: =G54+H32+H53 -> 84797.836 | I54: =H54+I32+I53 -> 75181.599 | J54: =I54+J32+J53 -> 67184.509 | K54: =J54+K32+K53 -> 59997.622 | ... AA54: =Z54+AA32+AA53 -> 186078.73
A55: Runway at the Day 90 gate after funding, months (used by the gate) | C55: =IF(C51<0,MAX(0,$F$54)/-C51,"funded") -> 10.20197
A57: Years 3 to 5 (annual): inventory days of landed COGS, receivable days of revenue | C57: Year 3 | D57: Year 4 | E57: Year 5
A58: Net income | C58: ='Annual PL Y1 to Y5'!E80 -> 426207.56 | D58: ='Annual PL Y1 to Y5'!F80 -> 540707.58 | E58: ='Annual PL Y1 to Y5'!G80 -> 612714.57
A59: Inventory (on hand plus in transit) at year end | C59: ='Annual PL Y1 to Y5'!E70*Assumptions!$F$105/365 -> 270278.05 | D59: ='Annual PL Y1 to Y5'!F70*Assumptions!$F$105/365 -> 392731.59 | E59: ='Annual PL Y1 to Y5'!G70*Assumptions!$F$105/365 -> 506359.85
A60: Receivable at year end | C60: ='Annual PL Y1 to Y5'!E69*Assumptions!$F$109/365 -> 100174.75 | D60: ='Annual PL Y1 to Y5'!F69*Assumptions!$F$109/365 -> 140213.06 | E60: ='Annual PL Y1 to Y5'!G69*Assumptions!$F$109/365 -> 175526.57
A61: Increase in inventory (Year 3 vs Month 24 on hand plus in transit) | C61: =C59-($AA$37+$AA$38) -> -2.6518542 | D61: =D59-C59 -> 122453.54 | E61: =E59-D59 -> 113628.26
A62: Increase in receivable | C62: =C60-$AA$28 -> 53008.976 | D62: =D60-C60 -> 40038.311 | E62: =E60-D60 -> 35313.512
A63: Net cash flow | C63: =C58-C61-C62 -> 373201.23 | D63: =D58-D61-D62 -> 378215.73 | E63: =E58-E61-E62 -> 463772.8
A64: Cash balance at year end before new funding | C64: =$AA$33+C63 -> 443696.94 | D64: =C64+D63 -> 821912.66 | E64: =D64+E63 -> 1285685.5
A65: Cash balance at year end after funding | C65: =$AA$54+C63 -> 559279.96 | D65: =C65+D63 -> 937495.69 | E65: =D65+E63 -> 1401268.5
A67: Funding plan: retained earnings first (the cash balance already includes them), then a line of credit or investor amount equal to the funding gap, in place by the month shown.
A68: Low case note: the order rule (closing stock = cover months times the next three months of sales) keeps buying through the lost quarter to rebuild cover for the recovery month, so the Low peak need at the end of Year 2 assumes purchases continue during the suppression. An operator would pause orders until the listing is restored; the modeled figure is conservative, not wrong.

Sheet Funding and Breakeven
A1: Funding and Breakeven
A2: ="Active scenario: "&ScenarioName&". Opening capital, breakeven, the funding plan, the Day 90 and Month 12 gates and the Plan B summary." -> Active scenario: Medium. Opening capital, breakeven, the funding plan, the Day 90 and Month 12 gates and the Plan B summary.
A4: Breakeven and funding plan
A5: Opening capital (self funded) | B5: =Assumptions!$F$106 -> 39000 | C5: DECISIONS.md: self funded to $39K, the August ask
A6: Cumulative breakeven month, Amazon US, within 18 months | B6: ='Monthly PL Y1 Y2'!$C$63 -> 8 | C6: none means no breakeven within 18 months
A7: Cumulative breakeven month, all channels, within 24 months | B7: ='Monthly PL Y1 Y2'!$C$67 -> 8
A8: Cumulative net at Month 12 (retained earnings available at the Month 12 gate) | B8: ='Monthly PL Y1 Y2'!$O$22 -> 38040.12
A9: Cumulative net at Month 24, all channels | B9: ='Monthly PL Y1 Y2'!$AA$56 -> 355095.42
A10: Peak cash need (negative minimum balance before funding) | B10: ='Cash Flow and Working Capital'!$C$48 -> 96319.189
A11: Peak cash need month | B11: ='Cash Flow and Working Capital'!$C$46 -> Month 12
A12: Funding gap (1.2 times the peak need) | B12: ='Cash Flow and Working Capital'!$C$49 -> 115583.03
A13: Funding needed by month | B13: ='Cash Flow and Working Capital'!$C$50 -> 2 | C13: the month before the balance first goes negative
A14: Runway at the Day 90 gate before funding, months | B14: ='Cash Flow and Working Capital'!$C$52 -> 0
A15: Runway at the Day 90 gate after funding, months | B15: ='Cash Flow and Working Capital'!$C$55 -> 10.20197
A17: Funding plan (in order) | B17: Amount | C17: When | D17: Source and terms
A18: 1. Opening capital from Lucy (self funded) | B18: =B5 -> 39000 | C18: Month 0, after the Korean overseas direct investment report | D18: Owner capital contribution to BRAND LLC
A19: 2. Retained earnings (cumulative net to Month 12, already inside the cash balance) | B19: =B8 -> 38040.12 | C19: Months 1 to 12 | D19: No distributions until the Month 12 gate passes
A20: 3. Line of credit or investor amount (the funding gap) | B20: =B12 -> 115583.03 | C20: =IF(ISNUMBER(B13),"In place by Month "&B13,"Not needed") -> In place by Month 2 | D20: [PLACEHOLDER: lender or investor and terms]. Sized at 1.2 times the peak cash need so one late payout does not break the plan.
A21: 4. Repayment capacity: cash balance after funding at Month 24 | B21: ='Cash Flow and Working Capital'!$AA$54 -> 186078.73 | C21: Month 24 | D21: Cash after funding, before any repayment or owner draw
A22: 5. Cash balance after funding at the end of Year 5 | B22: ='Cash Flow and Working Capital'!$E$65 -> 1401268.5 | C22: Year 5 | D22: Before repayment, tax and owner draws
A24: Kill criteria: Day 90 gate and Month 12 gate (active scenario)
A25: Metric | B25: Model value | C25: Pass threshold | D25: Kill trigger | E25: Pass? | F25: Kill? | G25: Note
A26: Day 90 gate (end of Month 3). Thresholds are read from the Gate thresholds block on Assumptions.
A27: Unit session conversion on at least 3 of the 5 launch SKUs | B27: [PLACEHOLDER: observed at Day 90] | C27: ="at or above "&TEXT(Assumptions!$F$114,"0%") -> at or above 8% | D27: ="hero below "&TEXT(Assumptions!$F$115,"0%") -> hero below 5% | E27: ="observed" -> observed | F27: ="observed" -> observed | G27: Not modeled; read from Amazon Business Reports at the gate
A28: TACOS in Month 3 (and falling month over month) | B28: ='Monthly PL Y1 Y2'!$F$24 -> 0.3 | C28: ="at or below "&TEXT(Assumptions!$F$116,"0%") -> at or below 30% | D28: ="above "&TEXT(Assumptions!$F$117,"0%") -> above 40% | E28: =B28<=Assumptions!$F$116 -> TRUE | F28: =B28>Assumptions!$F$117 -> FALSE | G28: Model ad spend phases are flat inside a phase; the falling test is observed
A29: Return rate in Month 3 | B29: ='Monthly PL Y1 Y2'!$F$32 -> 0.03 | C29: ="at or below "&TEXT(Assumptions!$F$118,"0%") -> at or below 4% | D29: ="above "&TEXT(Assumptions!$F$119,"0%") -> above 7% | E29: =B29<=Assumptions!$F$118 -> TRUE | F29: =B29>Assumptions!$F$119 -> FALSE
A30: Contribution per unit before advertising (hero basis) on at least 3 of 5 SKUs | B30: ='Monthly PL Y1 Y2'!$F$25 -> 12.14 | C30: ="at or above "&TEXT(Assumptions!$F$120,"$#,##0;($#,##0)") -> at or above $11 | D30: ="hero below "&TEXT(Assumptions!$F$121,"$#,##0;($#,##0)") -> hero below $8 | E30: =B30>=Assumptions!$F$120 -> TRUE | F30: =B30<Assumptions!$F$121 -> FALSE | G30: Medium hero $12.14 (ASP $42)
A31: Cash runway after funding the next purchase order, months | B31: ='Cash Flow and Working Capital'!$C$55 -> 10.20197 | C31: ="at or above "&TEXT(Assumptions!$F$122,"0")&" months" -> at or above 4 months | D31: ="below "&TEXT(Assumptions!$F$123,"0")&" months" -> below 2 months | E31: =IF(ISNUMBER(B31),B31>=Assumptions!$F$122,TRUE()) -> TRUE | F31: =IF(ISNUMBER(B31),B31<Assumptions!$F$123,FALSE()) -> FALSE | G31: funded means no burn in Months 4 to 6. Runway = cash after the funding draw at the end of Month 3 divided by the average burn of Months 4 to 6, so it depends on the size of the draw (1.2 times the peak need): a more profitable case with a smaller draw can show a shorter runway than a weaker case. Size the line at the larger of the funding gap and four months of burn if the test is marginal.
A32: No suppressed listing and no IP complaint open more than 14 days | B32: [PLACEHOLDER: observed at Day 90] | C32: none open | D32: ="any open more than "&TEXT(Assumptions!$F$124,"0")&" days" -> any open more than 14 days | E32: ="observed" -> observed | F32: ="observed" -> observed | G32: Observed from Account Health
A33: Day 90 result | B33: =IF(OR(F28,F29,F30,F31),"KILL",IF(AND(E28,E29,E30,E31),"PASS","REVIEW")) -> PASS | G33: KILL if any kill trigger fires; PASS if every modeled pass threshold is met; REVIEW otherwise (fix and retest within 30 days)
A35: Month 12 gate
A36: Monthly revenue in Month 12 | B36: ='Monthly PL Y1 Y2'!$O$9 -> 86100 | C36: ="at or above "&TEXT(Assumptions!$F$125,"$#,##0;($#,##0)") -> at or above $70,000 | D36: ="below "&TEXT(Assumptions!$F$126,"$#,##0;($#,##0)") -> below $50,000 | E36: =B36>=Assumptions!$F$125 -> TRUE | F36: =B36<Assumptions!$F$126 -> FALSE | G36: Medium Month 12 is $86,100; Low is $46,740
A37: Cumulative net at Month 12 (Amazon US, August basis) | B37: ='Monthly PL Y1 Y2'!$O$22 -> 38040.12 | C37: ="at or above "&TEXT(Assumptions!$F$127,"$#,##0;($#,##0)") -> at or above $0 | D37: ="below "&TEXT(Assumptions!$F$128,"$#,##0;($#,##0)") -> below ($25,000) | E37: =B37>=Assumptions!$F$127 -> TRUE | F37: =B37<Assumptions!$F$128 -> FALSE
A38: TACOS in Month 12 | B38: ='Monthly PL Y1 Y2'!$O$24 -> 0.15 | C38: ="at or below "&TEXT(Assumptions!$F$129,"0%") -> at or below 15% | D38: ="above "&TEXT(Assumptions!$F$130,"0%") -> above 25% | E38: =B38<=Assumptions!$F$129 -> TRUE | F38: =B38>Assumptions!$F$130 -> FALSE
A39: Return rate in Month 12 | B39: ='Monthly PL Y1 Y2'!$O$32 -> 0.03 | C39: ="at or below "&TEXT(Assumptions!$F$131,"0%") -> at or below 3% | D39: ="above "&TEXT(Assumptions!$F$132,"0%") -> above 5% | E39: =B39<=Assumptions!$F$131 -> TRUE | F39: =B39>Assumptions!$F$132 -> FALSE
A40: Operating cash flow positive two consecutive months (shown: the lower of Months 11 and 12) | B40: =MIN('Cash Flow and Working Capital'!$N$40,'Cash Flow and Working Capital'!$O$40) -> 7587.3433 | C40: positive in Months 11 and 12 | D40: ="negative in Months 10, 11 and 12 with a funding gap above "&TEXT(Assumptions!$F$133,"$#,##0;($#,##0)") -> negative in Months 10, 11 and 12 with a funding gap above $50,000 | E40: =B40>0 -> TRUE | F40: =AND('Cash Flow and Working Capital'!$M$40<0,'Cash Flow and Working Capital'!$N$40<0,'Cash Flow and Working Capital'!$O$40<0,'Cash Flow and Working Capital'!$C$49>Assumptions!$F$133) -> FALSE | G40: Operating cash flow = net income less the change in receivable. It excludes growth inventory, which the line of credit funds. Full net cash flow including inventory is on the cash tab row 32
A41: Month 12 result | B41: =IF(OR(F36,F37,F38,F39,F40),"KILL",IF(AND(E36,E37,E38,E39,E40),"PASS","REVIEW")) -> PASS | G41: Kill means: no further capital, sell down inventory, delist losers, move to Plan B
A44: Plan B summary (if Amazon fails): B2B installer distribution plus continued Korea wholesale. Full P&L on the Plan B tab.
A45: Line | B45: Year 1 | C45: Year 2 | D45: Year 3
A46: Plan B revenue | B46: =planb_Y1_revenue -> 188251.75 | C46: =planb_Y2_revenue -> 368251.75 | D46: =planb_Y3_revenue -> 518251.75
A47: Plan B net | B47: =planb_Y1_net -> 16752.381 | C47: =planb_Y2_net -> 31520.952 | D47: =planb_Y3_net -> 50126.429

Sheet Sensitivity
A1: Sensitivity (one way): 18 month net and Year 5 net, active scenario
A2: ="Base: "&ScenarioName&" scenario, "&DutyScenarioName&" duty, FX "&TEXT(FXRate,"#,##0")&". Every cell is a live formula: a compact one line P&L that applies the delta to the base from the Monthly and Annual tabs. No pasted values. The rows are approximations of the full model: use them for the tornado and quote duty and FX effects from the Scenario Summary or a full recalc (figures.json)." -> Base: Medium scenario, Copper duty, FX 1,430. Every cell is a live formula: a compact one line P&L that applies the delta to the base from the Monthly and Annual tabs. No pasted values. The rows are approximations of the full model: use them for the tornado and quote duty and FX effects from the Scenario Summary or a full recalc (figures.json).
A4: Base values
A5: 18 month revenue (Amazon US) | B5: ='Monthly PL Y1 Y2'!$C$60 -> 1166340
A6: 18 month net (Amazon US, August basis) | B6: ='Monthly PL Y1 Y2'!$C$61 -> 153020.18
A7: 18 month percentage based costs (COGS, referral, returns, storage, advertising) | B7: =SUM('Monthly PL Y1 Y2'!$D$10:$U$10)+SUM('Monthly PL Y1 Y2'!$D$11:$U$11)+SUM('Monthly PL Y1 Y2'!$D$13:$U$13)+SUM('Monthly PL Y1 Y2'!$D$14:$U$14)+SUM('Monthly PL Y1 Y2'!$D$15:$U$15) -> 835065
A8: 18 month landed COGS | B8: =SUM('Monthly PL Y1 Y2'!$D$10:$U$10) -> 443209.2
A9: Landed COGS % in Months 1 to 18 (active) | B9: =LandedPctActive -> 0.38
A10: Returns % Year 1 (active) | B10: =Assumptions!$F$12 -> 0.03
A11: Year 5 revenue, all channels | B11: ='Annual PL Y1 to Y5'!$G$69 -> 4576228.4
A12: Year 5 net | B12: ='Annual PL Y1 to Y5'!$G$80 -> 612714.57
A13: Year 5 percentage based costs (COGS, channel fees, advertising, returns) | B13: ='Annual PL Y1 to Y5'!$G$70+'Annual PL Y1 to Y5'!$G$71+'Annual PL Y1 to Y5'!$G$73+'Annual PL Y1 to Y5'!$G$74 -> 3071209.1
A14: Year 5 landed COGS, all channels | B14: ='Annual PL Y1 to Y5'!$G$70 -> 1945487.8
A15: Landed COGS % in Year 5 (Amazon US) | B15: ='Annual PL Y1 to Y5'!$G$8 -> 0.375
A16: Returns % Year 5 (active) | B16: =Assumptions!$F$31 -> 0.025
A17: Hero FOB share of price | B17: =HeroFobShare -> 0.16402091
A18: Active duty rate | B18: =DutyRateActive -> 0.401
A19: FX delta already in the base landed % | B19: =LandedFxDelta -> 0
A20: FX embedded in the KRW cost base | B20: =Assumptions!$F$111 -> 1430
A21: Alibaba benchmark FOB midpoint ($17 to $22) relative to the hero FOB, as a change | B21: =('SKU Unit Economics'!$B$29+'SKU Unit Economics'!$B$30)/2/HeroFobUsd-1 -> 1.6425268
A23: One way sensitivity table
A24: Driver | B24: Setting | C24: Setting value | D24: Landed % change (points) | E24: 18 month net | F24: Year 5 net | G24: 18 month net vs base | H24: Year 5 net vs base
A25: Duty rate | B25: Fiber 12.5% | C25: =duty_fiber_rate -> 0.125 | D25: =(C25-$B$18)*$B$17 -> -0.045269771 | E25: =$B$6-(D25)*$B$5 -> 205820.12 | F25: =$B$12-$B$14*(D25)/$B$15 -> 847572.67 | G25: =E25-$B$6 -> 52799.945 | H25: =F25-$B$12 -> 234858.1
A26: Duty rate | B26: Copper 40.1% | C26: =duty_copper_rate -> 0.401 | D26: =(C26-$B$18)*$B$17 -> 0 | E26: =$B$6-(D26)*$B$5 -> 153020.18 | F26: =$B$12-$B$14*(D26)/$B$15 -> 612714.57 | G26: =E26-$B$6 -> 0 | H26: =F26-$B$12 -> 0
A27: Duty rate | B27: Stress 50.1% | C27: =duty_stress_rate -> 0.501 | D27: =(C27-$B$18)*$B$17 -> 0.016402091 | E27: =$B$6-(D27)*$B$5 -> 133889.77 | F27: =$B$12-$B$14*(D27)/$B$15 -> 527621.05 | G27: =E27-$B$6 -> -19130.415 | H27: =F27-$B$12 -> -85093.515
A28: ASP | B28: minus 10% | C28: -0.1 | D28: =0 -> 0 | E28: =$B$6+C28*($B$5-$B$7) -> 119892.68 | F28: =$B$12+C28*($B$11-$B$13) -> 462212.63 | G28: =E28-$B$6 -> -33127.5 | H28: =F28-$B$12 -> -150501.94
A29: ASP | B29: base | C29: 0 | D29: =0 -> 0 | E29: =$B$6+C29*($B$5-$B$7) -> 153020.18 | F29: =$B$12+C29*($B$11-$B$13) -> 612714.57 | G29: =E29-$B$6 -> 0 | H29: =F29-$B$12 -> 0
A30: ASP | B30: plus 10% | C30: 0.1 | D30: =0 -> 0 | E30: =$B$6+C30*($B$5-$B$7) -> 186147.68 | F30: =$B$12+C30*($B$11-$B$13) -> 763216.5 | G30: =E30-$B$6 -> 33127.5 | H30: =F30-$B$12 -> 150501.94
A31: Ad spend | B31: minus 3 points | C31: -0.03 | D31: =0 -> 0 | E31: =$B$6-C31*$B$5 -> 188010.38 | F31: =$B$12-C31*$B$11 -> 750001.42 | G31: =E31-$B$6 -> 34990.2 | H31: =F31-$B$12 -> 137286.85
A32: Ad spend | B32: base | C32: 0 | D32: =0 -> 0 | E32: =$B$6-C32*$B$5 -> 153020.18 | F32: =$B$12-C32*$B$11 -> 612714.57 | G32: =E32-$B$6 -> 0 | H32: =F32-$B$12 -> 0
A33: Ad spend | B33: plus 3 points | C33: 0.03 | D33: =0 -> 0 | E33: =$B$6-C33*$B$5 -> 118029.98 | F33: =$B$12-C33*$B$11 -> 475427.71 | G33: =E33-$B$6 -> -34990.2 | H33: =F33-$B$12 -> -137286.85
A34: Return rate | B34: 2% | C34: 0.02 | D34: =0 -> 0 | E34: =$B$6-(C34-$B$10)*$B$5 -> 164683.58 | F34: =$B$12-(C34-$B$16)*$B$11 -> 635595.71 | G34: =E34-$B$6 -> 11663.4 | H34: =F34-$B$12 -> 22881.142
A35: Return rate | B35: 3% | C35: 0.03 | D35: =0 -> 0 | E35: =$B$6-(C35-$B$10)*$B$5 -> 153020.18 | F35: =$B$12-(C35-$B$16)*$B$11 -> 589833.43 | G35: =E35-$B$6 -> 0 | H35: =F35-$B$12 -> -22881.142
A36: Return rate | B36: 5% | C36: 0.05 | D36: =0 -> 0 | E36: =$B$6-(C36-$B$10)*$B$5 -> 129693.38 | F36: =$B$12-(C36-$B$16)*$B$11 -> 498308.86 | G36: =E36-$B$6 -> -23326.8 | H36: =F36-$B$12 -> -114405.71
A37: FX (KRW per USD) | B37: 1,300 | C37: 1300 | D37: =$B$17*($B$20/C37-1)-$B$19 -> 0.016402091 | E37: =$B$6-(D37)*$B$5 -> 133889.77 | F37: =$B$12-$B$14*(D37)/$B$15 -> 527621.05 | G37: =E37-$B$6 -> -19130.415 | H37: =F37-$B$12 -> -85093.515
A38: FX (KRW per USD) | B38: 1,430 | C38: 1430 | D38: =$B$17*($B$20/C38-1)-$B$19 -> 0 | E38: =$B$6-(D38)*$B$5 -> 153020.18 | F38: =$B$12-$B$14*(D38)/$B$15 -> 612714.57 | G38: =E38-$B$6 -> 0 | H38: =F38-$B$12 -> 0
A39: FX (KRW per USD) | B39: 1,550 | C39: 1550 | D39: =$B$17*($B$20/C39-1)-$B$19 -> -0.012698393 | E39: =$B$6-(D39)*$B$5 -> 167830.82 | F39: =$B$12-$B$14*(D39)/$B$15 -> 678593.42 | G39: =E39-$B$6 -> 14810.644 | H39: =F39-$B$12 -> 65878.851
A40: Factory cost (FOB) | B40: minus 10% | C40: -0.1 | D40: =$B$17*C40*(1+$B$18) -> -0.022979329 | E40: =$B$6-(D40)*$B$5 -> 179821.89 | F40: =$B$12-$B$14*(D40)/$B$15 -> 731930.58 | G40: =E40-$B$6 -> 26801.711 | H40: =F40-$B$12 -> 119216.02
A41: Factory cost (FOB) | B41: base | C41: 0 | D41: =$B$17*C41*(1+$B$18) -> 0 | E41: =$B$6-(D41)*$B$5 -> 153020.18 | F41: =$B$12-$B$14*(D41)/$B$15 -> 612714.57 | G41: =E41-$B$6 -> 0 | H41: =F41-$B$12 -> 0
A42: Factory cost (FOB) | B42: plus 25% | C42: 0.25 | D42: =$B$17*C42*(1+$B$18) -> 0.057448323 | E42: =$B$6-(D42)*$B$5 -> 86015.902 | F42: =$B$12-$B$14*(D42)/$B$15 -> 314674.53 | G42: =E42-$B$6 -> -67004.278 | H42: =F42-$B$12 -> -298040.04
A43: Factory cost (FOB) | B43: Alibaba benchmark | C43: =$B$21 -> 1.6425268 | D43: =$B$17*C43*(1+$B$18) -> 0.37744165 | E43: =$B$6-(D43)*$B$5 -> -287205.11 | F43: =$B$12-$B$14*(D43)/$B$15 -> -1345440.5 | G43: =E43-$B$6 -> -440225.29 | H43: =F43-$B$12 -> -1958155
A44: Duty, FX and factory cost move landed COGS % through the hero FOB share of price (duty on FOB included for the factory cost rows). ASP moves revenue and every percentage cost; FBA fees and fixed costs stay. The B2B, DTC, Canada and pro line COGS are scaled with the same landed % change (approximation noted). The FX rows follow the spec 2.4 formula literally (FX delta = hero FOB share times (1,430 divided by FX, minus 1), no duty on the FX delta), so a 10% FOB rise from FX moves landed COGS % less than the same rise from factory cost, which carries duty. Simplification recorded in the Decision Log.
A46: Tornado data (Year 5 net, active scenario; order by swing, largest first)
A47: Driver | B47: Low label | C47: Low value | D47: High label | E47: High value | F47: Base | G47: Swing | H47: Low minus base | I47: High minus base
A48: Factory cost (FOB) | B48: Alibaba benchmark | C48: =F43 -> -1345440.5 | D48: minus 10% | E48: =F40 -> 731930.58 | F48: =$B$12 -> 612714.57 | G48: =E48-C48 -> 2077371 | H48: =C48-F48 -> -1958155 | I48: =E48-F48 -> 119216.02
A49: Duty rate | B49: Stress 50.1% | C49: =F27 -> 527621.05 | D49: Fiber 12.5% | E49: =F25 -> 847572.67 | F49: =$B$12 -> 612714.57 | G49: =E49-C49 -> 319951.62 | H49: =C49-F49 -> -85093.515 | I49: =E49-F49 -> 234858.1
A50: ASP | B50: minus 10% | C50: =F28 -> 462212.63 | D50: plus 10% | E50: =F30 -> 763216.5 | F50: =$B$12 -> 612714.57 | G50: =E50-C50 -> 301003.87 | H50: =C50-F50 -> -150501.94 | I50: =E50-F50 -> 150501.94
A51: Ad spend | B51: plus 3 points | C51: =F33 -> 475427.71 | D51: minus 3 points | E51: =F31 -> 750001.42 | F51: =$B$12 -> 612714.57 | G51: =E51-C51 -> 274573.71 | H51: =C51-F51 -> -137286.85 | I51: =E51-F51 -> 137286.85
A52: FX (KRW per USD) | B52: 1,300 | C52: =F37 -> 527621.05 | D52: 1,550 | E52: =F39 -> 678593.42 | F52: =$B$12 -> 612714.57 | G52: =E52-C52 -> 150972.37 | H52: =C52-F52 -> -85093.515 | I52: =E52-F52 -> 65878.851
A53: Return rate | B53: 5% | C53: =F36 -> 498308.86 | D53: 2% | E53: =F34 -> 635595.71 | F53: =$B$12 -> 612714.57 | G53: =E53-C53 -> 137286.85 | H53: =C53-F53 -> -114405.71 | I53: =E53-F53 -> 22881.142
A55: Tornado data (18 month net, active scenario)
A56: Driver | B56: Low label | C56: Low value | D56: High label | E56: High value | F56: Base | G56: Swing | H56: Low minus base | I56: High minus base
A57: Factory cost (FOB) | B57: Alibaba benchmark | C57: =E43 -> -287205.11 | D57: minus 10% | E57: =E40 -> 179821.89 | F57: =$B$6 -> 153020.18 | G57: =E57-C57 -> 467027 | H57: =C57-F57 -> -440225.29 | I57: =E57-F57 -> 26801.711
A58: Duty rate | B58: Stress 50.1% | C58: =E27 -> 133889.77 | D58: Fiber 12.5% | E58: =E25 -> 205820.12 | F58: =$B$6 -> 153020.18 | G58: =E58-C58 -> 71930.359 | H58: =C58-F58 -> -19130.415 | I58: =E58-F58 -> 52799.945
A59: ASP | B59: minus 10% | C59: =E28 -> 119892.68 | D59: plus 10% | E59: =E30 -> 186147.68 | F59: =$B$6 -> 153020.18 | G59: =E59-C59 -> 66255 | H59: =C59-F59 -> -33127.5 | I59: =E59-F59 -> 33127.5
A60: Ad spend | B60: plus 3 points | C60: =E33 -> 118029.98 | D60: minus 3 points | E60: =E31 -> 188010.38 | F60: =$B$6 -> 153020.18 | G60: =E60-C60 -> 69980.4 | H60: =C60-F60 -> -34990.2 | I60: =E60-F60 -> 34990.2
A61: FX (KRW per USD) | B61: 1,300 | C61: =E37 -> 133889.77 | D61: 1,550 | E61: =E39 -> 167830.82 | F61: =$B$6 -> 153020.18 | G61: =E61-C61 -> 33941.058 | H61: =C61-F61 -> -19130.415 | I61: =E61-F61 -> 14810.644
A62: Return rate | B62: 5% | C62: =E36 -> 129693.38 | D62: 2% | E62: =E34 -> 164683.58 | F62: =$B$6 -> 153020.18 | G62: =E62-C62 -> 34990.2 | H62: =C62-F62 -> -23326.8 | I62: =E62-F62 -> 11663.4
A64: Static row order (largest expected swing first). Values are live; if inputs change the order may no longer be sorted.

Sheet KPI Dashboard
A1: KPI Dashboard
A2: ="Active scenario: "&ScenarioName&". Duty: "&DutyScenarioName&". FX "&TEXT(FXRate,"#,##0")&"." -> Active scenario: Medium. Duty: Copper. FX 1,430.
A4: KPI | B4: Value | C4: Note
A5: 18 month revenue (Amazon US) | B5: ='Monthly PL Y1 Y2'!$C$60 -> 1166340
A6: 18 month net | B6: ='Monthly PL Y1 Y2'!$C$61 -> 153020.18
A7: 18 month net margin | B7: ='Monthly PL Y1 Y2'!$C$62 -> 0.13119689
A8: Cumulative breakeven month (18 months) | B8: ='Monthly PL Y1 Y2'!$C$63 -> 8
A9: Month 18 run rate | B9: ='Monthly PL Y1 Y2'!$C$64 -> 1537200
A10: Exit margin (Month 18) | B10: ='Monthly PL Y1 Y2'!$C$65 -> 0.1721
A11: Year 5 revenue, all channels | B11: ='Annual PL Y1 to Y5'!$G$69 -> 4576228.4
A12: Year 5 net | B12: ='Annual PL Y1 to Y5'!$G$80 -> 612714.57
A13: Year 5 net margin | B13: ='Annual PL Y1 to Y5'!$G$81 -> 0.13389073
A14: Peak cash need | B14: ='Cash Flow and Working Capital'!$C$48 -> 96319.189
A15: Peak cash need month | B15: ='Cash Flow and Working Capital'!$C$46 -> Month 12
A16: Funding gap (1.2 times peak need) | B16: ='Cash Flow and Working Capital'!$C$49 -> 115583.03
A17: Funding needed by month | B17: ='Cash Flow and Working Capital'!$C$50 -> 2
A18: Day 90 gate | B18: ='Funding and Breakeven'!$B$33 -> PASS
A19: Month 12 gate | B19: ='Funding and Breakeven'!$B$41 -> PASS
A21: Chart data (links)
A22: Month | B22: Revenue, all channels | C22: Net, all channels | D22: Cash balance before funding | E22: Minimum marker | F22: Minimum balance line
A23: Month 0 | D23: ='Cash Flow and Working Capital'!C33 -> 31128.746 | E23: =IF(0='Cash Flow and Working Capital'!$C$47,D23,0) -> 0 | F23: ='Cash Flow and Working Capital'!$C$43 -> -96319.189
A24: Month 1 | B24: ='Monthly PL Y1 Y2'!D54 -> 6300 | C24: ='Monthly PL Y1 Y2'!D55 -> -10458.99 | D24: ='Cash Flow and Working Capital'!D33 -> 8533.7168 | E24: =IF(1='Cash Flow and Working Capital'!$C$47,D24,0) -> 0 | F24: ='Cash Flow and Working Capital'!$C$43 -> -96319.189
A25: Month 2 | B25: ='Monthly PL Y1 Y2'!E54 -> 10080 | C25: ='Monthly PL Y1 Y2'!E55 -> -1000.39 | D25: ='Cash Flow and Working Capital'!E33 -> 236.33981 | E25: =IF(2='Cash Flow and Working Capital'!$C$47,D25,0) -> 0 | F25: ='Cash Flow and Working Capital'!$C$43 -> -96319.189
A26: Month 3 | B26: ='Monthly PL Y1 Y2'!F54 -> 15120 | C26: ='Monthly PL Y1 Y2'!F55 -> -1055.59 | D26: ='Cash Flow and Working Capital'!F33 -> -9084.329 | E26: =IF(3='Cash Flow and Working Capital'!$C$47,D26,0) -> 0 | F26: ='Cash Flow and Working Capital'!$C$43 -> -96319.189
A27: Month 4 | B27: ='Monthly PL Y1 Y2'!G54 -> 21000 | C27: ='Monthly PL Y1 Y2'!G55 -> 560.01 | D27: ='Cash Flow and Working Capital'!G33 -> -18385.352 | E27: =IF(4='Cash Flow and Working Capital'!$C$47,D27,0) -> 0 | F27: ='Cash Flow and Working Capital'!$C$43 -> -96319.189
A28: Month 5 | B28: ='Monthly PL Y1 Y2'!H54 -> 27300 | C28: ='Monthly PL Y1 Y2'!H55 -> 995.01 | D28: ='Cash Flow and Working Capital'!H33 -> -30785.191 | E28: =IF(5='Cash Flow and Working Capital'!$C$47,D28,0) -> 0 | F28: ='Cash Flow and Working Capital'!$C$43 -> -96319.189
A29: Month 6 | B29: ='Monthly PL Y1 Y2'!I54 -> 34440 | C29: ='Monthly PL Y1 Y2'!I55 -> 1488.01 | D29: ='Cash Flow and Working Capital'!I33 -> -40401.428 | E29: =IF(6='Cash Flow and Working Capital'!$C$47,D29,0) -> 0 | F29: ='Cash Flow and Working Capital'!$C$43 -> -96319.189
A30: Month 7 | B30: ='Monthly PL Y1 Y2'!J54 -> 42000 | C30: ='Monthly PL Y1 Y2'!J55 -> 4950.01 | D30: ='Cash Flow and Working Capital'!J33 -> -48398.517 | E30: =IF(7='Cash Flow and Working Capital'!$C$47,D30,0) -> 0 | F30: ='Cash Flow and Working Capital'!$C$43 -> -96319.189
A31: Month 8 | B31: ='Monthly PL Y1 Y2'!K54 -> 50400 | C31: ='Monthly PL Y1 Y2'!K55 -> 6118.01 | D31: ='Cash Flow and Working Capital'!K33 -> -55585.405 | E31: =IF(8='Cash Flow and Working Capital'!$C$47,D31,0) -> 0 | F31: ='Cash Flow and Working Capital'!$C$43 -> -96319.189
A32: Month 9 | B32: ='Monthly PL Y1 Y2'!L54 -> 58800 | C32: ='Monthly PL Y1 Y2'!L55 -> 7286.01 | D32: ='Cash Flow and Working Capital'!L33 -> -64474.337 | E32: =IF(9='Cash Flow and Working Capital'!$C$47,D32,0) -> 0 | F32: ='Cash Flow and Working Capital'!$C$43 -> -96319.189
A33: Month 10 | B33: ='Monthly PL Y1 Y2'!M54 -> 67200 | C33: ='Monthly PL Y1 Y2'!M55 -> 8454.01 | D33: ='Cash Flow and Working Capital'!M33 -> -76337.125 | E33: =IF(10='Cash Flow and Working Capital'!$C$47,D33,0) -> 0 | F33: ='Cash Flow and Working Capital'!$C$43 -> -96319.189
A34: Month 11 | B34: ='Monthly PL Y1 Y2'!N54 -> 75600 | C34: ='Monthly PL Y1 Y2'!N55 -> 9622.01 | D34: ='Cash Flow and Working Capital'!N33 -> -87168.519 | E34: =IF(11='Cash Flow and Working Capital'!$C$47,D34,0) -> 0 | F34: ='Cash Flow and Working Capital'!$C$43 -> -96319.189
A35: Month 12 | B35: ='Monthly PL Y1 Y2'!O54 -> 86100 | C35: ='Monthly PL Y1 Y2'!O55 -> 11082.01 | D35: ='Cash Flow and Working Capital'!O33 -> -96319.189 | E35: =IF(12='Cash Flow and Working Capital'!$C$47,D35,0) -> -96319.189 | F35: ='Cash Flow and Working Capital'!$C$43 -> -96319.189
A36: Month 13 | B36: ='Monthly PL Y1 Y2'!P54 -> 112060 | C36: ='Monthly PL Y1 Y2'!P55 -> 19038.975 | D36: ='Cash Flow and Working Capital'!P33 -> -95581.754 | E36: =IF(13='Cash Flow and Working Capital'!$C$47,D36,0) -> 0 | F36: ='Cash Flow and Working Capital'!$C$43 -> -96319.189
A37: Month 14 | B37: ='Monthly PL Y1 Y2'!Q54 -> 121132 | C37: ='Monthly PL Y1 Y2'!Q55 -> 20714.495 | D37: ='Cash Flow and Working Capital'!Q33 -> -85176.196 | E37: =IF(14='Cash Flow and Working Capital'!$C$47,D37,0) -> 0 | F37: ='Cash Flow and Working Capital'!$C$43 -> -96319.189
A38: Month 15 | B38: ='Monthly PL Y1 Y2'!R54 -> 127936 | C38: ='Monthly PL Y1 Y2'!R55 -> 21971.135 | D38: ='Cash Flow and Working Capital'!R33 -> -72584.261 | E38: =IF(15='Cash Flow and Working Capital'!$C$47,D38,0) -> 0 | F38: ='Cash Flow and Working Capital'!$C$43 -> -96319.189
A39: Month 16 | B39: ='Monthly PL Y1 Y2'!S54 -> 134740 | C39: ='Monthly PL Y1 Y2'!S55 -> 23227.775 | D39: ='Cash Flow and Working Capital'!S33 -> -58017.486 | E39: =IF(16='Cash Flow and Working Capital'!$C$47,D39,0) -> 0 | F39: ='Cash Flow and Working Capital'!$C$43 -> -96319.189
A40: Month 17 | B40: ='Monthly PL Y1 Y2'!T54 -> 141544 | C40: ='Monthly PL Y1 Y2'!T55 -> 24484.415 | D40: ='Cash Flow and Working Capital'!T33 -> -41455.946 | E40: =IF(17='Cash Flow and Working Capital'!$C$47,D40,0) -> 0 | F40: ='Cash Flow and Working Capital'!$C$43 -> -96319.189
A41: Month 18 | B41: ='Monthly PL Y1 Y2'!U54 -> 148348 | C41: ='Monthly PL Y1 Y2'!U55 -> 25741.055 | D41: ='Cash Flow and Working Capital'!U33 -> -22853.153 | E41: =IF(18='Cash Flow and Working Capital'!$C$47,D41,0) -> 0 | F41: ='Cash Flow and Working Capital'!$C$43 -> -96319.189
A42: Month 19 | B42: ='Monthly PL Y1 Y2'!V54 -> 152884 | C42: ='Monthly PL Y1 Y2'!V55 -> 28037.158 | D42: ='Cash Flow and Working Capital'!V33 -> -1252.6368 | E42: =IF(19='Cash Flow and Working Capital'!$C$47,D42,0) -> 0 | F42: ='Cash Flow and Working Capital'!$C$43 -> -96319.189
A43: Month 20 | B43: ='Monthly PL Y1 Y2'!W54 -> 157420 | C43: ='Monthly PL Y1 Y2'!W55 -> 28947.458 | D43: ='Cash Flow and Working Capital'!W33 -> 19120.158 | E43: =IF(20='Cash Flow and Working Capital'!$C$47,D43,0) -> 0 | F43: ='Cash Flow and Working Capital'!$C$43 -> -96319.189
A44: Month 21 | B44: ='Monthly PL Y1 Y2'!X54 -> 161956 | C44: ='Monthly PL Y1 Y2'!X55 -> 29857.758 | D44: ='Cash Flow and Working Capital'!X33 -> 35464.328 | E44: =IF(21='Cash Flow and Working Capital'!$C$47,D44,0) -> 0 | F44: ='Cash Flow and Working Capital'!$C$43 -> -96319.189
A45: Month 22 | B45: ='Monthly PL Y1 Y2'!Y54 -> 166492 | C45: ='Monthly PL Y1 Y2'!Y55 -> 30768.058 | D45: ='Cash Flow and Working Capital'!Y33 -> 45474.324 | E45: =IF(22='Cash Flow and Working Capital'!$C$47,D45,0) -> 0 | F45: ='Cash Flow and Working Capital'!$C$43 -> -96319.189
A46: Month 23 | B46: ='Monthly PL Y1 Y2'!Z54 -> 171028 | C46: ='Monthly PL Y1 Y2'!Z55 -> 31678.358 | D46: ='Cash Flow and Working Capital'!Z33 -> 57333.905 | E46: =IF(23='Cash Flow and Working Capital'!$C$47,D46,0) -> 0 | F46: ='Cash Flow and Working Capital'!$C$43 -> -96319.189
A47: Month 24 | B47: ='Monthly PL Y1 Y2'!AA54 -> 175564 | C47: ='Monthly PL Y1 Y2'!AA55 -> 32588.658 | D47: ='Cash Flow and Working Capital'!AA33 -> 70495.702 | E47: =IF(24='Cash Flow and Working Capital'!$C$47,D47,0) -> 0 | F47: ='Cash Flow and Working Capital'!$C$43 -> -96319.189
A49: Annual revenue by channel (links) | B49: Year 1 | C49: Year 2 | D49: Year 3 | E49: Year 4 | F49: Year 5
A50: Amazon US | B50: ='Annual PL Y1 to Y5'!C15 -> 494340 | C50: ='Annual PL Y1 to Y5'!D15 -> 1528800 | D50: ='Annual PL Y1 to Y5'!E15 -> 1965180.7 | E50: ='Annual PL Y1 to Y5'!F15 -> 2263888.1 | F50: ='Annual PL Y1 to Y5'!G15 -> 2434132.5
A51: eBay and Walmart | B51: ='Annual PL Y1 to Y5'!C24 -> 0 | C51: ='Annual PL Y1 to Y5'!D24 -> 122304 | D51: ='Annual PL Y1 to Y5'!E24 -> 196518.07 | E51: ='Annual PL Y1 to Y5'!F24 -> 271666.58 | F51: ='Annual PL Y1 to Y5'!G24 -> 292095.9
A52: B2B installer and AV integrator | B52: ='Annual PL Y1 to Y5'!C33 -> 0 | C52: ='Annual PL Y1 to Y5'!D33 -> 120000 | D52: ='Annual PL Y1 to Y5'!E33 -> 350000 | E52: ='Annual PL Y1 to Y5'!F33 -> 600000 | F52: ='Annual PL Y1 to Y5'!G33 -> 850000
A53: DTC site | B53: ='Annual PL Y1 to Y5'!C42 -> 0 | C53: ='Annual PL Y1 to Y5'!D42 -> 0 | D53: ='Annual PL Y1 to Y5'!E42 -> 100000 | E53: ='Annual PL Y1 to Y5'!F42 -> 250000 | F53: ='Annual PL Y1 to Y5'!G42 -> 400000
A54: Amazon Canada | B54: ='Annual PL Y1 to Y5'!C51 -> 0 | C54: ='Annual PL Y1 to Y5'!D51 -> 0 | D54: ='Annual PL Y1 to Y5'!E51 -> 0 | E54: ='Annual PL Y1 to Y5'!F51 -> 120000 | F54: ='Annual PL Y1 to Y5'!G51 -> 250000
A55: Pro line | B55: ='Annual PL Y1 to Y5'!C60 -> 0 | C55: ='Annual PL Y1 to Y5'!D60 -> 0 | D55: ='Annual PL Y1 to Y5'!E60 -> 0 | E55: ='Annual PL Y1 to Y5'!F60 -> 150000 | F55: ='Annual PL Y1 to Y5'!G60 -> 350000
A57: Tornado (Year 5 net vs base) | B57: Low minus base | C57: High minus base
A58: =Sensitivity!A48 -> Factory cost (FOB) | B58: =Sensitivity!H48 -> -1958155 | C58: =Sensitivity!I48 -> 119216.02
A59: =Sensitivity!A49 -> Duty rate | B59: =Sensitivity!H49 -> -85093.515 | C59: =Sensitivity!I49 -> 234858.1
A60: =Sensitivity!A50 -> ASP | B60: =Sensitivity!H50 -> -150501.94 | C60: =Sensitivity!I50 -> 150501.94
A61: =Sensitivity!A51 -> Ad spend | B61: =Sensitivity!H51 -> -137286.85 | C61: =Sensitivity!I51 -> 137286.85
A62: =Sensitivity!A52 -> FX (KRW per USD) | B62: =Sensitivity!H52 -> -85093.515 | C62: =Sensitivity!I52 -> 65878.851
A63: =Sensitivity!A53 -> Return rate | B63: =Sensitivity!H53 -> -114405.71 | C63: =Sensitivity!I53 -> 22881.142
A65: Duty waterfall (hero net per unit) | B65: Invisible base | C65: Bar
A66: ='Landed Cost & Tariff Scenarios'!E31 -> Copper net | B66: ='Landed Cost & Tariff Scenarios'!F31 -> 0 | C66: ='Landed Cost & Tariff Scenarios'!G31 -> 7.997
A67: ='Landed Cost & Tariff Scenarios'!E32 -> Fiber ruling uplift | B67: ='Landed Cost & Tariff Scenarios'!F32 -> 7.997 | C67: ='Landed Cost & Tariff Scenarios'!G32 -> 2.036687
A68: ='Landed Cost & Tariff Scenarios'!E33 -> Fiber net | B68: ='Landed Cost & Tariff Scenarios'!F33 -> 0 | C68: ='Landed Cost & Tariff Scenarios'!G33 -> 10.033687
A69: ='Landed Cost & Tariff Scenarios'!E34 -> Stress penalty | B69: ='Landed Cost & Tariff Scenarios'!F34 -> 7.2590699 | C69: ='Landed Cost & Tariff Scenarios'!G34 -> 0.73793007
A70: ='Landed Cost & Tariff Scenarios'!E35 -> Stress net | B70: ='Landed Cost & Tariff Scenarios'!F35 -> 0 | C70: ='Landed Cost & Tariff Scenarios'!G35 -> 7.2590699

Sheet Levers
A1: Twelve levers, each mapped to the assumption it moves
A2: From and To values quote the Medium columns of the model (links where the model holds the number; yellow cells are typed targets). They are pinned to Medium on purpose, so the lever table reads the same whatever the Scenario selector shows (recorded in the Decision Log). Column I quantifies each lever from the Medium engine on the Scenario Summary tab. Owner and evidence per the build spec 2.8.
A4: # | B4: Lever | C4: Assumption it moves | D4: From (Medium values) | E4: To (Medium values) | F4: Owner | G4: Evidence | H4: Model cell or driver | I4: Model effect on net, Medium ($) | J4: How the effect is computed (approximate; Scenario Summary Medium engine)
A5: 1 | B5: CBP binding ruling: fiber classification 8544.70.00 | C5: Duty rate, landed COGS % | D5: ='Landed Cost & Tariff Scenarios'!$B$23 -> 0.38 | E5: ='Landed Cost & Tariff Scenarios'!$C$23 -> 0.33473023 | F5: Broker, Mark | G5: August deck lever, brief | H5: Landed Cost & Tariff Scenarios: Medium row, Copper vs Fiber | I5: =('Landed Cost & Tariff Scenarios'!$B$23-'Landed Cost & Tariff Scenarios'!$C$23)*'Scenario Summary'!$C$344 -> 52799.945 | J5: 18 month net: (copper landed % minus fiber landed %) times Medium 18 month revenue
A6: 2 | B6: Air to ocean freight after the Day 90 gate | C6: Freight per unit, landed COGS % | D6: ='SKU Unit Economics'!$B$19 -> 8.5 | E6: ='SKU Unit Economics'!$B$20 -> 1.1 | F6: Lucy, 3PL | G6: August deck lever | H6: SKU Unit Economics constants: air and ocean per kg; Assumptions: landed COGS change Year 2 | I6: =('SKU Unit Economics'!$J$6-'SKU Unit Economics'!$K$6)*'Scenario Summary'!$C$350 -> 41946.252 | J6: 18 month net, upper bound: (air minus ocean freight per hero unit) times 18 month units; the model phases the switch in from the ocean start month through the Year 2 landed change
A7: 3 | B7: Direction proof connector design | C7: Return rate | D7: =Assumptions!$D$12 -> 0.03 | E7: =Assumptions!$D$31 -> 0.025 | F7: Lucy, factory | G7: August deck lever | H7: Assumptions: returns % Year 1 and Year 2 onward (Medium) | I7: =(Assumptions!$D$12-Assumptions!$D$31)*'Scenario Summary'!$C$344 -> 5831.7 | J7: 18 month net: the returns point saved times 18 month revenue
A8: 4 | B8: Keyword pruning and negative keywords | C8: Ad spend % | D8: phase rate | E8: minus 2 points | F8: Mark, VA | G8: August deck lever | H8: Assumptions: ad spend % by phase; Sensitivity: ad spend minus 3 points | I8: =0.02*'Scenario Summary'!$C$344 -> 23326.8 | J8: 18 month net: 2 points of ad spend times 18 month revenue
A9: 5 | B9: Review velocity (Vine, insert card, Brand Registry follow up) | C9: Conversion, unit ramp | D9: base ramp | E9: plus 10% units | F9: Mark | G9: August deck lever | H9: Assumptions: unit ramp multiplier | I9: =0.1*SUM('Scenario Summary'!$D$300:$U$300) -> 17854 | J9: 18 month net: 10% more units at the same contribution per unit after advertising; fixed costs unchanged
A10: 6 | B10: Length variations under one parent ASIN | C10: Conversion, review pooling, ad efficiency | D10: separate ASINs | E10: one parent | F10: Mark | G10: August deck lever | H10: Not a numeric driver; supports levers 4 and 5 | I10: not numeric | J10: Supports levers 4 and 5 (shared reviews and ad budget across the lengths)
A11: 7 | B11: Factory volume pricing tiers | C11: FOB cost | D11: H2 base | E11: minus 5% at 5,000 units per quarter | F11: Lucy | G11: Management estimate | H11: SKU Unit Economics: H2 cost KRW; Sensitivity: factory cost minus 10% | I11: =0.05*HeroFobShare*(1+DutyRateCopper)*'Scenario Summary'!$C$344 -> 13400.856 | J11: 18 month net: FOB minus 5% with the duty on that FOB saved too, through the hero FOB share of price
A12: 8 | B12: Packaging to a smaller FBA size tier | C12: FBA fee per unit | D12: =Assumptions!$D$20 -> 5.5 | E12: 4.75 | F12: Lucy, factory | G12: Management estimate | H12: Assumptions: FBA fee per unit (hero basis); SKU tab FBA fee column | I12: =(Assumptions!$D$20-E12)*'Scenario Summary'!$C$350 -> 20827.5 | J12: 18 month net, upper bound: the FBA fee saving per unit times 18 month units (applies to the 7M and 10M lengths only)
A13: 9 | B13: 3PL feeding FBA, avoid aged inventory surcharges | C13: Storage and inbound % | D13: =Assumptions!$D$21 -> 0.02 | E13: 0.015 | F13: 3PL, Lucy | G13: Management estimate | H13: Assumptions: storage and inbound % | I13: =(Assumptions!$D$21-E13)*'Scenario Summary'!$C$344 -> 5831.7 | J13: 18 month net: half a point of storage and inbound times 18 month revenue
A14: 10 | B14: Price ladder and coupons (list vs sale price) | C14: ASP | D14: =Assumptions!$D$10 -> 42 | E14: plus or minus 5% test | F14: Mark | G14: Management estimate | H14: Assumptions: ASP Years 1 and 2; Sensitivity: ASP plus or minus 10% | I14: =0.05*('Scenario Summary'!$C$344-(SUM('Scenario Summary'!$D$294:$U$294)+SUM('Scenario Summary'!$D$295:$U$295)+SUM('Scenario Summary'!$D$297:$U$297)+SUM('Scenario Summary'!$D$298:$U$298)+SUM('Scenario Summary'!$D$299:$U$299))) -> 16563.75 | J14: 18 month net: plus 5% ASP with every percentage cost scaling with revenue (minus 5% costs the same amount)
A15: 11 | B15: Off Amazon email list (Spec Match finder, trade up registration) | C15: DTC revenue, ad % | D15: =0 -> 0 | E15: =Assumptions!$D$57 -> 100000 | F15: Mark | G15: Management estimate | H15: Assumptions: DTC site revenue Year 3 (channel from Year 3) | I15: ='Scenario Summary'!$E$400 -> 16012.868 | J15: Year 3 contribution of the DTC channel (Medium)
A16: 12 | B16: B2B installer program (AV integrators, custom installers) | C16: B2B channel revenue | D16: =0 -> 0 | E16: =Assumptions!$D$53 -> 120000 | F16: Mark, Lucy | G16: Management estimate | H16: Assumptions: B2B revenue Year 2 | I16: ='Scenario Summary'!$D$391 -> 14452.381 | J16: Year 2 contribution of the B2B channel (Medium)

Sheet Scenario Summary
A1: Scenario Summary: Low, Medium and High side by side
A2: Computed live by three parallel copies of the monthly, annual, cash and gate engines (rows 45 onward), each wired to its own Assumptions column, so the table does not depend on the Scenario selector. Duty scenario and FX follow the selectors.
A3: The active scenario column on the main tabs must equal the matching column here (the build script checks this after recalculation).
A5: Metric | B5: Low | C5: Medium | D5: High | E5: Unit
A6: 18 month revenue (Amazon US) | B6: =C102 -> 633156 | C6: =C344 -> 1166340 | D6: =C586 -> 1851021 | E6: $
A7: 18 month net (Amazon US, August basis) | B7: =C103 -> -19636.1 | C7: =C345 -> 153020.18 | D7: =C587 -> 447155.24 | E7: $
A8: 18 month net margin | B8: =C104 -> -0.031013052 | C8: =C346 -> 0.13119689 | D8: =C588 -> 0.24157222 | E8: %
A9: Cumulative breakeven month (18 months; none if never) | B9: =C105 -> none | C9: =C347 -> 8 | D9: =C589 -> 5 | E9: month
A10: Month 18 run rate | B10: =C106 -> 834480 | C10: =C348 -> 1537200 | D10: =C590 -> 2439648 | E10: $
A11: Exit margin (Month 18) | B11: =C107 -> 0.022464912 | C11: =C349 -> 0.1721 | D11: =C591 -> 0.27271539 | E11: %
A12: 18 month units | B12: =C108 -> 16662 | C12: =C350 -> 27770 | D12: =C592 -> 43047 | E12: units
A13: Year 1 revenue | B13: =C179 -> 268356 | C13: =C421 -> 494340 | D13: =C663 -> 784535 | E13: $
A14: Year 1 net | B14: =C190 -> -27160.16 | C14: =C432 -> 38040.12 | D14: =C674 -> 156979.36 | E14: $
A15: Year 2 revenue | B15: =D179 -> 641824.56 | C15: =D421 -> 1771104 | D15: =D663 -> 2841253.2 | E15: $
A16: Year 2 net | B16: =D190 -> 13602.987 | C16: =D432 -> 317055.3 | D16: =D674 -> 759085.13 | E16: $
A17: Year 3 revenue | B17: =E179 -> 737766.74 | C17: =E421 -> 2611698.7 | D17: =E663 -> 4416474.4 | E17: $
A18: Year 3 net | B18: =E190 -> 35684.63 | C18: =E432 -> 426207.56 | D18: =E674 -> 1133101.6 | E18: $
A19: Year 4 revenue | B19: =F179 -> 762708.55 | C19: =F421 -> 3655554.7 | D19: =F663 -> 6468356.6 | E19: $
A20: Year 4 net | B20: =F190 -> 25953.142 | C20: =F432 -> 540707.58 | D20: =F674 -> 1557531.7 | E20: $
A21: Year 5 revenue | B21: =G179 -> 768330.22 | C21: =G421 -> 4576228.4 | D21: =G663 -> 8296603.8 | E21: $
A22: Year 5 net | B22: =G190 -> -2460.9059 | C22: =G432 -> 612714.57 | D22: =G674 -> 1838289.8 | E22: $
A23: Year 5 net margin | B23: =G191 -> -0.0032029274 | C23: =G433 -> 0.13389073 | D23: =G675 -> 0.22157137 | E23: %
A24: Year 5 Amazon US revenue | B24: =G125 -> 655861.31 | C24: =G367 -> 2434132.5 | D24: =G609 -> 4434467.6 | E24: $
A25: Peak cash need | B25: =C244 -> 113736.21 | C25: =C486 -> 96319.189 | D25: =C728 -> 34098.586 | E25: $
A26: Peak cash need month (number; 36, 48 or 60 for a year end) | B26: =C243 -> 24 | C26: =C485 -> 12 | D26: =C727 -> 7 | E26: month
A27: Peak cash need month (label) | B27: =C242 -> Month 24 | C27: =C484 -> Month 12 | D27: =C726 -> Month 7
A28: Minimum cash balance before funding | B28: =C241 -> -113736.21 | C28: =C483 -> -96319.189 | D28: =C725 -> -34098.586 | E28: $
A29: Funding gap (1.2 times peak need) | B29: =C245 -> 136483.45 | C29: =C487 -> 115583.03 | D29: =C729 -> 40918.303 | E29: $
A30: Funding needed by month | B30: =C246 -> 2 | C30: =C488 -> 2 | D30: =C730 -> 1 | E30: month
A31: Runway at Day 90 after funding, months | B31: =C251 -> 15.261247 | C31: =C493 -> 10.20197 | D31: =C735 -> 4.0398372 | E31: months
A32: Day 90 gate result | B32: =B275 -> REVIEW | C32: =B517 -> PASS | D32: =B759 -> PASS
A33: Month 12 gate result | B33: =B283 -> KILL | C33: =B525 -> PASS | D33: =B767 -> PASS
A45: Low scenario: monthly P&L engine (Assumptions column C)
A46: Line | B46: Unit | C46: Month 0 (pre launch) | D46: Month 1 | E46: Month 2 | F46: Month 3 | G46: Month 4 | H46: Month 5 | I46: Month 6 | J46: Month 7 | K46: Month 8 | L46: Month 9 | M46: Month 10 | N46: Month 11 | O46: Month 12 | P46: Month 13 | Q46: Month 14 | R46: Month 15 | S46: Month 16 | T46: Month 17 | U46: Month 18 | V46: Month 19 | W46: Month 20 | X46: Month 21 | Y46: Month 22 | Z46: Month 23 | AA46: Month 24 | AB46: Year 1 | AC46: Year 2
A47: Month index | C47: 0 | D47: 1 | E47: 2 | F47: 3 | G47: 4 | H47: 5 | I47: 6 | J47: 7 | K47: 8 | L47: 9 | M47: 10 | N47: 11 | O47: 12 | P47: 13 | Q47: 14 | R47: 15 | S47: 16 | T47: 17 | U47: 18 | V47: 19 | W47: 20 | X47: 21 | Y47: 22 | Z47: 23 | AA47: 24 | AB47: Months 1 to 12 | AC47: Months 13 to 24
A48: Amazon US (Months 1 to 18 reproduce the August model; Year 2 driver changes start in Month 19)
A49: Units sold | B49: units | D49: =Assumptions!$C$137 -> 90 | E49: =Assumptions!$C$138 -> 144 | F49: =Assumptions!$C$139 -> 216 | G49: =Assumptions!$C$140 -> 300 | H49: =Assumptions!$C$141 -> 390 | I49: =Assumptions!$C$142 -> 492 | J49: =Assumptions!$C$143 -> 600 | K49: =Assumptions!$C$144 -> 720 | L49: =Assumptions!$C$145 -> 840 | M49: =Assumptions!$C$146 -> 960 | N49: =Assumptions!$C$147 -> 1080 | O49: =Assumptions!$C$148 -> 1230 | P49: =Assumptions!$C$149 -> 1350 | Q49: =Assumptions!$C$150 -> 1470 | R49: =Assumptions!$C$151 -> 1560 | S49: =Assumptions!$C$152 -> 1650 | T49: =Assumptions!$C$153 -> 1740 | U49: =Assumptions!$C$154 -> 1830 | V49: =Assumptions!$C$155 -> 183 | W49: =Assumptions!$C$156 -> 183 | X49: =Assumptions!$C$157 -> 183 | Y49: =Assumptions!$C$158 -> 1830 | Z49: =Assumptions!$C$159 -> 1830 | AA49: =Assumptions!$C$160 -> 1830 | AB49: =SUM(D49:O49) -> 7062 | AC49: =SUM(P49:AA49) -> 15639
A50: ASP | B50: $ per unit | D50: =Assumptions!$C$10 -> 38 | E50: =Assumptions!$C$10 -> 38 | F50: =Assumptions!$C$10 -> 38 | G50: =Assumptions!$C$10 -> 38 | H50: =Assumptions!$C$10 -> 38 | I50: =Assumptions!$C$10 -> 38 | J50: =Assumptions!$C$10 -> 38 | K50: =Assumptions!$C$10 -> 38 | ... AA50: =Assumptions!$C$10 -> 38 | AB50: =IF(AB49=0,0,AB51/AB49) -> 38 | AC50: =IF(AC49=0,0,AC51/AC49) -> 38
A51: Revenue | B51: $ | D51: =D49*D50 -> 3420 | E51: =E49*E50 -> 5472 | F51: =F49*F50 -> 8208 | G51: =G49*G50 -> 11400 | H51: =H49*H50 -> 14820 | I51: =I49*I50 -> 18696 | J51: =J49*J50 -> 22800 | K51: =K49*K50 -> 27360 | ... AA51: =AA49*AA50 -> 69540 | AB51: =SUM(D51:O51) -> 268356 | AC51: =SUM(P51:AA51) -> 594282
A52: Landed COGS | B52: $ | D52: =D51*D72 -> 1470.6 | E52: =E51*E72 -> 2352.96 | F52: =F51*F72 -> 3529.44 | G52: =G51*G72 -> 4902 | H52: =H51*H72 -> 6372.6 | I52: =I51*I72 -> 8039.28 | J52: =J51*J72 -> 9804 | K52: =K51*K72 -> 11764.8 | ... AA52: =AA51*AA72 -> 29902.2 | AB52: =SUM(D52:O52) -> 115393.08 | AC52: =SUM(P52:AA52) -> 255541.26
A53: Referral fee | B53: $ | D53: =D51*Assumptions!$C$19 -> 513 | E53: =E51*Assumptions!$C$19 -> 820.8 | F53: =F51*Assumptions!$C$19 -> 1231.2 | G53: =G51*Assumptions!$C$19 -> 1710 | H53: =H51*Assumptions!$C$19 -> 2223 | I53: =I51*Assumptions!$C$19 -> 2804.4 | J53: =J51*Assumptions!$C$19 -> 3420 | K53: =K51*Assumptions!$C$19 -> 4104 | ... AA53: =AA51*Assumptions!$C$19 -> 10431 | AB53: =SUM(D53:O53) -> 40253.4 | AC53: =SUM(P53:AA53) -> 89142.3
A54: FBA fulfillment | B54: $ | D54: =D49*D73 -> 495 | E54: =E49*E73 -> 792 | F54: =F49*F73 -> 1188 | G54: =G49*G73 -> 1650 | H54: =H49*H73 -> 2145 | I54: =I49*I73 -> 2706 | J54: =J49*J73 -> 3300 | K54: =K49*K73 -> 3960 | ... AA54: =AA49*AA73 -> 10366.95 | AB54: =SUM(D54:O54) -> 38841 | AC54: =SUM(P54:AA54) -> 87010.935
A55: Returns | B55: $ | D55: =D51*D74 -> 136.8 | E55: =E51*E74 -> 218.88 | F55: =F51*F74 -> 328.32 | G55: =G51*G74 -> 456 | H55: =H51*H74 -> 592.8 | I55: =I51*I74 -> 747.84 | J55: =J51*J74 -> 912 | K55: =K51*K74 -> 1094.4 | ... AA55: =AA51*AA74 -> 2781.6 | AB55: =SUM(D55:O55) -> 10734.24 | AC55: =SUM(P55:AA55) -> 23771.28
A56: Storage and inbound | B56: $ | D56: =D51*Assumptions!$C$21 -> 68.4 | E56: =E51*Assumptions!$C$21 -> 109.44 | F56: =F51*Assumptions!$C$21 -> 164.16 | G56: =G51*Assumptions!$C$21 -> 228 | H56: =H51*Assumptions!$C$21 -> 296.4 | I56: =I51*Assumptions!$C$21 -> 373.92 | J56: =J51*Assumptions!$C$21 -> 456 | K56: =K51*Assumptions!$C$21 -> 547.2 | ... AA56: =AA51*Assumptions!$C$21 -> 1390.8 | AB56: =SUM(D56:O56) -> 5367.12 | AC56: =SUM(P56:AA56) -> 11885.64
A57: Advertising | B57: $ | D57: =D51*D75 -> 1265.4 | E57: =E51*E75 -> 2024.64 | F57: =F51*F75 -> 3036.96 | G57: =G51*G75 -> 3306 | H57: =H51*H75 -> 4297.8 | I57: =I51*I75 -> 5421.84 | J57: =J51*J75 -> 5016 | K57: =K51*K75 -> 6019.2 | ... AA57: =AA51*AA75 -> 12517.2 | AB57: =SUM(D57:O57) -> 64747.44 | AC57: =SUM(P57:AA57) -> 106970.76
A58: Contribution, Amazon US (after advertising) | B58: $ | D58: =D51-D52-D53-D54-D55-D56-D57 -> -529.2 | E58: =E51-E52-E53-E54-E55-E56-E57 -> -846.72 | F58: =F51-F52-F53-F54-F55-F56-F57 -> -1270.08 | G58: =G51-G52-G53-G54-G55-G56-G57 -> -852 | H58: =H51-H52-H53-H54-H55-H56-H57 -> -1107.6 | I58: =I51-I52-I53-I54-I55-I56-I57 -> -1397.28 | J58: =J51-J52-J53-J54-J55-J56-J57 -> -108 | K58: =K51-K52-K53-K54-K55-K56-K57 -> -129.6 | ... AA58: =AA51-AA52-AA53-AA54-AA55-AA56-AA57 -> 2150.25 | AB58: =SUM(D58:O58) -> -6980.28 | AC58: =SUM(P58:AA58) -> 19959.825
A59: Fixed (software, insurance, misc; people from Year 3) | B59: $ | D59: =IF(D$47>=Assumptions!$C$26,Assumptions!$C$45,Assumptions!$C$17) -> 850 | E59: =IF(E$47>=Assumptions!$C$26,Assumptions!$C$45,Assumptions!$C$17) -> 850 | F59: =IF(F$47>=Assumptions!$C$26,Assumptions!$C$45,Assumptions!$C$17) -> 850 | G59: =IF(G$47>=Assumptions!$C$26,Assumptions!$C$45,Assumptions!$C$17) -> 850 | H59: =IF(H$47>=Assumptions!$C$26,Assumptions!$C$45,Assumptions!$C$17) -> 850 | I59: =IF(I$47>=Assumptions!$C$26,Assumptions!$C$45,Assumptions!$C$17) -> 850 | J59: =IF(J$47>=Assumptions!$C$26,Assumptions!$C$45,Assumptions!$C$17) -> 850 | K59: =IF(K$47>=Assumptions!$C$26,Assumptions!$C$45,Assumptions!$C$17) -> 850 | ... AA59: =IF(AA$47>=Assumptions!$C$26,Assumptions!$C$45,Assumptions!$C$17) -> 1200 | AB59: =SUM(D59:O59) -> 10200 | AC59: =SUM(P59:AA59) -> 12300
A60: Professional seller fee | B60: $ | D60: =Assumptions!$C$22 -> 39.99 | E60: =Assumptions!$C$22 -> 39.99 | F60: =Assumptions!$C$22 -> 39.99 | G60: =Assumptions!$C$22 -> 39.99 | H60: =Assumptions!$C$22 -> 39.99 | I60: =Assumptions!$C$22 -> 39.99 | J60: =Assumptions!$C$22 -> 39.99 | K60: =Assumptions!$C$22 -> 39.99 | ... AA60: =Assumptions!$C$22 -> 39.99 | AB60: =SUM(D60:O60) -> 479.88 | AC60: =SUM(P60:AA60) -> 479.88
A61: One time launch costs | B61: $ | D61: =IF(D$47=1,Assumptions!$C$23,0) -> 9500 | E61: =IF(E$47=1,Assumptions!$C$23,0) -> 0 | F61: =IF(F$47=1,Assumptions!$C$23,0) -> 0 | G61: =IF(G$47=1,Assumptions!$C$23,0) -> 0 | H61: =IF(H$47=1,Assumptions!$C$23,0) -> 0 | I61: =IF(I$47=1,Assumptions!$C$23,0) -> 0 | J61: =IF(J$47=1,Assumptions!$C$23,0) -> 0 | K61: =IF(K$47=1,Assumptions!$C$23,0) -> 0 | ... AA61: =IF(AA$47=1,Assumptions!$C$23,0) -> 0 | AB61: =SUM(D61:O61) -> 9500 | AC61: =SUM(P61:AA61) -> 0
A62: Compliance (Form 5472, Wyoming report, bond, insurance; spread over the months from the Year 2 start month to Month 24) | B62: $ | D62: =IF(D$47>=Assumptions!$C$26,(Assumptions!$C$94+Assumptions!$C$95+Assumptions!$C$96+Assumptions!$C$97)/(24-Assumptions!$C$26+1),0) -> 0 | E62: =IF(E$47>=Assumptions!$C$26,(Assumptions!$C$94+Assumptions!$C$95+Assumptions!$C$96+Assumptions!$C$97)/(24-Assumptions!$C$26+1),0) -> 0 | F62: =IF(F$47>=Assumptions!$C$26,(Assumptions!$C$94+Assumptions!$C$95+Assumptions!$C$96+Assumptions!$C$97)/(24-Assumptions!$C$26+1),0) -> 0 | G62: =IF(G$47>=Assumptions!$C$26,(Assumptions!$C$94+Assumptions!$C$95+Assumptions!$C$96+Assumptions!$C$97)/(24-Assumptions!$C$26+1),0) -> 0 | H62: =IF(H$47>=Assumptions!$C$26,(Assumptions!$C$94+Assumptions!$C$95+Assumptions!$C$96+Assumptions!$C$97)/(24-Assumptions!$C$26+1),0) -> 0 | I62: =IF(I$47>=Assumptions!$C$26,(Assumptions!$C$94+Assumptions!$C$95+Assumptions!$C$96+Assumptions!$C$97)/(24-Assumptions!$C$26+1),0) -> 0 | J62: =IF(J$47>=Assumptions!$C$26,(Assumptions!$C$94+Assumptions!$C$95+Assumptions!$C$96+Assumptions!$C$97)/(24-Assumptions!$C$26+1),0) -> 0 | K62: =IF(K$47>=Assumptions!$C$26,(Assumptions!$C$94+Assumptions!$C$95+Assumptions!$C$96+Assumptions!$C$97)/(24-Assumptions!$C$26+1),0) -> 0 | ... AA62: =IF(AA$47>=Assumptions!$C$26,(Assumptions!$C$94+Assumptions!$C$95+Assumptions!$C$96+Assumptions!$C$97)/(24-Assumptions!$C$26+1),0) -> 426.66667 | AB62: =SUM(D62:O62) -> 0 | AC62: =SUM(P62:AA62) -> 2560
A63: Net, Amazon US after fixed costs (August basis) | B63: $ | D63: =D58-D59-D60-D61-D62 -> -10919.19 | E63: =E58-E59-E60-E61-E62 -> -1736.71 | F63: =F58-F59-F60-F61-F62 -> -2160.07 | G63: =G58-G59-G60-G61-G62 -> -1741.99 | H63: =H58-H59-H60-H61-H62 -> -1997.59 | I63: =I58-I59-I60-I61-I62 -> -2287.27 | J63: =J58-J59-J60-J61-J62 -> -997.99 | K63: =K58-K59-K60-K61-K62 -> -1019.59 | ... AA63: =AA58-AA59-AA60-AA61-AA62 -> 483.59333 | AB63: =SUM(D63:O63) -> -27160.16 | AC63: =SUM(P63:AA63) -> 4619.945
A64: Cumulative net | B64: $ | D64: =D63 -> -10919.19 | E64: =D64+E63 -> -12655.9 | F64: =E64+F63 -> -14815.97 | G64: =F64+G63 -> -16557.96 | H64: =G64+H63 -> -18555.55 | I64: =H64+I63 -> -20842.82 | J64: =I64+J63 -> -21840.81 | K64: =J64+K63 -> -22860.4 | L64: =K64+L63 -> -23901.59 | ... AA64: =Z64+AA63 -> -22540.215 | AB64: =O64 -> -27160.16 | AC64: =AA64 -> -22540.215
A65: Net margin | B65: % | D65: =IF(D51=0,0,D63/D51) -> -3.1927456 | E65: =IF(E51=0,0,E63/E51) -> -0.31738121 | F65: =IF(F51=0,0,F63/F51) -> -0.26316642 | G65: =IF(G51=0,0,G63/G51) -> -0.15280614 | H65: =IF(H51=0,0,H63/H51) -> -0.13479015 | I65: =IF(I51=0,0,I63/I51) -> -0.12234007 | J65: =IF(J51=0,0,J63/J51) -> -0.043771491 | K65: =IF(K51=0,0,K63/K51) -> -0.037265716 | ... AC65: =IF(AC51=0,0,AC63/AC51) -> 0.0077739945
A66: TACOS (advertising divided by revenue) | B66: % | D66: =IF(D51=0,0,D57/D51) -> 0.37 | E66: =IF(E51=0,0,E57/E51) -> 0.37 | F66: =IF(F51=0,0,F57/F51) -> 0.37 | G66: =IF(G51=0,0,G57/G51) -> 0.29 | H66: =IF(H51=0,0,H57/H51) -> 0.29 | I66: =IF(I51=0,0,I57/I51) -> 0.29 | J66: =IF(J51=0,0,J57/J51) -> 0.22 | K66: =IF(K51=0,0,K57/K51) -> 0.22 | ... AC66: =IF(AC51=0,0,AC57/AC51) -> 0.18
A67: Contribution per unit before advertising | B67: $ per unit | D67: =IF(D49=0,0,(D58+D57)/D49) -> 8.18 | E67: =IF(E49=0,0,(E58+E57)/E49) -> 8.18 | F67: =IF(F49=0,0,(F58+F57)/F49) -> 8.18 | G67: =IF(G49=0,0,(G58+G57)/G49) -> 8.18 | H67: =IF(H49=0,0,(H58+H57)/H49) -> 8.18 | I67: =IF(I49=0,0,(I58+I57)/I49) -> 8.18 | J67: =IF(J49=0,0,(J58+J57)/J49) -> 8.18 | K67: =IF(K49=0,0,(K58+K57)/K49) -> 8.18 | ... AC67: =IF(AC49=0,0,(AC58+AC57)/AC49) -> 8.1162852
A68: Contribution per unit after advertising | B68: $ per unit | D68: =IF(D49=0,0,D58/D49) -> -5.88 | E68: =IF(E49=0,0,E58/E49) -> -5.88 | F68: =IF(F49=0,0,F58/F49) -> -5.88 | G68: =IF(G49=0,0,G58/G49) -> -2.84 | H68: =IF(H49=0,0,H58/H49) -> -2.84 | I68: =IF(I49=0,0,I58/I49) -> -2.84 | J68: =IF(J49=0,0,J58/J49) -> -0.18 | K68: =IF(K49=0,0,K58/K49) -> -0.18 | ... AC68: =IF(AC49=0,0,AC58/AC49) -> 1.2762852
A69: Cumulative breakeven flag (1 when cumulative net is at or above 0) | B69: flag | D69: =IF(D64>=0,1,0) -> 0 | E69: =IF(E64>=0,1,0) -> 0 | F69: =IF(F64>=0,1,0) -> 0 | G69: =IF(G64>=0,1,0) -> 0 | H69: =IF(H64>=0,1,0) -> 0 | I69: =IF(I64>=0,1,0) -> 0 | J69: =IF(J64>=0,1,0) -> 0 | K69: =IF(K64>=0,1,0) -> 0 | ... AA69: =IF(AA64>=0,1,0) -> 0
A71: Monthly drivers (from Assumptions)
A72: Landed COGS % of revenue (base plus duty, FX and the Year 2 change from the Year 2 start month) | B72: % | D72: =IF(D$47>=Assumptions!$C$26,LandedPctLow+Assumptions!$C$33,LandedPctLow) -> 0.43 | E72: =IF(E$47>=Assumptions!$C$26,LandedPctLow+Assumptions!$C$33,LandedPctLow) -> 0.43 | F72: =IF(F$47>=Assumptions!$C$26,LandedPctLow+Assumptions!$C$33,LandedPctLow) -> 0.43 | G72: =IF(G$47>=Assumptions!$C$26,LandedPctLow+Assumptions!$C$33,LandedPctLow) -> 0.43 | H72: =IF(H$47>=Assumptions!$C$26,LandedPctLow+Assumptions!$C$33,LandedPctLow) -> 0.43 | I72: =IF(I$47>=Assumptions!$C$26,LandedPctLow+Assumptions!$C$33,LandedPctLow) -> 0.43 | J72: =IF(J$47>=Assumptions!$C$26,LandedPctLow+Assumptions!$C$33,LandedPctLow) -> 0.43 | K72: =IF(K$47>=Assumptions!$C$26,LandedPctLow+Assumptions!$C$33,LandedPctLow) -> 0.43 | ... AA72: =IF(AA$47>=Assumptions!$C$26,LandedPctLow+Assumptions!$C$33,LandedPctLow) -> 0.43 | AB72: =IF(AB51=0,0,AB52/AB51) -> 0.43 | AC72: =IF(AC51=0,0,AC52/AC51) -> 0.43
A73: FBA fee per unit (inflation from the Year 2 start month) | B73: $ per unit | D73: =Assumptions!$C$20*IF(D$47>=Assumptions!$C$26,1+Assumptions!$C$32,1) -> 5.5 | E73: =Assumptions!$C$20*IF(E$47>=Assumptions!$C$26,1+Assumptions!$C$32,1) -> 5.5 | F73: =Assumptions!$C$20*IF(F$47>=Assumptions!$C$26,1+Assumptions!$C$32,1) -> 5.5 | G73: =Assumptions!$C$20*IF(G$47>=Assumptions!$C$26,1+Assumptions!$C$32,1) -> 5.5 | H73: =Assumptions!$C$20*IF(H$47>=Assumptions!$C$26,1+Assumptions!$C$32,1) -> 5.5 | I73: =Assumptions!$C$20*IF(I$47>=Assumptions!$C$26,1+Assumptions!$C$32,1) -> 5.5 | J73: =Assumptions!$C$20*IF(J$47>=Assumptions!$C$26,1+Assumptions!$C$32,1) -> 5.5 | K73: =Assumptions!$C$20*IF(K$47>=Assumptions!$C$26,1+Assumptions!$C$32,1) -> 5.5 | ... AA73: =Assumptions!$C$20*IF(AA$47>=Assumptions!$C$26,1+Assumptions!$C$32,1) -> 5.665 | AB73: =IF(AB49=0,0,AB54/AB49) -> 5.5 | AC73: =IF(AC49=0,0,AC54/AC49) -> 5.5637148
A74: Returns % (Year 2 rate from the Year 2 start month) | B74: % | D74: =IF(D$47>=Assumptions!$C$26,Assumptions!$C$31,Assumptions!$C$12) -> 0.04 | E74: =IF(E$47>=Assumptions!$C$26,Assumptions!$C$31,Assumptions!$C$12) -> 0.04 | F74: =IF(F$47>=Assumptions!$C$26,Assumptions!$C$31,Assumptions!$C$12) -> 0.04 | G74: =IF(G$47>=Assumptions!$C$26,Assumptions!$C$31,Assumptions!$C$12) -> 0.04 | H74: =IF(H$47>=Assumptions!$C$26,Assumptions!$C$31,Assumptions!$C$12) -> 0.04 | I74: =IF(I$47>=Assumptions!$C$26,Assumptions!$C$31,Assumptions!$C$12) -> 0.04 | J74: =IF(J$47>=Assumptions!$C$26,Assumptions!$C$31,Assumptions!$C$12) -> 0.04 | K74: =IF(K$47>=Assumptions!$C$26,Assumptions!$C$31,Assumptions!$C$12) -> 0.04 | ... AA74: =IF(AA$47>=Assumptions!$C$26,Assumptions!$C$31,Assumptions!$C$12) -> 0.04 | AB74: =IF(AB51=0,0,AB55/AB51) -> 0.04 | AC74: =IF(AC51=0,0,AC55/AC51) -> 0.04
A75: Ad spend % (phases: Months 1 to 3, 4 to 6, 7 to 12, 13 to 18, then the Year 2 start month to 24) | B75: % | D75: =IF(D$47<=3,Assumptions!$C$13,IF(D$47<=6,Assumptions!$C$14,IF(D$47<=12,Assumptions!$C$15,IF(D$47<Assumptions!$C$26,Assumptions!$C$16,Assumptions!$C$27)))) -> 0.37 | E75: =IF(E$47<=3,Assumptions!$C$13,IF(E$47<=6,Assumptions!$C$14,IF(E$47<=12,Assumptions!$C$15,IF(E$47<Assumptions!$C$26,Assumptions!$C$16,Assumptions!$C$27)))) -> 0.37 | F75: =IF(F$47<=3,Assumptions!$C$13,IF(F$47<=6,Assumptions!$C$14,IF(F$47<=12,Assumptions!$C$15,IF(F$47<Assumptions!$C$26,Assumptions!$C$16,Assumptions!$C$27)))) -> 0.37 | G75: =IF(G$47<=3,Assumptions!$C$13,IF(G$47<=6,Assumptions!$C$14,IF(G$47<=12,Assumptions!$C$15,IF(G$47<Assumptions!$C$26,Assumptions!$C$16,Assumptions!$C$27)))) -> 0.29 | H75: =IF(H$47<=3,Assumptions!$C$13,IF(H$47<=6,Assumptions!$C$14,IF(H$47<=12,Assumptions!$C$15,IF(H$47<Assumptions!$C$26,Assumptions!$C$16,Assumptions!$C$27)))) -> 0.29 | I75: =IF(I$47<=3,Assumptions!$C$13,IF(I$47<=6,Assumptions!$C$14,IF(I$47<=12,Assumptions!$C$15,IF(I$47<Assumptions!$C$26,Assumptions!$C$16,Assumptions!$C$27)))) -> 0.29 | J75: =IF(J$47<=3,Assumptions!$C$13,IF(J$47<=6,Assumptions!$C$14,IF(J$47<=12,Assumptions!$C$15,IF(J$47<Assumptions!$C$26,Assumptions!$C$16,Assumptions!$C$27)))) -> 0.22 | K75: =IF(K$47<=3,Assumptions!$C$13,IF(K$47<=6,Assumptions!$C$14,IF(K$47<=12,Assumptions!$C$15,IF(K$47<Assumptions!$C$26,Assumptions!$C$16,Assumptions!$C$27)))) -> 0.22 | ... AA75: =IF(AA$47<=3,Assumptions!$C$13,IF(AA$47<=6,Assumptions!$C$14,IF(AA$47<=12,Assumptions!$C$15,IF(AA$47<Assumptions!$C$26,Assumptions!$C$16,Assumptions!$C$27)))) -> 0.18 | AB75: =IF(AB51=0,0,AB57/AB51) -> 0.24127443 | AC75: =IF(AC51=0,0,AC57/AC51) -> 0.18
A77: Year 2 channels (Months 13 to 24) so Year 2 ties to the annual tab
A78: eBay and Walmart overflow revenue (% of Amazon US revenue) | B78: $ | D78: =IF(D$47>=13,D51*Assumptions!$C$49,0) -> 0 | E78: =IF(E$47>=13,E51*Assumptions!$C$49,0) -> 0 | F78: =IF(F$47>=13,F51*Assumptions!$C$49,0) -> 0 | G78: =IF(G$47>=13,G51*Assumptions!$C$49,0) -> 0 | H78: =IF(H$47>=13,H51*Assumptions!$C$49,0) -> 0 | I78: =IF(I$47>=13,I51*Assumptions!$C$49,0) -> 0 | J78: =IF(J$47>=13,J51*Assumptions!$C$49,0) -> 0 | K78: =IF(K$47>=13,K51*Assumptions!$C$49,0) -> 0 | ... AA78: =IF(AA$47>=13,AA51*Assumptions!$C$49,0) -> 5563.2 | AB78: =SUM(D78:O78) -> 0 | AC78: =SUM(P78:AA78) -> 47542.56
A79: eBay and Walmart units | B79: units | D79: =IF(D50=0,0,D78/D50) -> 0 | E79: =IF(E50=0,0,E78/E50) -> 0 | F79: =IF(F50=0,0,F78/F50) -> 0 | G79: =IF(G50=0,0,G78/G50) -> 0 | H79: =IF(H50=0,0,H78/H50) -> 0 | I79: =IF(I50=0,0,I78/I50) -> 0 | J79: =IF(J50=0,0,J78/J50) -> 0 | K79: =IF(K50=0,0,K78/K50) -> 0 | ... AA79: =IF(AA50=0,0,AA78/AA50) -> 146.4 | AB79: =SUM(D79:O79) -> 0 | AC79: =SUM(P79:AA79) -> 1251.12
A80: eBay and Walmart landed COGS | B80: $ | D80: =D78*D72 -> 0 | E80: =E78*E72 -> 0 | F80: =F78*F72 -> 0 | G80: =G78*G72 -> 0 | H80: =H78*H72 -> 0 | I80: =I78*I72 -> 0 | J80: =J78*J72 -> 0 | K80: =K78*K72 -> 0 | ... AA80: =AA78*AA72 -> 2392.176 | AB80: =SUM(D80:O80) -> 0 | AC80: =SUM(P80:AA80) -> 20443.301
A81: eBay and Walmart referral | B81: $ | D81: =D78*Assumptions!$C$66 -> 0 | E81: =E78*Assumptions!$C$66 -> 0 | F81: =F78*Assumptions!$C$66 -> 0 | G81: =G78*Assumptions!$C$66 -> 0 | H81: =H78*Assumptions!$C$66 -> 0 | I81: =I78*Assumptions!$C$66 -> 0 | J81: =J78*Assumptions!$C$66 -> 0 | K81: =K78*Assumptions!$C$66 -> 0 | ... AA81: =AA78*Assumptions!$C$66 -> 723.216 | AB81: =SUM(D81:O81) -> 0 | AC81: =SUM(P81:AA81) -> 6180.5328
A82: eBay and Walmart multi channel fulfillment | B82: $ | D82: =D79*Assumptions!$C$67 -> 0 | E82: =E79*Assumptions!$C$67 -> 0 | F82: =F79*Assumptions!$C$67 -> 0 | G82: =G79*Assumptions!$C$67 -> 0 | H82: =H79*Assumptions!$C$67 -> 0 | I82: =I79*Assumptions!$C$67 -> 0 | J82: =J79*Assumptions!$C$67 -> 0 | K82: =K79*Assumptions!$C$67 -> 0 | ... AA82: =AA79*Assumptions!$C$67 -> 951.6 | AB82: =SUM(D82:O82) -> 0 | AC82: =SUM(P82:AA82) -> 8132.28
A83: eBay and Walmart advertising | B83: $ | D83: =D78*Assumptions!$C$68 -> 0 | E83: =E78*Assumptions!$C$68 -> 0 | F83: =F78*Assumptions!$C$68 -> 0 | G83: =G78*Assumptions!$C$68 -> 0 | H83: =H78*Assumptions!$C$68 -> 0 | I83: =I78*Assumptions!$C$68 -> 0 | J83: =J78*Assumptions!$C$68 -> 0 | K83: =K78*Assumptions!$C$68 -> 0 | ... AA83: =AA78*Assumptions!$C$68 -> 278.16 | AB83: =SUM(D83:O83) -> 0 | AC83: =SUM(P83:AA83) -> 2377.128
A84: eBay and Walmart returns | B84: $ | D84: =D78*Assumptions!$C$69 -> 0 | E84: =E78*Assumptions!$C$69 -> 0 | F84: =F78*Assumptions!$C$69 -> 0 | G84: =G78*Assumptions!$C$69 -> 0 | H84: =H78*Assumptions!$C$69 -> 0 | I84: =I78*Assumptions!$C$69 -> 0 | J84: =J78*Assumptions!$C$69 -> 0 | K84: =K78*Assumptions!$C$69 -> 0 | ... AA84: =AA78*Assumptions!$C$69 -> 166.896 | AB84: =SUM(D84:O84) -> 0 | AC84: =SUM(P84:AA84) -> 1426.2768
A85: eBay and Walmart contribution | B85: $ | D85: =D78-D80-D81-D82-D83-D84 -> 0 | E85: =E78-E80-E81-E82-E83-E84 -> 0 | F85: =F78-F80-F81-F82-F83-F84 -> 0 | G85: =G78-G80-G81-G82-G83-G84 -> 0 | H85: =H78-H80-H81-H82-H83-H84 -> 0 | I85: =I78-I80-I81-I82-I83-I84 -> 0 | J85: =J78-J80-J81-J82-J83-J84 -> 0 | K85: =K78-K80-K81-K82-K83-K84 -> 0 | ... AA85: =AA78-AA80-AA81-AA82-AA83-AA84 -> 1051.152 | AB85: =SUM(D85:O85) -> 0 | AC85: =SUM(P85:AA85) -> 8983.0416
A86: B2B installer and AV integrator revenue (Year 2 total spread evenly) | B86: $ | D86: =IF(D$47>=13,Assumptions!$C$53/12,0) -> 0 | E86: =IF(E$47>=13,Assumptions!$C$53/12,0) -> 0 | F86: =IF(F$47>=13,Assumptions!$C$53/12,0) -> 0 | G86: =IF(G$47>=13,Assumptions!$C$53/12,0) -> 0 | H86: =IF(H$47>=13,Assumptions!$C$53/12,0) -> 0 | I86: =IF(I$47>=13,Assumptions!$C$53/12,0) -> 0 | J86: =IF(J$47>=13,Assumptions!$C$53/12,0) -> 0 | K86: =IF(K$47>=13,Assumptions!$C$53/12,0) -> 0 | ... AA86: =IF(AA$47>=13,Assumptions!$C$53/12,0) -> 0 | AB86: =SUM(D86:O86) -> 0 | AC86: =SUM(P86:AA86) -> 0
A87: B2B units (price 60% of retail ASP) | B87: units | D87: =IF(D50=0,0,D86/(D50*Assumptions!$C$70)) -> 0 | E87: =IF(E50=0,0,E86/(E50*Assumptions!$C$70)) -> 0 | F87: =IF(F50=0,0,F86/(F50*Assumptions!$C$70)) -> 0 | G87: =IF(G50=0,0,G86/(G50*Assumptions!$C$70)) -> 0 | H87: =IF(H50=0,0,H86/(H50*Assumptions!$C$70)) -> 0 | I87: =IF(I50=0,0,I86/(I50*Assumptions!$C$70)) -> 0 | J87: =IF(J50=0,0,J86/(J50*Assumptions!$C$70)) -> 0 | K87: =IF(K50=0,0,K86/(K50*Assumptions!$C$70)) -> 0 | ... AA87: =IF(AA50=0,0,AA86/(AA50*Assumptions!$C$70)) -> 0 | AB87: =SUM(D87:O87) -> 0 | AC87: =SUM(P87:AA87) -> 0
A88: B2B landed COGS | B88: $ | D88: =D87*D50*D72 -> 0 | E88: =E87*E50*E72 -> 0 | F88: =F87*F50*F72 -> 0 | G88: =G87*G50*G72 -> 0 | H88: =H87*H50*H72 -> 0 | I88: =I87*I50*I72 -> 0 | J88: =J87*J50*J72 -> 0 | K88: =K87*K50*K72 -> 0 | ... AA88: =AA87*AA50*AA72 -> 0 | AB88: =SUM(D88:O88) -> 0 | AC88: =SUM(P88:AA88) -> 0
A89: B2B 3PL pick pack ship | B89: $ | D89: =D87*Assumptions!$C$71 -> 0 | E89: =E87*Assumptions!$C$71 -> 0 | F89: =F87*Assumptions!$C$71 -> 0 | G89: =G87*Assumptions!$C$71 -> 0 | H89: =H87*Assumptions!$C$71 -> 0 | I89: =I87*Assumptions!$C$71 -> 0 | J89: =J87*Assumptions!$C$71 -> 0 | K89: =K87*Assumptions!$C$71 -> 0 | ... AA89: =AA87*Assumptions!$C$71 -> 0 | AB89: =SUM(D89:O89) -> 0 | AC89: =SUM(P89:AA89) -> 0
A90: B2B sales commission | B90: $ | D90: =D86*Assumptions!$C$72 -> 0 | E90: =E86*Assumptions!$C$72 -> 0 | F90: =F86*Assumptions!$C$72 -> 0 | G90: =G86*Assumptions!$C$72 -> 0 | H90: =H86*Assumptions!$C$72 -> 0 | I90: =I86*Assumptions!$C$72 -> 0 | J90: =J86*Assumptions!$C$72 -> 0 | K90: =K86*Assumptions!$C$72 -> 0 | ... AA90: =AA86*Assumptions!$C$72 -> 0 | AB90: =SUM(D90:O90) -> 0 | AC90: =SUM(P90:AA90) -> 0
A91: B2B marketing | B91: $ | D91: =D86*Assumptions!$C$73 -> 0 | E91: =E86*Assumptions!$C$73 -> 0 | F91: =F86*Assumptions!$C$73 -> 0 | G91: =G86*Assumptions!$C$73 -> 0 | H91: =H86*Assumptions!$C$73 -> 0 | I91: =I86*Assumptions!$C$73 -> 0 | J91: =J86*Assumptions!$C$73 -> 0 | K91: =K86*Assumptions!$C$73 -> 0 | ... AA91: =AA86*Assumptions!$C$73 -> 0 | AB91: =SUM(D91:O91) -> 0 | AC91: =SUM(P91:AA91) -> 0
A92: B2B returns | B92: $ | D92: =D86*Assumptions!$C$74 -> 0 | E92: =E86*Assumptions!$C$74 -> 0 | F92: =F86*Assumptions!$C$74 -> 0 | G92: =G86*Assumptions!$C$74 -> 0 | H92: =H86*Assumptions!$C$74 -> 0 | I92: =I86*Assumptions!$C$74 -> 0 | J92: =J86*Assumptions!$C$74 -> 0 | K92: =K86*Assumptions!$C$74 -> 0 | ... AA92: =AA86*Assumptions!$C$74 -> 0 | AB92: =SUM(D92:O92) -> 0 | AC92: =SUM(P92:AA92) -> 0
A93: B2B contribution | B93: $ | D93: =D86-D88-D89-D90-D91-D92 -> 0 | E93: =E86-E88-E89-E90-E91-E92 -> 0 | F93: =F86-F88-F89-F90-F91-F92 -> 0 | G93: =G86-G88-G89-G90-G91-G92 -> 0 | H93: =H86-H88-H89-H90-H91-H92 -> 0 | I93: =I86-I88-I89-I90-I91-I92 -> 0 | J93: =J86-J88-J89-J90-J91-J92 -> 0 | K93: =K86-K88-K89-K90-K91-K92 -> 0 | ... AA93: =AA86-AA88-AA89-AA90-AA91-AA92 -> 0 | AB93: =SUM(D93:O93) -> 0 | AC93: =SUM(P93:AA93) -> 0
A95: All channels
A96: Revenue, all channels | B96: $ | D96: =D51+D78+D86 -> 3420 | E96: =E51+E78+E86 -> 5472 | F96: =F51+F78+F86 -> 8208 | G96: =G51+G78+G86 -> 11400 | H96: =H51+H78+H86 -> 14820 | I96: =I51+I78+I86 -> 18696 | J96: =J51+J78+J86 -> 22800 | K96: =K51+K78+K86 -> 27360 | ... AA96: =AA51+AA78+AA86 -> 75103.2 | AB96: =SUM(D96:O96) -> 268356 | AC96: =SUM(P96:AA96) -> 641824.56
A97: Net, all channels | B97: $ | D97: =D63+D85+D93 -> -10919.19 | E97: =E63+E85+E93 -> -1736.71 | F97: =F63+F85+F93 -> -2160.07 | G97: =G63+G85+G93 -> -1741.99 | H97: =H63+H85+H93 -> -1997.59 | I97: =I63+I85+I93 -> -2287.27 | J97: =J63+J85+J93 -> -997.99 | K97: =K63+K85+K93 -> -1019.59 | ... AA97: =AA63+AA85+AA93 -> 1534.7453 | AB97: =SUM(D97:O97) -> -27160.16 | AC97: =SUM(P97:AA97) -> 13602.987
A98: Cumulative net, all channels | B98: $ | D98: =D97 -> -10919.19 | E98: =D98+E97 -> -12655.9 | F98: =E98+F97 -> -14815.97 | G98: =F98+G97 -> -16557.96 | H98: =G98+H97 -> -18555.55 | I98: =H98+I97 -> -20842.82 | J98: =I98+J97 -> -21840.81 | K98: =J98+K97 -> -22860.4 | L98: =K98+L97 -> -23901.59 | ... AA98: =Z98+AA97 -> -13557.173 | AB98: =O98 -> -27160.16 | AC98: =AA98 -> -13557.173
A99: Net margin, all channels | B99: % | D99: =IF(D96=0,0,D97/D96) -> -3.1927456 | E99: =IF(E96=0,0,E97/E96) -> -0.31738121 | F99: =IF(F96=0,0,F97/F96) -> -0.26316642 | G99: =IF(G96=0,0,G97/G96) -> -0.15280614 | H99: =IF(H96=0,0,H97/H96) -> -0.13479015 | I99: =IF(I96=0,0,I97/I96) -> -0.12234007 | J99: =IF(J96=0,0,J97/J96) -> -0.043771491 | K99: =IF(K96=0,0,K97/K96) -> -0.037265716 | ... AC99: =IF(AC96=0,0,AC97/AC96) -> 0.021194244
A101: Eighteen month block (Amazon US only, August basis, Months 1 to 18)
A102: 18 month revenue | C102: =SUM(D51:U51) -> 633156
A103: 18 month net | C103: =SUM(D63:U63) -> -19636.1
A104: 18 month net margin | C104: =IF(C102=0,0,C103/C102) -> -0.031013052
A105: Cumulative breakeven month within 18 months (none if never) | C105: =IFERROR(MATCH(1,D69:U69,0),"none") -> none
A106: Month 18 run rate (Month 18 revenue times 12) | C106: =U51*12 -> 834480
A107: Exit margin (Month 18 net margin) | C107: =U65 -> 0.022464912
A108: 18 month units | C108: =SUM(D49:U49) -> 16662
A109: Cumulative breakeven month within 24 months (all channels) | C109: =IFERROR(MATCH(1,D69:AA69,0),"none") -> none
A110: 24 month revenue, all channels | C110: =SUM(D96:AA96) -> 910180.56
A111: 24 month net, all channels | C111: =SUM(D97:AA97) -> -13557.173
A113: Low scenario: annual P&L engine
A114: Line | B114: Unit | C114: Year 1 | D114: Year 2 | E114: Year 3 | F114: Year 4 | G114: Year 5 | H114: Basis
A115: Amazon US drivers
A116: Amazon US units | B116: units | C116: =AB49 -> 7062 | D116: =AC49 -> 15639 | E116: =D116*(1+Assumptions!$C$37) -> 17202.9 | F116: =E116*(1+Assumptions!$C$38) -> 18579.132 | G116: =F116*(1+Assumptions!$C$39) -> 19508.089 | H116: Years 1 and 2 from the monthly tab; then unit growth driver
A117: ASP (Years 3 to 5: yearly change plus the Year 3 roadmap mix uplift) | B117: $ per unit | C117: =AB50 -> 38 | D117: =AC50 -> 38 | E117: =D117*(1+Assumptions!$C$40)*IF(3=3,1+Assumptions!$C$41,1) -> 36.48 | F117: =E117*(1+Assumptions!$C$40)*IF(4=3,1+Assumptions!$C$41,1) -> 35.0208 | G117: =F117*(1+Assumptions!$C$40)*IF(5=3,1+Assumptions!$C$41,1) -> 33.619968
...

Sheet Plan B
A1: Plan B: B2B installer distribution in the US plus continued Korea wholesale (if Amazon fails)
A2: A side business, shown honestly. B2B at the B2B economics (price 60% of retail, 3PL only, no Amazon fees). Korea wholesale at the August deal pace. Reads the Medium column of Assumptions (not the Active column) because Plan B is a fixed side case per spec 2.7; the landed % follows the duty and FX selectors.
A4: Line | B4: Unit | C4: Year 1 | D4: Year 2 | E4: Year 3 | F4: Basis
A5: B2B installer revenue | B5: $ | C5: 120000 | D5: 300000 | E5: 450000 | F5: Management estimate (spec 2.7)
A6: Retail ASP reference (Medium) | B6: $ per unit | C6: =Assumptions!$D$10 -> 42 | D6: =Assumptions!$D$10 -> 42 | E6: =Assumptions!$D$10 -> 42 | F6: August model
A7: Landed COGS % (Medium, active duty and FX) | B7: % | C7: =LandedPctMedium -> 0.38 | D7: =LandedPctMedium -> 0.38 | E7: =LandedPctMedium -> 0.38
A8: B2B units (price 60% of retail) | B8: units | C8: =C5/(C6*Assumptions!$D$70) -> 4761.9048 | D8: =D5/(D6*Assumptions!$D$70) -> 11904.762 | E8: =E5/(E6*Assumptions!$D$70) -> 17857.143
A9: Landed COGS | B9: $ | C9: =C8*C6*C7 -> 76000 | D9: =D8*D6*D7 -> 190000 | E9: =E8*E6*E7 -> 285000
A10: 3PL pick pack ship | B10: $ | C10: =C8*Assumptions!$D$71 -> 19047.619 | D10: =D8*Assumptions!$D$71 -> 47619.048 | E10: =E8*Assumptions!$D$71 -> 71428.571
A11: Sales commission | B11: $ | C11: =C5*Assumptions!$D$72 -> 6000 | D11: =D5*Assumptions!$D$72 -> 15000 | E11: =E5*Assumptions!$D$72 -> 22500
A12: Marketing | B12: $ | C12: =C5*Assumptions!$D$73 -> 3600 | D12: =D5*Assumptions!$D$73 -> 9000 | E12: =E5*Assumptions!$D$73 -> 13500
A13: Returns | B13: $ | C13: =C5*Assumptions!$D$74 -> 2400 | D13: =D5*Assumptions!$D$74 -> 6000 | E13: =E5*Assumptions!$D$74 -> 9000
A14: B2B contribution | B14: $ | C14: =C5-C9-C10-C11-C12-C13 -> 12952.381 | D14: =D5-D9-D10-D11-D12-D13 -> 32380.952 | E14: =E5-E9-E10-E11-E12-E13 -> 48571.429
A16: Korea wholesale deals per year (August deal pace) | B16: deals | C16: 4 | D16: 4 | E16: 4 | F16: Management estimate
A17: Units per deal | B17: units | C17: =FX!$B$9 -> 1400 | D17: =FX!$B$9 -> 1400 | E17: =FX!$B$9 -> 1400 | F17: August deal units (FX tab input)
A18: Gross profit per unit, Year 1 (August deal: about $2.50 per unit) | B18: $ per unit | C18: 2.5 | F18: Management estimate
A19: Gross profit per unit growth per year | B19: % | D19: 0.15 | E19: 0.15 | F19: Management estimate
A20: Gross profit per unit (Year 1 input, then growing by the rate above) | B20: $ per unit | C20: =C18 -> 2.5 | D20: =C20*(1+D19) -> 2.875 | E20: =D20*(1+E19) -> 3.30625 | F20: Management estimate
A21: August deal revenue per unit in USD (FX tab deal revenue divided by the units per deal) | B21: $ per unit | C21: =FX!$B$20/C17 -> 12.187812 | D21: =FX!$B$20/D17 -> 12.187812 | E21: =FX!$B$20/E17 -> 12.187812 | F21: August deal revenue (FX tab input) on the units per deal, at FXRate
A22: Korea wholesale revenue (deals times units times the August deal revenue per unit) | B22: $ | C22: =C16*C17*C21 -> 68251.748 | D22: =D16*D17*D21 -> 68251.748 | E22: =E16*E17*E21 -> 68251.748 | F22: August deal
A23: Korea wholesale gross profit | B23: $ | C23: =C16*C17*C20 -> 14000 | D23: =D16*D17*D20 -> 16100 | E23: =E16*E17*E20 -> 18515
A25: Fixed costs (software, insurance, 3PL account) per month | B25: $ | C25: 850 | D25: 1200 | E25: 1200 | F25: Management estimate: 850 per month Year 1, 1,200 after
A26: Fixed costs per year | B26: $ | C26: =C25*12 -> 10200 | D26: =D25*12 -> 14400 | E26: =E25*12 -> 14400
A27: Compliance (Form 5472, Wyoming report, bond, insurance) from Year 2 | B27: $ | C27: =0 -> 0 | D27: =Assumptions!$D$94+Assumptions!$D$95+Assumptions!$D$96+Assumptions!$D$97 -> 2560 | E27: =Assumptions!$D$94+Assumptions!$D$95+Assumptions!$D$96+Assumptions!$D$97 -> 2560
A28: Plan B revenue (B2B plus Korea wholesale) | B28: $ | C28: =C5+C22 -> 188251.75 | D28: =D5+D22 -> 368251.75 | E28: =E5+E22 -> 518251.75
A29: Plan B net (B2B contribution plus Korea gross profit less fixed and compliance) | B29: $ | C29: =C14+C23-C26-C27 -> 16752.381 | D29: =D14+D23-D26-D27 -> 31520.952 | E29: =E14+E23-E26-E27 -> 50126.429
A30: Plan B net margin | B30: % | C30: =IF(C28=0,0,C29/C28) -> 0.088989245 | D30: =IF(D28=0,0,D29/D28) -> 0.085596206 | E30: =IF(E28=0,0,E29/E28) -> 0.09672216
A31: Cumulative Plan B net | B31: $ | C31: =C29 -> 16752.381 | D31: =C31+D29 -> 48273.333 | E31: =D31+E29 -> 98399.762
A33: Plan B keeps the LLC, the bond and the insurance. It does not need Amazon fees, advertising at Amazon rates or the inventory cover of the Amazon plan.
