Workbook

Sheet Cover
A1: 06 Compliance Checklist: BRAND LLC US launch
A2: Built October 8, 2026. Generator build/build_checklist.py. Facts from build/facts.json, model numbers from build/figures.json.
A4: Purpose | B4: Every US, Korea, Amazon, HDMI, FCC, Prop 65, CL3, insurance, customs, product labeling and data item the launch needs, each with an owner, a due point, an estimated cost, the evidence that proves it is done, a status and the basis of the entry.
A5: How to use | B5: Work in the Checklist tab. Change only the Status column (dropdown: Not started, In progress, Done, Blocked) and, when a quote arrives, the Estimated cost. The summary block at the top and the Summary tab recalculate. Mark reviews it in week 4 of every month (05_Operating_Processes.docx section 8); Lucy approves and pays; the owner files; the evidence goes into the compliance folder.
A6: Readers | B6: Lucy (owner, signs everything), Mark (keeps the calendar), 세무사 (Korea foreign exchange and Korea tax rows), US CPA (US tax rows), attorney (brand and trademark, agreements), customs broker (customs rows), factory (HDMI, FCC, Prop 65, CL3 documents).
A7: Due | B7: Relative to the launch critical path: weeks count from the start of formation; Month 1 is the first month with inventory live on Amazon (assumed early 2027); fixed calendar deadlines (Form 5472 by April 15) are shown as dates.
A8: Estimated cost | B8: USD for the first 12 months after formation, Medium case. Facts from the brief where known (state fee $100, annual report $60, trademark $350 per class, bond $500, entry fee $150, seller fee $39.99 per month). Everything else is a management estimate marked [PLACEHOLDER: ...] in Notes until the named professional quotes. Costs carried per unit in the model (QC, broker per unit, duty) are not repeated here.
A9: Tie to the model | B9: The August model carries Year 1 compliance inside the $9,500 one time launch costs and the $850 per month fixed costs; from Year 2 the model carries $2,560 per year (Form 5472 preparation $800, Wyoming report $60, bond $500, insurance $1,200). Opening capital $39,000; Medium funding gap $116K needed by Month 2 (03_Financial_Model_5Y.xlsx).
A10: Basis | B10: Evidence based = brief section 1, the August model, or a verified regulatory fact. Management estimate = the build team's assumption, to be confirmed by the named owner. Nothing in this file asserts a certification, license or legal status that the brief did not verify; those cells carry a labeled placeholder.
A11: Legend | B11: Yellow fill with blue text = cell you edit (Status, Estimated cost). Black = fixed text or formula. Green = pulled from another sheet.
A12: Hard stops | B12: No capital transfer before the ODI report is accepted by the foreign exchange bank. No PO before the HDMI Adopter certificate, ATC report and FCC report are on file. No in wall claim before the CL3 documentation. No HDMI version number on any box or promotion.
A14: Glossary
A15: AOC | B15: active optical cable
A16: HDMI | B16: High Definition Multimedia Interface
A17: HDMI LA | B17: HDMI Licensing Administrator
A18: ATC | B18: HDMI Authorized Test Center
A19: FCC | B19: Federal Communications Commission
A20: Prop 65 | B20: California Proposition 65 warning label
A21: CL3 | B21: in wall cable fire rating (Class 3)
A22: CBP | B22: US Customs and Border Protection
A23: HTS | B23: Harmonized Tariff Schedule
A24: MFN | B24: most favored nation duty rate
A25: Section 301 | B25: US trade law tariffs on China origin goods
A26: EIN | B26: Employer Identification Number
... A48: ITIN | B48: individual taxpayer identification number

Sheet Checklist
A1: Compliance checklist: BRAND LLC US launch (Lucy, Hyejin Yoo, 100% owner; H2 Company, Seoul)
A2: Edit the yellow cells only. Status dropdown: Not started, In progress, Done, Blocked. Spare rows below the last item take new entries and the counts include them. Built October 8, 2026.
A4: Summary | B4: Items | C4: Not started | D4: In progress | E4: Done | F4: Blocked | G4: Done % | H4: Cost (12 months)
B5: =COUNTA($A$9:$A$153) -> 105 | C5: =COUNTIF($H$9:$H$153,"Not started") -> 105 | D5: =COUNTIF($H$9:$H$153,"In progress") -> 0 | E5: =COUNTIF($H$9:$H$153,"Done") -> 0 | F5: =COUNTIF($H$9:$H$153,"Blocked") -> 0 | G5: =IF(B5=0,0,E5/B5) -> 0 | H5: =SUM($F$9:$F$153) -> 13514.88
A6: Status check (0 = ok) | B6: =B5-SUM(C5:F5) -> 0
A8: Area | B8: Item | C8: Jurisdiction | D8: Owner | E8: Due | F8: Estimated cost (USD, first 12 months) | G8: Evidence required | H8: Status | I8: Notes | J8: Basis
A9: US entity | B9: Decide the US brand name so the legal name BRAND LLC is final before any filing | C9: US (Wyoming) | D9: Lucy, Mark | E9: Week 1 | F9: 0 | G9: Written decision in 11_Decision_Log.md | H9: Not started | I9: One time. The Korean deck used MBF; nothing is filed until the name is chosen. The same spelling is then used at the state, the IRS, the bank and Amazon. | J9: Evidence based
A10: US entity | B10: Check name availability with the Wyoming Secretary of State | C10: US (Wyoming) | D10: Lucy, attorney | E10: Week 1 | F10: 0 | G10: Screenshot of the availability search | H10: Not started | I10: One time. Free search. Do it the same day as the trademark clearance search so both names agree. | J10: Management estimate
A11: US entity | B11: File the articles of organization for a Wyoming single member LLC | C11: US (Wyoming) | D11: Lucy, attorney or formation service | E11: Weeks 1 to 2 | F11: 100 | G11: Certificate of organization from the Secretary of State | H11: Not started | I11: One time. State fee $100 (brief). No state income tax; strong privacy. Delaware costs about $300 per year and is only worth it for raising investment. | J11: Evidence based
A12: US entity | B12: Appoint a Wyoming registered agent | C12: US (Wyoming) | D12: Lucy | E12: Weeks 1 to 2 | F12: 125 | G12: Registered agent agreement and the agent's address on the articles | H12: Not started | I12: Per year. Fee is a management estimate [PLACEHOLDER: agent quote]. The agent receives state and legal mail; set the renewal reminder with the annual report. | J12: Management estimate
A13: US entity | B13: Sign a single member operating agreement naming Lucy (Hyejin Yoo) as 100% owner | C13: US (Wyoming) | D13: Lucy, attorney | E13: Weeks 1 to 2 | F13: 300 | G13: Signed operating agreement in the entity folder | H13: Not started | I13: One time. Attorney fee is a management estimate [PLACEHOLDER: attorney quote]. Banks and Amazon ask for it. Mark holds no equity (DECISIONS.md decision 2); if he did, the LLC becomes a partnership with Form 1065 and 37% withholding on Lucy's share. | J13: Evidence based
A14: US entity | B14: Obtain the EIN by phone or fax with Form SS-4 (no SSN needed) | C14: US (federal, IRS) | D14: Lucy, attorney | E14: Weeks 1 to 2 | F14: 0 | G14: IRS EIN confirmation letter [PLACEHOLDER: EIN] | H14: Not started | I14: One time. Free. The EIN is the importer of record number for CBP and the tax ID for the bank and Amazon. | J14: Evidence based
A15: US entity | B15: Exact legal name match across state, IRS, bank and Amazon | C15: US | D15: Lucy, Mark | E15: Weeks 1 to 4, checked at every registration | F15: 0 | G15: One page showing the name on the certificate, the EIN letter, the bank letter and Seller Central | H15: Not started | I15: Ongoing. A single spelling difference (LLC versus L.L.C., a missing comma) blocks Amazon identity verification. | J15: Evidence based
A16: US entity | B16: Record that no BOI report is needed (FinCEN exemption for US formed companies, finalized August 11, 2026) | C16: US (federal, FinCEN) | D16: Lucy, attorney | E16: Week 2 | F16: 0 | G16: Note in the entity folder citing the exemption | H16: Not started | I16: One time. No filing. Revisit only if the rule changes or the LLC is reorganized under a foreign parent. | J16: Evidence based
A17: US entity | B17: Written consulting or commission agreement between BRAND LLC and Mark Taylor (no equity, no authority to negotiate or sign) | C17: US | D17: Lucy, Mark, attorney | E17: Before the Amazon account opens (week 3) | F17: 500 | G17: Signed agreement | H17: Not started | I17: One time. Attorney fee is a management estimate [PLACEHOLDER: attorney quote]. The wording keeps the treaty position: Mark is not a dependent agent of the LLC. | J17: Evidence based
A18: US entity | B18: No US office, no US employees, no US agent who negotiates or signs contracts (treaty position policy) | C18: US | D18: Lucy, Mark | E18: Ongoing, reviewed every quarter | F18: 0 | G18: Quarterly confirmation line in the compliance review | H18: Not started | I18: Ongoing. Goods stored and shipped from FBA warehouses do not create a permanent establishment (1976 US Korea tax treaty, Article 9(3)(b)). Any hire or lease in the US reopens the question with the CPA first. | J18: Evidence based
A19: US entity | B19: US business mailing address for the LLC (registered agent or virtual mailbox) | C19: US | D19: Lucy, Mark | E19: Week 2 | F19: 120 | G19: Mailbox agreement; address used on the IRS, bank and Amazon forms | H19: Not started | I19: Per year. Management estimate [PLACEHOLDER: mailbox quote]. A mailbox is not an office and does not create a permanent establishment; do not use Mark's home or business address as the LLC's place of business. | J19: Management estimate
A20: US entity | B20: Wyoming annual report and license tax | C20: US (Wyoming) | D20: Lucy, registered agent | E20: Annually, formation anniversary month [PLACEHOLDER: exact date from the registered agent] | F20: 60 | G20: Filing receipt from the Secretary of State | H20: Not started | I20: Per year, about $60 (brief). Missing it costs good standing and can freeze the bank or Amazon account. | J20: Evidence based
... A113: Data and privacy (placeholder) | B113: Access control and password manager for Seller Central, bank, registrar and email platform | C113: US | D113: Mark | E113: Week 4 | F113: 60 | G113: Password manager account; access list | H113: Not started | I113: Per year. Management estimate [PLACEHOLDER: tool price]. | J113: Management estimate
A154: End of list. Add new items in the spare rows above this line so the summary counts them.

Sheet Summary
A1: Summary: counts by status and area, cost by area (live formulas reading the Checklist tab)
A2: All counts and sums are COUNTIF, COUNTIFS and SUMIFS over the Checklist tab, including the spare rows.
A4: Area | B4: Items | C4: Not started | D4: In progress | E4: Done | F4: Blocked | G4: Estimated cost, first 12 months | H4: Done %
A5: US entity | B5: =COUNTIF(Checklist!$A$9:$A$153,A5) -> 13 | C5: =COUNTIFS(Checklist!$A$9:$A$153,$A5,Checklist!$H$9:$H$153,"Not started") -> 13 | D5: =COUNTIFS(Checklist!$A$9:$A$153,$A5,Checklist!$H$9:$H$153,"In progress") -> 0 | E5: =COUNTIFS(Checklist!$A$9:$A$153,$A5,Checklist!$H$9:$H$153,"Done") -> 0 | F5: =COUNTIFS(Checklist!$A$9:$A$153,$A5,Checklist!$H$9:$H$153,"Blocked") -> 0 | G5: =SUMIFS(Checklist!$F$9:$F$153,Checklist!$A$9:$A$153,$A5) -> 1205 | H5: =IF(B5=0,0,E5/B5) -> 0
A6: US tax | B6: =COUNTIF(Checklist!$A$9:$A$153,A6) -> 9 | C6: =COUNTIFS(Checklist!$A$9:$A$153,$A6,Checklist!$H$9:$H$153,"Not started") -> 9 | D6: =COUNTIFS(Checklist!$A$9:$A$153,$A6,Checklist!$H$9:$H$153,"In progress") -> 0 | E6: =COUNTIFS(Checklist!$A$9:$A$153,$A6,Checklist!$H$9:$H$153,"Done") -> 0 | F6: =COUNTIFS(Checklist!$A$9:$A$153,$A6,Checklist!$H$9:$H$153,"Blocked") -> 0 | G6: =SUMIFS(Checklist!$F$9:$F$153,Checklist!$A$9:$A$153,$A6) -> 800 | H6: =IF(B6=0,0,E6/B6) -> 0
A7: Korea foreign exchange | B7: =COUNTIF(Checklist!$A$9:$A$153,A7) -> 8 | C7: =COUNTIFS(Checklist!$A$9:$A$153,$A7,Checklist!$H$9:$H$153,"Not started") -> 8 | D7: =COUNTIFS(Checklist!$A$9:$A$153,$A7,Checklist!$H$9:$H$153,"In progress") -> 0 | E7: =COUNTIFS(Checklist!$A$9:$A$153,$A7,Checklist!$H$9:$H$153,"Done") -> 0 | F7: =COUNTIFS(Checklist!$A$9:$A$153,$A7,Checklist!$H$9:$H$153,"Blocked") -> 0 | G7: =SUMIFS(Checklist!$F$9:$F$153,Checklist!$A$9:$A$153,$A7) -> 300 | H7: =IF(B7=0,0,E7/B7) -> 0
A8: Korea tax | B8: =COUNTIF(Checklist!$A$9:$A$153,A8) -> 6 | C8: =COUNTIFS(Checklist!$A$9:$A$153,$A8,Checklist!$H$9:$H$153,"Not started") -> 6 | D8: =COUNTIFS(Checklist!$A$9:$A$153,$A8,Checklist!$H$9:$H$153,"In progress") -> 0 | E8: =COUNTIFS(Checklist!$A$9:$A$153,$A8,Checklist!$H$9:$H$153,"Done") -> 0 | F8: =COUNTIFS(Checklist!$A$9:$A$153,$A8,Checklist!$H$9:$H$153,"Blocked") -> 0 | G8: =SUMIFS(Checklist!$F$9:$F$153,Checklist!$A$9:$A$153,$A8) -> 600 | H8: =IF(B8=0,0,E8/B8) -> 0
A9: Amazon account | B9: =COUNTIF(Checklist!$A$9:$A$153,A9) -> 14 | C9: =COUNTIFS(Checklist!$A$9:$A$153,$A9,Checklist!$H$9:$H$153,"Not started") -> 14 | D9: =COUNTIFS(Checklist!$A$9:$A$153,$A9,Checklist!$H$9:$H$153,"In progress") -> 0 | E9: =COUNTIFS(Checklist!$A$9:$A$153,$A9,Checklist!$H$9:$H$153,"Done") -> 0 | F9: =COUNTIFS(Checklist!$A$9:$A$153,$A9,Checklist!$H$9:$H$153,"Blocked") -> 0 | G9: =SUMIFS(Checklist!$F$9:$F$153,Checklist!$A$9:$A$153,$A9) -> 929.88 | H9: =IF(B9=0,0,E9/B9) -> 0
A10: Brand and trademark | B10: =COUNTIF(Checklist!$A$9:$A$153,A10) -> 9 | C10: =COUNTIFS(Checklist!$A$9:$A$153,$A10,Checklist!$H$9:$H$153,"Not started") -> 9 | D10: =COUNTIFS(Checklist!$A$9:$A$153,$A10,Checklist!$H$9:$H$153,"In progress") -> 0 | E10: =COUNTIFS(Checklist!$A$9:$A$153,$A10,Checklist!$H$9:$H$153,"Done") -> 0 | F10: =COUNTIFS(Checklist!$A$9:$A$153,$A10,Checklist!$H$9:$H$153,"Blocked") -> 0 | G10: =SUMIFS(Checklist!$F$9:$F$153,Checklist!$A$9:$A$153,$A10) -> 1870 | H10: =IF(B10=0,0,E10/B10) -> 0
A11: HDMI licensing | B11: =COUNTIF(Checklist!$A$9:$A$153,A11) -> 6 | C11: =COUNTIFS(Checklist!$A$9:$A$153,$A11,Checklist!$H$9:$H$153,"Not started") -> 6 | D11: =COUNTIFS(Checklist!$A$9:$A$153,$A11,Checklist!$H$9:$H$153,"In progress") -> 0 | E11: =COUNTIFS(Checklist!$A$9:$A$153,$A11,Checklist!$H$9:$H$153,"Done") -> 0 | F11: =COUNTIFS(Checklist!$A$9:$A$153,$A11,Checklist!$H$9:$H$153,"Blocked") -> 0 | G11: =SUMIFS(Checklist!$F$9:$F$153,Checklist!$A$9:$A$153,$A11) -> 0 | H11: =IF(B11=0,0,E11/B11) -> 0
A12: FCC | B12: =COUNTIF(Checklist!$A$9:$A$153,A12) -> 4 | C12: =COUNTIFS(Checklist!$A$9:$A$153,$A12,Checklist!$H$9:$H$153,"Not started") -> 4 | D12: =COUNTIFS(Checklist!$A$9:$A$153,$A12,Checklist!$H$9:$H$153,"In progress") -> 0 | E12: =COUNTIFS(Checklist!$A$9:$A$153,$A12,Checklist!$H$9:$H$153,"Done") -> 0 | F12: =COUNTIFS(Checklist!$A$9:$A$153,$A12,Checklist!$H$9:$H$153,"Blocked") -> 0 | G12: =SUMIFS(Checklist!$F$9:$F$153,Checklist!$A$9:$A$153,$A12) -> 1500 | H12: =IF(B12=0,0,E12/B12) -> 0
A13: Prop 65 | B13: =COUNTIF(Checklist!$A$9:$A$153,A13) -> 4 | C13: =COUNTIFS(Checklist!$A$9:$A$153,$A13,Checklist!$H$9:$H$153,"Not started") -> 4 | D13: =COUNTIFS(Checklist!$A$9:$A$153,$A13,Checklist!$H$9:$H$153,"In progress") -> 0 | E13: =COUNTIFS(Checklist!$A$9:$A$153,$A13,Checklist!$H$9:$H$153,"Done") -> 0 | F13: =COUNTIFS(Checklist!$A$9:$A$153,$A13,Checklist!$H$9:$H$153,"Blocked") -> 0 | G13: =SUMIFS(Checklist!$F$9:$F$153,Checklist!$A$9:$A$153,$A13) -> 0 | H13: =IF(B13=0,0,E13/B13) -> 0
A14: CL3 | B14: =COUNTIF(Checklist!$A$9:$A$153,A14) -> 3 | C14: =COUNTIFS(Checklist!$A$9:$A$153,$A14,Checklist!$H$9:$H$153,"Not started") -> 3 | D14: =COUNTIFS(Checklist!$A$9:$A$153,$A14,Checklist!$H$9:$H$153,"In progress") -> 0 | E14: =COUNTIFS(Checklist!$A$9:$A$153,$A14,Checklist!$H$9:$H$153,"Done") -> 0 | F14: =COUNTIFS(Checklist!$A$9:$A$153,$A14,Checklist!$H$9:$H$153,"Blocked") -> 0 | G14: =SUMIFS(Checklist!$F$9:$F$153,Checklist!$A$9:$A$153,$A14) -> 2000 | H14: =IF(B14=0,0,E14/B14) -> 0
A15: Insurance | B15: =COUNTIF(Checklist!$A$9:$A$153,A15) -> 5 | C15: =COUNTIFS(Checklist!$A$9:$A$153,$A15,Checklist!$H$9:$H$153,"Not started") -> 5 | D15: =COUNTIFS(Checklist!$A$9:$A$153,$A15,Checklist!$H$9:$H$153,"In progress") -> 0 | E15: =COUNTIFS(Checklist!$A$9:$A$153,$A15,Checklist!$H$9:$H$153,"Done") -> 0 | F15: =COUNTIFS(Checklist!$A$9:$A$153,$A15,Checklist!$H$9:$H$153,"Blocked") -> 0 | G15: =SUMIFS(Checklist!$F$9:$F$153,Checklist!$A$9:$A$153,$A15) -> 1500 | H15: =IF(B15=0,0,E15/B15) -> 0
A16: Customs | B16: =COUNTIF(Checklist!$A$9:$A$153,A16) -> 12 | C16: =COUNTIFS(Checklist!$A$9:$A$153,$A16,Checklist!$H$9:$H$153,"Not started") -> 12 | D16: =COUNTIFS(Checklist!$A$9:$A$153,$A16,Checklist!$H$9:$H$153,"In progress") -> 0 | E16: =COUNTIFS(Checklist!$A$9:$A$153,$A16,Checklist!$H$9:$H$153,"Done") -> 0 | F16: =COUNTIFS(Checklist!$A$9:$A$153,$A16,Checklist!$H$9:$H$153,"Blocked") -> 0 | G16: =SUMIFS(Checklist!$F$9:$F$153,Checklist!$A$9:$A$153,$A16) -> 1950 | H16: =IF(B16=0,0,E16/B16) -> 0
... A18: Data and privacy (placeholder) | B18: =COUNTIF(Checklist!$A$9:$A$153,A18) -> 5 | C18: =COUNTIFS(Checklist!$A$9:$A$153,$A18,Checklist!$H$9:$H$153,"Not started") -> 5 | D18: =COUNTIFS(Checklist!$A$9:$A$153,$A18,Checklist!$H$9:$H$153,"In progress") -> 0 | E18: =COUNTIFS(Checklist!$A$9:$A$153,$A18,Checklist!$H$9:$H$153,"Done") -> 0 | F18: =COUNTIFS(Checklist!$A$9:$A$153,$A18,Checklist!$H$9:$H$153,"Blocked") -> 0 | G18: =SUMIFS(Checklist!$F$9:$F$153,Checklist!$A$9:$A$153,$A18) -> 560 | H18: =IF(B18=0,0,E18/B18) -> 0
A19: Total | B19: =SUM(B5:B18) -> 105 | C19: =SUM(C5:C18) -> 105 | D19: =SUM(D5:D18) -> 0 | E19: =SUM(E5:E18) -> 0 | F19: =SUM(F5:F18) -> 0 | G19: =SUM(G5:G18) -> 13514.88 | H19: =IF(B19=0,0,E19/B19) -> 0
A20: Check: area totals equal the Checklist item count (0 = ok) | B20: =B19-COUNTA(Checklist!$A$9:$A$153) -> 0
A22: By status | B22: Items | C22: Share
A23: Not started | B23: =COUNTIF(Checklist!$H$9:$H$153,A23) -> 105 | C23: =IF($B$19=0,0,B23/$B$19) -> 1
A24: In progress | B24: =COUNTIF(Checklist!$H$9:$H$153,A24) -> 0 | C24: =IF($B$19=0,0,B24/$B$19) -> 0
A25: Done | B25: =COUNTIF(Checklist!$H$9:$H$153,A25) -> 0 | C25: =IF($B$19=0,0,B25/$B$19) -> 0
A26: Blocked | B26: =COUNTIF(Checklist!$H$9:$H$153,A26) -> 0 | C26: =IF($B$19=0,0,B26/$B$19) -> 0
A28: By owner (an item with two owners counts under each) | B28: Items | C28: Open (not Done)
A29: Lucy | B29: =COUNTIF(Checklist!$D$9:$D$153,"*Lucy*") -> 61 | C29: =COUNTIFS(Checklist!$D$9:$D$153,"*Lucy*",Checklist!$H$9:$H$153,"<>Done") -> 61
A30: Mark | B30: =COUNTIF(Checklist!$D$9:$D$153,"*Mark*") -> 44 | C30: =COUNTIFS(Checklist!$D$9:$D$153,"*Mark*",Checklist!$H$9:$H$153,"<>Done") -> 44
A31: 세무사 | B31: =COUNTIF(Checklist!$D$9:$D$153,"*세무사*") -> 11 | C31: =COUNTIFS(Checklist!$D$9:$D$153,"*세무사*",Checklist!$H$9:$H$153,"<>Done") -> 11
A32: CPA | B32: =COUNTIF(Checklist!$D$9:$D$153,"*CPA*") -> 10 | C32: =COUNTIFS(Checklist!$D$9:$D$153,"*CPA*",Checklist!$H$9:$H$153,"<>Done") -> 10
A33: Attorney | B33: =COUNTIF(Checklist!$D$9:$D$153,"*attorney*") -> 16 | C33: =COUNTIFS(Checklist!$D$9:$D$153,"*attorney*",Checklist!$H$9:$H$153,"<>Done") -> 16
A34: Broker | B34: =COUNTIF(Checklist!$D$9:$D$153,"*broker*") -> 12 | C34: =COUNTIFS(Checklist!$D$9:$D$153,"*broker*",Checklist!$H$9:$H$153,"<>Done") -> 12
A35: Factory | B35: =COUNTIF(Checklist!$D$9:$D$153,"*factory*") -> 20 | C35: =COUNTIFS(Checklist!$D$9:$D$153,"*factory*",Checklist!$H$9:$H$153,"<>Done") -> 20
A36: 3PL | B36: =COUNTIF(Checklist!$D$9:$D$153,"*3PL*") -> 2 | C36: =COUNTIFS(Checklist!$D$9:$D$153,"*3PL*",Checklist!$H$9:$H$153,"<>Done") -> 2
A37: VA | B37: =COUNTIF(Checklist!$D$9:$D$153,"*VA*") -> 2 | C37: =COUNTIFS(Checklist!$D$9:$D$153,"*VA*",Checklist!$H$9:$H$153,"<>Done") -> 2
A38: Registered agent | B38: =COUNTIF(Checklist!$D$9:$D$153,"*registered agent*") -> 1 | C38: =COUNTIFS(Checklist!$D$9:$D$153,"*registered agent*",Checklist!$H$9:$H$153,"<>Done") -> 1
A39: QC agency | B39: =COUNTIF(Checklist!$D$9:$D$153,"*QC agency*") -> 1 | C39: =COUNTIFS(Checklist!$D$9:$D$153,"*QC agency*",Checklist!$H$9:$H$153,"<>Done") -> 1
A41: By basis | B41: Items | C41: Estimated cost
A42: Evidence based | B42: =COUNTIF(Checklist!$J$9:$J$153,A42) -> 56 | C42: =SUMIFS(Checklist!$F$9:$F$153,Checklist!$J$9:$J$153,A42) -> 4039.88
A43: Management estimate | B43: =COUNTIF(Checklist!$J$9:$J$153,A43) -> 49 | C43: =SUMIFS(Checklist!$F$9:$F$153,Checklist!$J$9:$J$153,A43) -> 9475
A45: Items with an open placeholder in Notes or Evidence | B45: =COUNTIF(Checklist!$I$9:$I$153,"*PLACEHOLDER*")+COUNTIFS(Checklist!$G$9:$G$153,"*PLACEHOLDER*",Checklist!$I$9:$I$153,"<>*PLACEHOLDER*") -> 54
A46: Hard stop items (ODI before capital, HDMI and FCC documents before the PO, CL3 before the in wall claim) not Done | B46: =COUNTIFS(Checklist!$B$9:$B$153,"*before any capital moves*",Checklist!$H$9:$H$153,"<>Done")+COUNTIFS(Checklist!$B$9:$B$153,"*HDMI Adopter*",Checklist!$H$9:$H$153,"<>Done")+COUNTIFS(Checklist!$B$9:$B$153,"*FCC test report for the active heads*",Checklist!$H$9:$H$153,"<>Done")+COUNTIFS(Checklist!$B$9:$B$153,"*CL3 documentation from the factory*",Checklist!$H$9:$H$153,"<>Done") -> 4
